Workbook
Name NativeTimeline_List_Date: #N/A
Name Slicer_FROM_1000_1500: #N/A
Name Slicer_FROM_1500_2000: #N/A
Name Slicer_GRP_BY_50: #N/A
Name Slicer_GRP_BY_50IN_500: #N/A
Name Slicer_grp_by_Listing: #N/A
Name Slicer_grp_by_Listing1: #N/A
Name Slicer_grp_by_Listing2: #N/A
Name Slicer_Grp_by_total: #N/A
Name Slicer_Grp_by_total1: #N/A
Name Slicer_Grp_by_total2: #N/A
Name Slicer_IPO_NAME: #N/A
Name Slicer_Postive: #N/A
Name Slicer_Size_grp: #N/A
Name Slicer_Size_grp2: #N/A
Name Slicer_Size_grp21: #N/A
Name Slicer_Year: #N/A
Name Slicer_Year1: #N/A

Sheet Total_vs_Gains
A3: IPO NAME | B3: Total SuCcription | C3: Sum of Listing Gains(%) | D3: Gains(%) | E3: Count of IPO NAME | H3: =GETPIVOTDATA("Count of IPO NAME",Total_vs_Gains!$A$3) -> 6
A4: Borana Weaves Ltd | B4: 148.78 | C4: 12.5 | D4: 12.5 | E4: 1 | R4: Row Labels | S4: Sum of Issue size divide by 10 | T4: Sum of Listing Gains(%) | U4: Count of First name
A5: Exicom Tele-System | B5: 129.54 | C5: 85.92 | D5: 85.92 | E5: 1 | G5: {=MAX(0, SUMPRODUCT( SUBTOTAL(103, OFFSET(Total_vs_Gains!$C$4, ROW($C$4:$C$306)-ROW(Total_vs_Gains!$C$4), 0, 1)) * --(ISNUMBER($C$4:$C$306)) * --($C$4:$C$306 > 0) ) ) - 1} -> 6 | R5: Uma Exports Ltd | S5: 6 | T5: 17.65 | U5: 1
A6: GNG Electronics Lt | B6: 147.93 | C6: 47.68 | D6: 47.68 | E6: 1 | R6: Udayshivakumar Inf | S6: 6.6 | T6: 0 | U6: 1
A7: Go Fashion (India) | B7: 135.46 | C7: 90.72 | D7: 90.72 | E7: 1 | R7: Sah Polymers Ltd | S7: 6.63 | T7: 30.77 | U7: 1
A8: Mukka Proteins Ltd | B8: 136.99 | C8: 57.14 | D8: 57.14 | E8: 1 | R8: Plaza Wires Ltd | S8: 7.128 | T8: 55.56 | U8: 1
A9: Rolex Rings Ltd | B9: 130.44 | C9: 38.78 | D9: 38.78 | E9: 1 | R9: Vibhor Steel Tubes | S9: 7.217 | T9: 178.81 | U9: 1
A10: Grand Total | B10: 829.14 | C10: 332.74 | D10: 332.74 | E10: 6 | H10: Z | R10: Nureca Ltd | S10: 10 | T10: 58.74 | U10: 1
R11: RBZ Jewellers Ltd | S11: 10 | T11: 0 | U11: 1
R12: Globe Civil Projec | S12: 11.9 | T12: 28.31 | U12: 1
R13: Sigachi Industries | S13: 12.543 | T13: 252.76 | U13: 1
R14: HP Adhesives Ltd | S14: 12.596 | T14: 16.42 | U14: 1
R15: Highway Infrastruc | S15: 13 | T15: 67.14 | U15: 1
R16: Hariom Pipe Indust | S16: 13.005 | T16: 39.87 | U16: 1
R17: Kronox Lab Science | S17: 13.015 | T17: 21.32 | U17: 1
R18: SRM Contractors Lt | S18: 13.02 | T18: 7.14 | U18: 1
R19: Akme Fintrade (Ind | S19: 13.2 | T19: 4.75 | U19: 1
R20: Nova Agritech Ltd | S20: 14.381 | T20: 36.59 | U20: 1
R21: Borana Weaves Ltd | S21: 14.489 | T21: 12.5 | U21: 1
R22: Manba Finance Ltd | S22: 15.084 | T22: 25 | U22: 1
... R36: Vraj Iron & Steel | S36: 17.1 | T36: 15.94 | U36: 1
R37: Mamata Machinery L | S37: 17.935 | T37: 146.91 | U37: 1 | X37: POSITIVE AGINS | Z37: NEGATIVE GAINS | AB37: NO GAINS
J38: NEGATVE GAINS | K38: NEUTRAL AGAIN | R38: Stallion India Flu | S38: 19.945 | T38: 33.33 | U38: 1 | Z38: {=MAX(0, SUMPRODUCT( SUBTOTAL(103,OFFSET($T$4,ROW($C$4:$T$306)-ROW($T$4),0,1))* --(ISNUMBER($T$4:$T$306))* --($T$4:$T$306<0) ))} -> 11 | AB38: {=MAX(0, SUMPRODUCT( SUBTOTAL(103,OFFSET($T$4,ROW($T$4:$T$306)-ROW($T$4),0,1))* --(ISNUMBER($T$4:$T$306))* --($T$4:$T$306=0) ))} -> 7
J39: {=MAX(0, SUMPRODUCT( SUBTOTAL(103,OFFSET(Total_vs_Gains!$C$4,ROW($C$4:$C$306)-ROW(Total_vs_Gains!$C$4),0,1))* --(ISNUMBER($C$4:$C$306))* --($C$4:$C$306<0) ))} -> 0 | K39: {=MAX(0, SUMPRODUCT( SUBTOTAL(103, OFFSET(Total_vs_Gains!$C$4, ROW($C$4:$C$306)-ROW(Total_vs_Gains!$C$4), 0, 1)) * --(ISNUMBER($C$4:$C$306)) * --($C$4:$C$306 = 0) ) )} -> 0 | R39: Veranda Learning S | S39: 20 | T39: 14.6 | U39: 1
R40: Indogulf Cropscien | S40: 20 | T40: 0 | U40: 1
K41: Average | R41: Orient Technologie | S41: 21.476 | T41: 40.78 | U41: 1 | Y41: Average gains
R42: Scoda Tubes Ltd | S42: 22 | T42: 0 | U42: 1 | Y42: =GETPIVOTDATA("Sum of Listing Gains(%)",$R$4)/GETPIVOTDATA("Count of First name",$R$4) -> 31.582706
K43: =(GETPIVOTDATA("Gains(%)",Total_vs_Gains!$A$3)/GETPIVOTDATA("Count of IPO NAME",Total_vs_Gains!$A$3)) -> 55.456667 | R43: Denta Water & Infr | S43: 22.05 | T43: 12.24 | U43: 1
R44: Mukka Proteins Ltd | S44: 22.4 | T44: 57.14 | U44: 1
R45: Tolins Tyres Ltd | S45: 23 | T45: 0.44 | U45: 1
R46: Platinum Industrie | S46: 23.532 | T46: 33.33 | U46: 1
R47: Dharmaj Crop Guard | S47: 25.109 | T47: 12.24 | U47: 1
R48: J.G.Chemicals Ltd | S48: 25.119 | T48: -4.52 | U48: 1
R49: Laxmi India Financ | S49: 25.426 | T49: -13.92 | U49: 1
R50: Radiant Cash Manag | S50: 25.664 | T50: 5.64 | U50: 1
R51: Deepak Builders & | S51: 26.004 | T51: -2.22 | U51: 1
R52: Indo Farm Equipmen | S52: 26.015 | T52: 20.19 | U52: 1
R53: Garuda Constructio | S53: 26.41 | T53: 8.63 | U53: 1
R54: Manoj Vaibhav Gems | S54: 27.02 | T54: 0 | U54: 1
R55: Unicommerce eSolut | S55: 27.657 | T55: 112.96 | U55: 1
... R90: Grand Total | S90: 2221.921 | T90: 2684.53 | U90: 85

Sheet DASHBOARD(ISSUE SIZE)
B2: IPO DATASET
J4: =Total_vs_Gains!J39 -> 0
V12: Row Labels | W12: Sum of Issue size divide by 10 | X12: Sum of Listing Gains(%) | Y12: Count of First name
V13: Abans Financial Se | W13: 34.56 | X13: 0 | Y13: 1
V14: Aeroflex Industrie | W14: 35.1 | X14: 82.78 | Y14: 1
V15: Akme Fintrade (Ind | W15: 13.2 | X15: 4.75 | Y15: 1
K16: postive | L16: NEGATIVE | N16: NEUTRAL | Q16: Average gains | V16: All Time Plastics | W16: 40.06 | X16: 14.29 | Y16: 1
K17: {=MAX(0, SUMPRODUCT( SUBTOTAL(103, OFFSET($X$13, ROW($X$13:$X$320)-ROW($X$13), 0, 1)) * --(ISNUMBER($X$13:$X$320)) * --($X$13:$X$320 > 0) ) ) - 1} -> 67 | L17: {=MAX(0, SUMPRODUCT( SUBTOTAL(103, OFFSET($X$13, ROW($X$13:$X$320)-ROW($X$13), 0, 1)) * --(ISNUMBER($X$13:$X$320)) * --($X$13:$X$320 < 0) ) )} -> 11 | N17: {=MAX(0, SUMPRODUCT( SUBTOTAL(103, OFFSET($X$13, ROW($X$13:$X$320)-ROW($X$13), 0, 1)) * --(ISNUMBER($X$13:$X$320)) * --($X$13:$X$320 = 0) ) )} -> 7 | Q17: =GETPIVOTDATA("Sum of Listing Gains(%)",$V$12)/GETPIVOTDATA("Count of First name",$V$12) -> 31.582706 | V17: Antony Waste Handl | W17: 29.999 | X17: 36.51 | Y17: 1
V18: Arisinfra Solution | W18: 49.96 | X18: -5.81 | Y18: 1
V19: Arkade Developers | W19: 41 | X19: 37.42 | Y19: 1
V20: Barbeque-Nation Ho | W20: 45.287 | X20: -1.6 | Y20: 1
V21: BLS E-Services Ltd | W21: 30.929 | X21: 128.89 | Y21: 1
V22: Borana Weaves Ltd | W22: 14.489 | X22: 12.5 | Y22: 1
V23: DEE Development En | W23: 41.801 | X23: 60.1 | Y23: 1
V24: Deepak Builders & | W24: 26.004 | X24: -2.22 | Y24: 1
V25: Denta Water & Infr | W25: 22.05 | X25: 12.24 | Y25: 1
V26: Dharmaj Crop Guard | W26: 25.109 | X26: 12.24 | Y26: 1
V27: Diffusion Engineer | W27: 15.796 | X27: 11.9 | Y27: 1
V28: Divgi Torqtransfer | W28: 41.212 | X28: 1.69 | Y28: 1
V29: Elin Electronics L | W29: 47.5 | X29: -1.62 | Y29: 1
... V98: Grand Total | W98: 2221.921 | X98: 2684.53 | Y98: 85

Sheet DASHBOARD(SUB)
B2: IPO DATASET
J4: =Total_vs_Gains!J39 -> 0
V11: IPO NAME | W11: Total SuCcription | X11: Sum of Listing Gains(%) | Y11: Gains(%) | Z11: Count of IPO NAME
V12: Borana Weaves Ltd | W12: 148.78 | X12: 12.5 | Y12: 12.5 | Z12: 1
V13: Exicom Tele-System | W13: 129.54 | X13: 85.92 | Y13: 85.92 | Z13: 1
V14: GNG Electronics Lt | W14: 147.93 | X14: 47.68 | Y14: 47.68 | Z14: 1
V15: Go Fashion (India) | W15: 135.46 | X15: 90.72 | Y15: 90.72 | Z15: 1
V16: Mukka Proteins Ltd | W16: 136.99 | X16: 57.14 | Y16: 57.14 | Z16: 1
V17: Rolex Rings Ltd | W17: 130.44 | X17: 38.78 | Y17: 38.78 | Z17: 1
V18: Grand Total | W18: 829.14 | X18: 332.74 | Y18: 332.74 | Z18: 6

Sheet ALL DATA 
G2: ISSUE SIZE | H2: NO COM | I2: SUM OF GAINS | J2: AVERGAE GAINS | L2: ISSUE SIZE | M2: NO COM | N2: SUM OF GAINS | O2: AVERGAE GAINS | Q2: ISSUE SIZE | R2: NO COM | S2: SUM OF GAINS | T2: AVERGAE GAINS | V2: ISSUE SIZE | W2: NO COM | X2: SUM OF GAINS | Y2: AVERGAE GAINS | AC2: ISSUE | AD2: AVERAGE GAINS | AE2: 2021 AVERAGE GAIN | AF2: 2022 | AG2: 23 | AH2: 24 | AI2: 25
A3: GRP BY 50IN 500 | B3: Grp by total | C3: Count of Listing Gains(%) | D3: Sum of Listing Gains(%) | E3: Count of IPO NAME | G3: 50-100 | H3: 5 | I3: 282.79 | J3: =I3/H3 -> 56.558 | L3: 500-550 | M3: 18 | N3: 552.54 | O3: =N3/M3 -> 30.696667 | Q3: 1000-1050 | R3: 6 | S3: 223.53 | T3: =S3/R3 -> 37.255 | V3: 1500-1550 | W3: 6 | X3: 118.71 | Y3: =X3/W3 -> 19.785 | AC3: 0-500 | AD3: 31.5 | AE3: 61.77 | AF3: 8.96 | AG3: 23.7 | AH3: 42.7 | AI3: 20.22
A4: 500-550 | B4: 0 to 5 | C4: 2 | D4: -2.29 | E4: 2 | G4: 100-150 | H4: 12 | I4: 545.54 | J4: =I4/H4 -> 45.461667 | L4: 550-600 | M4: 19 | N4: 660.1 | O4: =N4/M4 -> 34.742105 | Q4: 1050-1100 | R4: 1 | S4: -1.61 | T4: =S4/R4 -> -1.61 | V4: 1550-1600 | W4: 6 | X4: 59.77 | Y4: =X4/W4 -> 9.9616667 | AC4: 500-1000 | AD4: 24.7 | AE4: 39.5 | AF4: 15.09 | AG4: 25.1 | AH4: 22.8 | AI4: 10.6
B5: 10 to 15 | C5: 1 | D5: 18.69 | E5: 1 | G5: 150-200 | H5: 17 | I5: 672.43 | J5: =I5/H5 -> 39.554706 | L5: 600-650 | M5: 15 | N5: 521.43 | O5: =N5/M5 -> 34.762 | Q5: 1100-1150 | R5: 4 | S5: 75.09 | T5: =S5/R5 -> 18.7725 | V5: 1600-1650 | W5: 2 | X5: 10.66 | Y5: =X5/W5 -> 5.33 | AC5: 1000-1500 | AD5: 18.9 | AE5: 18.5 | AF5: 9.9 | AG5: 26.27 | AH5: 16.05 | AI5: 16
B6: 100 to 125 | C6: 1 | D6: 59.8 | E6: 1 | G6: 200-250 | H6: 8 | I6: 158.53 | J6: =I6/H6 -> 19.81625 | L6: 650-700 | M6: 7 | N6: 69.56 | O6: =N6/M6 -> 9.9371429 | Q6: 1150-1200 | R6: 4 | S6: 89.36 | T6: =S6/R6 -> 22.34 | V6: 1700-1750 | W6: 1 | X6: 0 | Y6: =X6/W6 -> 0 | AC6: 1500-2000 | AD6: 16.28 | AE6: 40.3 | AF6: -1.8 | AG6: 15.9 | AH6: 19.7 | AI6: -0.5
B7: 15 to 20 | C7: 1 | D7: 0 | E7: 1 | G7: 250-300 | H7: 11 | I7: 204.48 | J7: =I7/H7 -> 18.589091 | L7: 700-750 | M7: 8 | N7: 213.01 | O7: =N7/M7 -> 26.62625 | Q7: 1200-1250 | R7: 5 | S7: 107.56 | T7: =S7/R7 -> 21.512 | V7: 1800-1850 | W7: 3 | X7: 102.95 | Y7: =X7/W7 -> 34.316667 | AC7: 2000-2500 | AD7: 17.02 | AE7: 16.69 | AF7: 18.5 | AG7: 56.25 | AH7: 12.5 | AI7: 5.91
B8: 150 to 175 | C8: 1 | D8: 10.16 | E8: 1 | G8: 300-350 | H8: 8 | I8: 394.88 | J8: =I8/H8 -> 49.36 | L8: 750-800 | M8: 6 | N8: 66.41 | O8: =N8/M8 -> 11.068333 | Q8: 1250-1300 | R8: 4 | S8: 0.07 | T8: =S8/R8 -> 0.0175 | V8: 1850-1900 | W8: 2 | X8: 8.9 | Y8: =X8/W8 -> 4.45 | AC8: 2500-3000 | AD8: 11.124 | AE8: -4 | AF8: 0 | AG8: 20 | AH8: 37 | AI8: -2.4 | BQ8: TOATL SUB | BR8: 0-5 | BS8: 5-10 | BT8: 10-15 | BU8: 15-20 | BV8: 20-25 | BW8: 25-50 | BX8: 50-75 | BY8: 75-100 | BZ8: 100-125 | CA8: 125-150 | CB8: 150-175 | CC8: 175-200 | CD8: >200
B9: 175 to 200 | C9: 2 | D9: 184.94 | E9: 2 | G9: 350-400 | H9: 2 | I9: 97.91 | J9: =I9/H9 -> 48.955 | L9: 800-850 | M9: 14 | N9: 137.37 | O9: =N9/M9 -> 9.8121429 | Q9: 1300-1350 | R9: 2 | S9: 36.65 | T9: =S9/R9 -> 18.325 | V9: 1900-1950 | W9: 1 | X9: 28.24 | Y9: =X9/W9 -> 28.24 | AC9: 3000-3500 | AD9: 27.99 | AE9: 0 | AF9: 8.08 | AG9: 71.13 | AH9: 10 | AI9: 12.7 | BQ9: WITHOUT OULINERS | BR9: -1.0365 | BS9: 5.0388 | BT9: 9.235 | BU9: 4.13 | BV9: 6.56 | BW9: 23.046875 | BX9: 40.151 | BY9: 38.553333 | BZ9: 51.866667 | CA9: 50.81 | CB9: 77.68 | CC9: 73.355 | CD9: 92.768 | DJ9: AVERGAE LISTING AGINS
B10: 25 to 50 | C10: 3 | D10: 52.48 | E10: 3 | G10: 400-450 | H10: 13 | I10: 261.21 | J10: =I10/H10 -> 20.093077 | L10: 850-900 | M10: 8 | N10: 112.21 | O10: =N10/M10 -> 14.02625 | Q10: 1350-1400 | R10: 5 | S10: 42.83 | T10: =S10/R10 -> 8.566 | V10: 1950-2000 | W10: 2 | X10: 45.36 | Y10: =X10/W10 -> 22.68 | AC10: 3500-4000 | AD10: -1.8 | AE10: -1.42 | AF10: -3.41 | AG10: 0 | AH10: 0 | AI10: -1.7 | BQ10: WITH OUTLINERS | BR10: 1.855 | BS10: 4.6855 | BT10: 13.348333 | BU10: 7.3825 | BV10: 10.67 | BW10: 22.727222 | BX10: 59.325625 | BY10: 52.198333 | BZ10: 51.866667 | CA10: 60.103333 | CB10: 46.963333 | CC10: 73.355 | CD10: 92.768 | DH10: AVERGAE LISTING GAINS | DI10: 2021 | DJ10: 2022 | DK10: 2023 | DL10: 2024 | DM10: 2025
B11: 5 to 10 | C11: 2 | D11: 51.44 | E11: 2 | G11: 450-500 | H11: 9 | I11: 66.76 | J11: =I11/H11 -> 7.4177778 | L11: 900-950 | M11: 2 | N11: 40.58 | O11: =N11/M11 -> 20.29 | Q11: 1450-1500 | R11: 2 | S11: 51.71 | T11: =S11/R11 -> 25.855 | AC11: 4000-4500 | AD11: 31.25 | AE11: 0 | AF11: 30.7 | AG11: 20 | AH11: 39.4 | AI11: 10 | BQ11: DIFFERENCE | BR11: =BR9-BR10 -> -2.8915 | BS11: =BS9-BS10 -> 0.3533 | BT11: =BT9-BT10 -> -4.1133333 | BU11: =BU9-BU10 -> -3.2525 | BV11: =BV9-BV10 -> -4.11 | BW11: =BW9-BW10 -> 0.31965278 | BX11: =BX9-BX10 -> -19.174625 | BY11: =BY9-BY10 -> -13.645 | ... CD11: =CD9-CD10 -> 0 | DG11: 0-5 | DH11: -0.2 | DI11: -3.8 | DJ11: 4.66 | DK11: 1 | DL11: -1.6 | DM11: -2.7
B12: 50 to 75 | C12: 4 | D12: 165.32 | E12: 4 | L12: 950-1000 | M12: 3 | N12: 98.92 | O12: =N12/M12 -> 32.973333 | AC12: 4500-5000 | AD12: -5.74 | AE12: -10.61 | AF12: 0 | AG12: 0 | AH12: 0 | AI12: 4 | DG12: 5-10 | DH12: 5.3 | DI12: 5.7 | DJ12: 3.7 | DK12: 2.33 | DL12: 9.06 | DM12: 4.2
B13: 75 to 100 | C13: 1 | D13: 12 | E13: 1 | AC13: >5000 | AD13: 16.48 | AE13: 19.95 | AF13: -3.6 | AG13: 0 | AH13: 20.5 | AI13: 8 | CI13: Issue Size | CJ13: With outliners | CK13: Without outliners | DG13: 10-15 | DH13: 9.77 | DI13: 0 | DK13: 6.5 | DL13: 17.5 | DM13: 1.14
A14: 500-550 Total | C14: 18 | D14: 552.54 | E14: 18 | CI14: 0-500 | CJ14: 32.613 | CK14: 32.613 | CL14: DIFFERENCE | DG14: 15-20 | DH14: 10.1 | DI14: 10.8 | DJ14: 7.5 | DK14: 15 | DL14: 1.18 | DM14: 12.84
A15: 550-600 | B15: > 200 | C15: 1 | D15: 85.03 | E15: 1 | CI15: 500-1000 | CJ15: 32.289692 | CK15: 34.7826 | CL15: =CK15-CJ15 -> 2.4929077 | DG15: 20-25 | DH15: 8.2 | DI15: 3.9 | DK15: 10.7 | DL15: 6.8 | DM15: 23
B16: 0 to 5 | C16: 3 | D16: -22.57 | E16: 3 | Q16: TOTAL SUB | AE16: POSTIVE | AF16: NEGATIVE | AG16: NO GAINS | CI16: 1000-1500 | CJ16: 29.25 | CK16: 20.82 | CL16: =CK16-CJ16 -> -8.43 | DF16: TOTAL SUB | DG16: 25-50 | DH16: 18.95 | DI16: 31.4 | DJ16: 16.77 | DK16: 21.1 | DL16: 13.86 | DM16: 9.4
B17: 10 to 15 | C17: 2 | D17: 5.93 | E17: 2 | L17: 0-5 | M17: 5-10 | N17: 10-15 | O17: 15-20 | P17: 20-25 | Q17: 25-50 | R17: 50-75 | S17: 75-100 | T17: 100-125 | U17: 125-150 | V17: 150-175 | W17: 175-200 | X17: >200 | AE17: 67 | AF17: 11 | AG17: 7 | CI17: 1500-2000 | CJ17: 22.061429 | CK17: 22.23 | CL17: =CK17-CJ17 -> 0.16857143 | DG17: 50-75 | DH17: 40.32 | DI17: 48.3 | DJ17: 48.2 | DK17: 40.46 | DL17: 43.3 | DM17: 15.13
B18: 100 to 125 | C18: 4 | D18: 213.27 | E18: 4 | K18: 0-500 | L18: 5.5 | M18: 5.154 | N18: 13.81 | O18: 18.42 | P18: 3.45 | Q18: 6.98 | R18: 15.135 | S18: 37.93 | T18: 51.6 | U18: 50.81 | V18: 77.68 | W18: 58.73 | X18: 78.77 | Z18: =AVERAGE(L18:X18) -> 32.613 | AE18: 74 | AF18: 23 | AG18: 3 | CI18: 2000-2500 | CJ18: 18.032 | CK18: 12.6275 | CL18: =CK18-CJ18 -> -5.4045 | DG18: 75-100 | DH18: 43.25 | DI18: 42.3 | DK18: 56.76 | DL18: 41.19 | DM18: 20.83
B19: 15 to 20 | C19: 1 | D19: -4.35 | E19: 1 | K19: 500-1000 | L19: -3 | M19: 8.79 | N19: 4.66 | O19: 3.14 | P19: 23 | Q19: 18.87 | R19: 35.37 | S19: 44.15 | T19: 41.1 | U19: 38.78 | V19: 10.16 | W19: 87.98 | X19: 106.766 | Z19: =AVERAGE(L19:X19) -> 32.289692 | AE19: 25 | AF19: 8 | AG19: 6 | CI19: 2500-3000 | CJ19: 25.814 | CK19: -6.35 | CL19: =CK19-CJ19 -> -32.164 | DG19: 100-125 | DH19: 48.26 | DI19: 78.7 | DK19: 77 | DL19: 26.49 | DM19: 37.085
B20: 175 to 200 | C20: 1 | D20: 79.02 | E20: 1 | K20: 1000-1500 | L20: -2 | M20: -1 | N20: 2.99 | O20: -1.46 | Q20: 14.94 | R20: 38.78 | S20: 33.58 | T20: 62.9 | U20: 90.72 | V20: 53.05 | Z20: =AVERAGE(L20:X20) -> 29.25 | AE20: 17 | AF20: 4 | AG20: 2 | CI20: 3000-3500 | CJ20: 17.43 | CK20: 16.872 | CL20: =CK20-CJ20 -> -0.558 | DG20: 125-150 | DH20: 55.4 | DI20: 64.9 | DL20: 71.53 | DM20: 30.09
B21: 25 to 50 | C21: 2 | D21: 96.02 | E21: 2 | K21: 1500-2000 | L21: -0.07 | M21: 1.6 | O21: 13.91 | P21: 17.33 | Q21: 43.61 | R21: 28.05 | S21: 50 | Z21: =AVERAGE(L21:X21) -> 22.061429 | AE21: 10 | AF21: 0 | AG21: 0 | CI21: 3500-4000 | CJ21: -4.7 | CK21: -4.7 | CL21: =CK21-CJ21 -> 0 | DG21: 150-175 | DH21: 66.16 | DI21: 31.6 | DK21: 72.23 | DL21: 94.21
B22: 50 to 75 | C22: 4 | D22: 155.91 | E22: 4 | J22: ISSUE SIZE | K22: 2000-2500 | L22: 8.57 | M22: 10.2 | P22: -1.1 | Q22: 32.84 | R22: 39.65 | Z22: =AVERAGE(L22:X22) -> 18.032 | AE22: 4 | AF22: 5 | AG22: 1 | CI22: 4000-4500 | CJ22: 26.6825 | CK22: 21.18 | CL22: =CK22-CJ22 -> -5.5025 | DG22: 175-200 | DH22: 71.26 | DI22: 87.01 | DL22: 118 | DM22: 29.33
B23: 75 to 100 | C23: 1 | D23: 51.84 | E23: 1 | K23: 2500-3000 | L23: -6.2 | M23: 1.6 | O23: -6.5 | Q23: 20.17 | R23: 120 | Z23: =AVERAGE(L23:X23) -> 25.814 | AE23: 5 | AF23: 2 | AG23: 0 | CI23: 4500-5000 | CJ23: 21.02 | CK23: -10.6 | CL23: =CK23-CJ23 -> -31.62 | DG23: >200 | DH23: 86.4 | DI23: 122.9 | DL23: 89.8 | DM23: 33.19
A24: 550-600 Total | C24: 19 | D24: 660.1 | E24: 19 | K24: 3000-3500 | L24: 3.02 | M24: 2.05 | N24: 20.22 | O24: -3.91 | Q24: -0.22 | R24: 83.42 | Z24: =AVERAGE(L24:X24) -> 17.43 | AE24: 1 | AF24: 4 | AG24: 0 | BL24: =AVERAGE(Z48:Z58) -> 14.509252 | CI24: >5000 | CJ24: 43.59 | CK24: 20.126667 | CL24: =CK24-CJ24 -> -23.463333
A25: 600-650 | B25: > 200 | C25: 2 | D25: 235.27 | E25: 2 | K25: 3500-4000 | L25: -4.7 | Z25: =AVERAGE(L25:X25) -> -4.7 | AE25: 7 | AF25: 0 | AG25: 0
B26: 0 to 5 | C26: 4 | D26: -18.8 | E26: 4 | K26: 4000-4500 | L26: 30.77 | N26: 34.41 | O26: 20.37 | Q26: 21.18 | Z26: =AVERAGE(L26:X26) -> 26.6825 | AE26: 0 | AF26: 3 | AG26: 0 | CI26: AVE | CJ26: =AVERAGE(CJ14:CJ24) -> 24.007511 | CK26: =AVERAGE(CK14:CK24) -> 14.509252
B27: 100 to 125 | C27: 1 | D27: 20.15 | E27: 1 | K27: 4500-5000 | L27: -10.6 | N27: 4 | S27: 69.66 | Z27: =AVERAGE(L27:X27) -> 21.02 | AE27: 13 | AF27: 6 | AG27: 0 | CI27: SD | CJ27: =_xlfn.STDEV.P(CJ15:CJ24) -> 11.825268 | CK27: =_xlfn.STDEV.P(CK15:CK24) -> 14.133031 | DJ27: POSTIVE GAINS | DK27: NEGATIVE GAINS | DL27: NEUTRAL GAINS
B28: 15 to 20 | C28: 1 | D28: -2.17 | E28: 1 | K28: >5000 | L28: -0.885 | M28: 9.09 | O28: 15.09 | Q28: 46.175 | R28: 114.2 | S28: 77.87 | Z28: =AVERAGE(L28:X28) -> 43.59 | DJ28: 5 | DK28: 14 | DL28: 0
B29: 25 to 50 | C29: 1 | D29: 49.4 | E29: 1 | BQ29: QIB GRP | BR29: NO COM | BS29: SUM GAINS | BT29: AVERAGE GAINS | DJ29: 18 | DK29: 4 | DL29: 2
B30: 50 to 75 | C30: 3 | D30: 62.07 | E30: 3 | L30: =AVERAGE(L18:L28) -> 1.855 | M30: =AVERAGE(M18:M28) -> 4.6855 | N30: =AVERAGE(N18:N28) -> 13.348333 | O30: =AVERAGE(O18:O28) -> 7.3825 | P30: =AVERAGE(P18:P28) -> 10.67 | Q30: =AVERAGE(Q18:Q28) -> 22.727222 | R30: =AVERAGE(R18:R28) -> 59.325625 | S30: =AVERAGE(S18:S28) -> 52.198333 | ... X30: =AVERAGE(X18:X28) -> 92.768 | BQ30: 0-5 | BR30: 73 | BS30: 174.04 | BT30: =BS30/BR30 -> 2.3841096 | DJ30: 9 | DK30: 3 | DL30: 0
B31: 75 to 100 | C31: 3 | D31: 175.51 | E31: 3 | BQ31: 5-15 | BR31: 41 | BS31: 126.98 | BT31: =BS31/BR31 -> 3.0970732 | DJ31: 11 | DK31: 6 | DL31: 0
A32: 600-650 Total | C32: 15 | D32: 521.43 | E32: 15 | Z32: =AVERAGE(Z18:Z28) -> 24.007511 | AX32: YEAR | AY32: postive | AZ32: negative | BA32: neutral | BB32: avergae gain | BC32: total | BD32: %postive | BE32: %negative | BF32: neutral | BQ32: 15-30 | BR32: 22 | BS32: 117.35 | BT32: =BS32/BR32 -> 5.3340909 | DJ32: 6 | DK32: 2 | DL32: 1
A33: 650-700 | B33: 100 to 125 | C33: 1 | D33: 23.36 | E33: 1 | AM33: YEAR | AN33: AVERAGE GAIN | AO33: MARKET GAIN | AX33: 2021 | AY33: 46 | AZ33: 19 | BA33: 0 | BB33: 30.28 | BC33: =AY33+AZ33+BA33 -> 65 | BD33: =AY33/BC33 *100 -> 70.769231 | BE33: =AZ33/BC33 *100 -> 29.230769 | BF33: =BA33/BC33 -> 0 | BQ33: 30-60 | BR33: 31 | BS33: 396.1 | BT33: =BS33/BR33 -> 12.777419 | DJ33: 33 | DK33: 8 | DL33: 3
B34: 25 to 50 | C34: 2 | D34: 1.59 | E34: 2 | AM34: 2021 | AN34: 30.28 | AO34: 22 | AX34: 2022 | AY34: 27 | AZ34: 10 | BA34: 2 | BB34: 10.2 | BC34: =AY34+AZ34+BA34 -> 39 | BD34: =AY34/BC34 *100 -> 69.230769 | BE34: =AZ34/BC34 *100 -> 25.641026 | BF34: =BA34/BC34 *100 -> 5.1282051 | BQ34: 60-90 | BR34: 33 | BS34: 1093.74 | BT34: =BS34/BR34 -> 33.143636 | DJ34: 35 | DK34: 0 | DL34: 1
B35: 5 to 10 | C35: 3 | D35: -2.69 | E35: 3 | AM35: 2022 | AN35: 10.2 | AO35: 4.5 | AX35: 2023 | AY35: 47 | AZ35: 8 | BA35: 5 | BB35: 26.06 | BC35: =AY35+AZ35+BA35 -> 60 | BD35: =AY35/BC35 *100 -> 78.333333 | BE35: =AZ35/BC35 *100 -> 13.333333 | BF35: =BA35/BC35 *100 -> 8.3333333 | BQ35: 90-120 | BR35: 26 | BS35: 942.9 | BT35: =BS35/BR35 -> 36.265385 | DJ35: 25 | DK35: 0 | DL35: 0
B36: 75 to 100 | C36: 1 | D36: 47.3 | E36: 1 | AM36: 2023 | AN36: 26.06 | AO36: 18.8 | AX36: 2024 | AY36: 72 | AZ36: 18 | BA36: 2 | BB36: 28.49 | BC36: =AY36+AZ36+BA36 -> 92 | BD36: =AY36/BC36 *100 -> 78.26087 | BE36: =AZ36/BC36 *100 -> 19.565217 | BF36: =BA36/BC36 *100 -> 2.173913 | BQ36: 120-160 | BR36: 27 | BS36: 1384.71 | BT36: =BS36/BR36 -> 51.285556 | DJ36: 20 | DK36: 0 | DL36: 0
A37: 650-700 Total | C37: 7 | D37: 69.56 | E37: 7 | AM37: 2024 | AN37: 28.49 | AO37: 8.12 | AX37: 2025 | AY37: 32 | AZ37: 9 | BA37: 3 | BB37: 12.34 | BC37: =AY37+AZ37+BA37 -> 44 | BD37: =AY37/BC37 *100 -> 72.727273 | BE37: =AZ37/BC37 *100 -> 20.454545 | BF37: =BA37/BC37 *100 -> 6.8181818 | BQ37: 160-200 | BR37: 29 | BS37: 1549.02 | BT37: =BS37/BR37 -> 53.414483 | DJ37: 6 | DK37: 0 | DL37: 0
A38: 700-750 | B38: 0 to 5 | C38: 1 | D38: -6.92 | E38: 1 | AM38: 2025 | AN38: 12.34 | AO38: 2 | BA38: SD | BB38: =_xlfn.STDEV.P(BB33:BB37) -> 8.4656284 | BC38: average | BD38: =AVERAGE(BD33:BD37) -> 73.864295 | BE38: =AVERAGE(BE33:BE37) -> 21.644978 | BF38: =AVERAGE(BF33:BF37) -> 4.4907267 | BQ38: 200-250 | BR38: 15 | BS38: 1010.28 | BT38: =BS38/BR38 -> 67.352 | DJ38: 8 | DK38: 0 | DL38: 0
B39: 10 to 15 | C39: 2 | D39: 7.86 | E39: 2 | BQ39: 250-300 | BR39: 2 | BS39: 161.32 | BT39: =BS39/BR39 -> 80.66 | DJ39: 7 | DK39: 0 | DL39: 0
B40: 125 to 150 | C40: 1 | D40: 38.78 | E40: 1 | BQ40: >300 | BR40: 3 | BS40: 182.79 | BT40: =BS40/BR40 -> 60.93 | DJ40: 11 | DK40: 0 | DL40: 0
B41: 50 to 75 | C41: 2 | D41: 92.63 | E41: 2
B42: 75 to 100 | C42: 2 | D42: 80.66 | E42: 2
A43: 700-750 Total | C43: 8 | D43: 213.01 | E43: 8
A44: 750-800 | B44: 0 to 5 | C44: 2 | D44: -17.34 | E44: 2 | P44: WITHOUT CATEGORIES WITH JUST ONE LISTING
B45: 100 to 125 | C45: 1 | D45: 33.46 | E45: 1
B46: 25 to 50 | C46: 2 | D46: 30.89 | E46: 2 | Q46: TOTAL SUB
B47: 50 to 75 | C47: 1 | D47: 19.4 | E47: 1 | L47: 0-5 | M47: 5-10 | N47: 10-15 | O47: 15-20 | P47: 20-25 | Q47: 25-50 | R47: 50-75 | S47: 75-100 | T47: 100-125 | U47: 125-150 | V47: 150-175 | W47: 175-200 | X47: >200
A48: 750-800 Total | C48: 6 | D48: 66.41 | E48: 6 | I48: C | K48: 0-500 | L48: 5.5 | M48: 5.154 | N48: 13.81 | O48: 18.42 | P48: 3.45 | Q48: 6.98 | R48: 15.135 | S48: 37.93 | T48: 51.6 | U48: 50.81 | V48: 77.68 | W48: 58.73 | X48: 78.77 | Z48: =AVERAGE(L48:X48) -> 32.613
A49: 800-850 | B49: 0 to 5 | C49: 5 | D49: -0.69 | E49: 5 | K49: 500-1000 | L49: -3 | M49: 8.79 | N49: 4.66 | O49: 3.14 | Q49: 18.87 | R49: 35.37 | S49: 44.15 | T49: 41.1 | W49: 87.98 | X49: 106.766 | Z49: =AVERAGE(L49:X49) -> 34.7826
B50: 15 to 20 | C50: 1 | D50: 19.09 | E50: 1 | K50: 1000-1500 | L50: -2 | M50: -1 | O50: -1.46 | Q50: 14.94 | R50: 38.78 | S50: 33.58 | T50: 62.9 | Z50: =AVERAGE(L50:X50) -> 20.82
B51: 25 to 50 | C51: 4 | D51: 32.55 | E51: 4 | K51: 1500-2000 | L51: -0.07 | P51: 17.33 | Q51: 43.61 | R51: 28.05 | Z51: =AVERAGE(L51:X51) -> 22.23
B52: 5 to 10 | C52: 1 | D52: 4.02 | E52: 1 | J52: ISSUE SIZE | K52: 2000-2500 | L52: 8.57 | M52: 10.2 | P52: -1.1 | Q52: 32.84 | Z52: =AVERAGE(L52:X52) -> 12.6275
B53: 50 to 75 | C53: 1 | D53: 8.12 | E53: 1 | K53: 2500-3000 | L53: -6.2 | O53: -6.5 | Z53: =AVERAGE(L53:X53) -> -6.35
B54: 75 to 100 | C54: 2 | D54: 74.28 | E54: 2 | K54: 3000-3500 | L54: 3.02 | M54: 2.05 | O54: -3.91 | Q54: -0.22 | R54: 83.42 | Z54: =AVERAGE(L54:X54) -> 16.872
A55: 800-850 Total | C55: 14 | D55: 137.37 | E55: 14 | K55: 3500-4000 | L55: -4.7 | Z55: =AVERAGE(L55:X55) -> -4.7
A56: 850-900 | B56: 0 to 5 | C56: 3 | D56: 5.23 | E56: 3 | K56: 4000-4500 | Q56: 21.18 | Z56: =AVERAGE(L56:X56) -> 21.18
B57: 20 to 25 | C57: 1 | D57: 23 | E57: 1 | K57: 4500-5000 | L57: -10.6 | Z57: =AVERAGE(L57:X57) -> -10.6
B58: 25 to 50 | C58: 2 | D58: 39.08 | E58: 2 | K58: >5000 | L58: -0.885 | O58: 15.09 | Q58: 46.175 | Z58: =AVERAGE(L58:X58) -> 20.126667
B59: 50 to 75 | C59: 2 | D59: 44.9 | E59: 2
A60: 850-900 Total | C60: 8 | D60: 112.21 | E60: 8
A61: 900-950 | B61: 100 to 125 | C61: 1 | D61: 19.93 | E61: 1 | L61: =AVERAGE(L48:L58) -> -1.0365 | M61: =AVERAGE(M48:M58) -> 5.0388 | N61: -1.0365 | O61: 5.0388 | P61: 9.235 | Q61: 4.13 | R61: 6.56 | S61: 23.046875 | T61: 40.151 | U61: 38.553333 | V61: 51.866667 | W61: 50.81 | X61: 77.68
B62: 50 to 75 | C62: 1 | D62: 20.65 | E62: 1
A63: 900-950 Total | C63: 2 | D63: 40.58 | E63: 2
A64: 950-1000 | B64: 0 to 5 | C64: 1 | D64: 0.28 | E64: 1
B65: 10 to 15 | C65: 1 | D65: -4.47 | E65: 1
B66: 50 to 75 | C66: 1 | D66: 103.11 | E66: 1
A67: 950-1000 Total | C67: 3 | D67: 98.92 | E67: 3
A68: (blank) | B68: > 200 | C68: 8 | D68: 630.23 | E68: 8
B69: 0 to 5 | C69: 60 | D69: 46.19 | E69: 60
B70: 10 to 15 | C70: 6 | D70: 89.24 | E70: 6
B71: 100 to 125 | C71: 11 | D71: 595.34 | E71: 11
B72: 125 to 150 | C72: 5 | D72: 293.96 | E72: 5
B73: 15 to 20 | C73: 15 | D73: 180.08 | E73: 15
B74: 150 to 175 | C74: 7 | D74: 519.17 | E74: 7
B75: 175 to 200 | C75: 4 | D75: 234.92 | E75: 4
B76: 20 to 25 | C76: 8 | D76: 50.84 | E76: 8
B77: 25 to 50 | C77: 28 | D77: 531.95 | E77: 28
B78: 5 to 10 | C78: 18 | D78: 75.85 | E78: 18
B79: 50 to 75 | C79: 17 | D79: 779.65 | E79: 17
B80: 75 to 100 | C80: 15 | D80: 639.68 | E80: 15
B81: (blank)
A82: (blank) Total | C82: 202 | D82: 4667.1 | E82: 202
A83: Grand Total | C83: 302 | D83: 7139.23 | E83: 302

Sheet subvsgains
C1: total sub | D1: LISTIING GAINS | F1: POSTIVE GAINS | G1: NEGATIVE GAINS | H1: NEUTRAL GAINS | J1: 2021 average gains | K1: 2022 | L1: 2023 | M1: 2024 | N1: 2025
C2: 0-5 | D2: -0.2 | F2: 5 | G2: 14 | H2: 0 | J2: -3.8 | K2: 4.66 | L2: 1 | M2: -1.6 | N2: -2.7
C3: 5-10 | D3: 5.3 | F3: 18 | G3: 4 | H3: 2 | J3: 5.7 | K3: 3.7 | L3: 2.33 | M3: 9.06 | N3: 4.2
C4: 10-15 | D4: 9.77 | F4: 9 | G4: 3 | H4: 0 | J4: 0 | L4: 6.5 | M4: 17.5 | N4: 1.14
C5: 15-20 | D5: 10.1 | F5: 11 | G5: 6 | H5: 0 | J5: 10.8 | K5: 7.5 | L5: 15 | M5: 1.18 | N5: 12.84
C6: 20-25 | D6: 8.2 | F6: 6 | G6: 2 | H6: 1 | J6: 3.9 | L6: 10.7 | M6: 6.8 | N6: 23
C7: 25-50 | D7: 18.95 | F7: 33 | G7: 8 | H7: 3 | J7: 31.4 | K7: 16.77 | L7: 21.1 | M7: 13.86 | N7: 9.4
C8: 50-75 | D8: 40.32 | F8: 35 | G8: 0 | H8: 1 | J8: 48.3 | K8: 48.2 | L8: 40.46 | M8: 43.3 | N8: 15.13
C9: 75-100 | D9: 43.25 | F9: 25 | G9: 0 | H9: 0 | J9: 42.3 | L9: 56.76 | M9: 41.19 | N9: 20.83
C10: 100-125 | D10: 48.26 | F10: 20 | G10: 0 | H10: 0 | J10: 78.7 | L10: 77 | M10: 26.49 | N10: 37.085
C11: 125-150 | D11: 55.4 | F11: 6 | G11: 0 | H11: 0 | J11: 64.9 | M11: 71.53 | N11: 30.09
C12: 150-175 | D12: 66.16 | F12: 8 | G12: 0 | H12: 0 | J12: 31.6 | L12: 72.23 | M12: 94.21
C13: 175-200 | D13: 71.26 | F13: 7 | G13: 0 | H13: 0 | J13: 87.01 | M13: 118 | N13: 29.33
C14: >200 | D14: 86.4 | F14: 11 | G14: 0 | H14: 0 | J14: 122.9 | M14: 89.8 | N14: 33.19

Sheet issuevsgains 
B1: ISSUE | C1: AVERAGE GAINS | D1: POSTIVE | E1: NEGATIVE | F1: NO GAINS | G1: 2021 AVERAGE GAIN | H1: 2022 | I1: 23 | J1: 24 | K1: 25
B2: 0-500 | C2: 31.5 | D2: 67 | E2: 11 | F2: 7 | G2: 61.77 | H2: 8.96 | I2: 23.7 | J2: 42.7 | K2: 20.22 | M2: =_xlfn.STDEV.S(G2:K2) -> 20.843694
B3: 500-1000 | C3: 24.7 | D3: 74 | E3: 23 | F3: 3 | G3: 39.5 | H3: 15.09 | I3: 25.1 | J3: 22.8 | K3: 10.6 | M3: =_xlfn.STDEV.S(G3:K3) -> 11.0939
B4: 1000-1500 | C4: 18.9 | D4: 25 | E4: 8 | F4: 6 | G4: 18.5 | H4: 9.9 | I4: 26.27 | J4: 16.05 | K4: 16 | M4: =_xlfn.STDEV.S(G4:K4) -> 5.9140451
B5: 1500-2000 | C5: 16.28 | D5: 17 | E5: 4 | F5: 2 | G5: 40.3 | H5: -1.8 | I5: 15.9 | J5: 19.7 | K5: -0.5 | M5: =_xlfn.STDEV.S(G5:K5) -> 17.212554
B6: 2000-2500 | C6: 17.02 | D6: 10 | E6: 0 | F6: 0 | G6: 16.69 | H6: 18.5 | I6: 56.25 | J6: 12.5 | K6: 5.91 | M6: =_xlfn.STDEV.S(G6:K6) -> 19.765135
B7: 2500-3000 | C7: 11.124 | D7: 4 | E7: 5 | F7: 1 | G7: -4 | H7: 0 | I7: 20 | J7: 37 | K7: -2.4 | M7: =_xlfn.STDEV.S(G7:K7) -> 17.879374
B8: 3000-3500 | C8: 27.99 | D8: 5 | E8: 2 | F8: 0 | G8: 0 | H8: 8.08 | I8: 71.13 | J8: 10 | K8: 12.7 | M8: =_xlfn.STDEV.S(G8:K8) -> 28.761622
B9: 3500-4000 | C9: -1.8 | D9: 1 | E9: 4 | F9: 0 | G9: -1.42 | H9: -3.41 | I9: 0 | J9: 0 | K9: -1.7 | M9: =_xlfn.STDEV.S(G9:K9) -> 1.4147721
B10: 4000-4500 | C10: 31.25 | D10: 7 | E10: 0 | F10: 0 | G10: 0 | H10: 30.7 | I10: 20 | J10: 39.4 | K10: 10 | M10: =_xlfn.STDEV.S(G10:K10) -> 15.738869
B11: 4500-5000 | C11: -5.74 | D11: 0 | E11: 3 | F11: 0 | G11: -10.61 | H11: 0 | I11: 0 | J11: 0 | K11: 4 | M11: =_xlfn.STDEV.S(G11:K11) -> 5.4734285
B12: >5000 | C12: 16.48 | D12: 13 | E12: 6 | F12: 0 | G12: 19.95 | H12: -3.6 | I12: 0 | J12: 20.5 | K12: 8 | M12: =_xlfn.STDEV.S(G12:K12) -> 11.100766
G15: =_xlfn.STDEV.S(G2:G12) -> 22.76295 | H15: =_xlfn.STDEV.S(H2:H12) -> 10.799554 | I15: =_xlfn.STDEV.S(I2:I12) -> 22.562048 | J15: =_xlfn.STDEV.S(J2:J12) -> 14.69913 | K15: =_xlfn.STDEV.S(K2:K12) -> 7.3390503

Sheet FOR NO OF +
A3: Row Labels | B3: Gains(%) | C3: Count of IPO NAME | F3: No of companies | G3: =_xlfn.XLOOKUP(A14,A14,GETPIVOTDATA("Count of IPO NAME",$A$3)) -> 7 | H3: Percentage in positive | I3: {=SUMPRODUCT( SUBTOTAL(103, OFFSET($B$4, ROW($B$4:$B$303)-ROW($B$4), 0, 1)) * --(ISNUMBER($B$4:$B$303)) * --($B$4:$B$303 >= 0) )} -> 8 | J3: COMPANIES IN NEGATIVE
A4: Protean eGov Techn | B4: 0 | C4: 1
A5: Abans Financial Se | B5: 0 | C5: 1 | I5: =COUNT(A4:A37) -> 0
A6: RBZ Jewellers Ltd | B6: 0 | C6: 1
A7: Manoj Vaibhav Gems | B7: 0 | C7: 1
A8: Scoda Tubes Ltd | B8: 0 | C8: 1
A9: Indogulf Cropscien | B9: 0 | C9: 1
A10: Udayshivakumar Inf | B10: 0 | C10: 1
A11: Grand Total | B11: 0 | C11: 7

Sheet Sheet9 (2)
A3: Row Labels | B3: Count of IPO NAME | C3: Sum of Listing Gains(%) | D3: YEAR
A4: Abans Financial Se | B4: 1 | C4: 0 | D4: =_xlfn.XLOOKUP(A4,'ipo_21-25'!C:C,'ipo_21-25'!#REF!) -> #REF! | G4: =_xlfn.XLOOKUP('FOR NO OF +'!A11,'FOR NO OF +'!A11,GETPIVOTDATA("Count of IPO NAME",'FOR NO OF +'!$A$3)) -> 7
A5: Indogulf Cropscien | B5: 1 | C5: 0 | D5: =_xlfn.XLOOKUP(A5,'ipo_21-25'!C:C,'ipo_21-25'!#REF!) -> #REF!
A6: Manoj Vaibhav Gems | B6: 1 | C6: 0 | D6: =_xlfn.XLOOKUP(A6,'ipo_21-25'!C:C,'ipo_21-25'!#REF!) -> #REF! | F6: POSITIVE GAINS | G6: NEGATIVE GAINS | H6: NO GAINS
A7: Protean eGov Techn | B7: 1 | C7: 0 | D7: =_xlfn.XLOOKUP(A7,'ipo_21-25'!C:C,'ipo_21-25'!#REF!) -> #REF! | G7: {=MAX(0, SUMPRODUCT( SUBTOTAL(103,OFFSET($B$4,ROW($B$4:$B$306)-ROW($B$4),0,1))* --(ISNUMBER($B$4:$B$306))* --($B$4:$B$306<0) ))} -> 0
A8: RBZ Jewellers Ltd | B8: 1 | C8: 0 | D8: =_xlfn.XLOOKUP(A8,'ipo_21-25'!C:C,'ipo_21-25'!#REF!) -> #REF!
A9: Scoda Tubes Ltd | B9: 1 | C9: 0 | D9: =_xlfn.XLOOKUP(A9,'ipo_21-25'!C:C,'ipo_21-25'!#REF!) -> #REF!
A10: Udayshivakumar Inf | B10: 1 | C10: 0 | D10: =_xlfn.XLOOKUP(A10,'ipo_21-25'!C:C,'ipo_21-25'!#REF!) -> #REF!
D11: =_xlfn.XLOOKUP(A11,'ipo_21-25'!C:C,'ipo_21-25'!#REF!) -> #REF!
D12: =_xlfn.XLOOKUP(A12,'ipo_21-25'!C:C,'ipo_21-25'!#REF!) -> #REF!
D13: =_xlfn.XLOOKUP(A13,'ipo_21-25'!C:C,'ipo_21-25'!#REF!) -> #REF!
D14: =_xlfn.XLOOKUP(A14,'ipo_21-25'!C:C,'ipo_21-25'!#REF!) -> #REF!
D15: =_xlfn.XLOOKUP(A15,'ipo_21-25'!C:C,'ipo_21-25'!#REF!) -> #REF!
D16: =_xlfn.XLOOKUP(A16,'ipo_21-25'!C:C,'ipo_21-25'!#REF!) -> #REF!
D17: =_xlfn.XLOOKUP(A17,'ipo_21-25'!C:C,'ipo_21-25'!#REF!) -> #REF!
D18: =_xlfn.XLOOKUP(A18,'ipo_21-25'!C:C,'ipo_21-25'!#REF!) -> #REF!
D19: =_xlfn.XLOOKUP(A19,'ipo_21-25'!C:C,'ipo_21-25'!#REF!) -> #REF!
D20: =_xlfn.XLOOKUP(A20,'ipo_21-25'!C:C,'ipo_21-25'!#REF!) -> #REF!
D21: =_xlfn.XLOOKUP(A21,'ipo_21-25'!C:C,'ipo_21-25'!#REF!) -> #REF!
D22: =_xlfn.XLOOKUP(A22,'ipo_21-25'!C:C,'ipo_21-25'!#REF!) -> #REF!
... D305: =_xlfn.XLOOKUP(A305,'ipo_21-25'!C:C,'ipo_21-25'!#REF!) -> #REF!

Sheet Sheet9
A3: Row Labels | B3: Gains(%) | C3: Count of IPO NAME | F3: No of companies | G3: =_xlfn.XLOOKUP(A14,A14,GETPIVOTDATA("Count of IPO NAME",$A$3)) -> 10
A4: Indus Infra Trust | B4: 1 | C4: 1
A5: Travel Food Servic | B5: 2.38 | C5: 1 | I5: =COUNT(A4:A37) -> 0
A6: Sagility India Ltd | B6: 3.53 | C6: 1
A7: Niva Bupa Health I | B7: 6.08 | C7: 1
A8: Belrise Industries | B8: 9.44 | C8: 1
A9: Sapphire Foods Ind | B9: 11.1 | C9: 1
A10: Global Health Ltd | B10: 18.5 | C10: 1
A11: Krishna Institute | B11: 22.29 | C11: 1
A12: Inventurus Knowled | B12: 39.65 | C12: 1
A13: Indian Renewable E | B13: 56.25 | C13: 1
A14: Grand Total | B14: 170.22 | C14: 10

Sheet ipo_21-25
A1: List Date | B1: Year | C1: IPO NAME | D1: First name | E1: name without l | F1: CMP FROM D | G1: CMP(26_09) from c | H1: Issue Size(â‚¹.Cr) | I1: GRP BY 50 | J1: GRP BY 50IN 500 | K1: Issue size divide by 10 | L1: FROM 1000-1500 | M1: FROM 1500-2000 | N1: Size grp | O1: QIB | P1: NII | Q1: RII | R1: Total | S1: Grp by total | T1: Offer Price(â‚¹) | U1: List Price | V1: Listing Gains(%) | W1: grp by Listing | X1: CMP (BSE) | Y1: CMP (NSE) | Z1: Postive | AA1: GRP BY QIB | AB1: Current Gains(%)
A2: 45889 | B2: =TEXT(A2,"yyyy") -> 2025 | C2: Regaal Resources L | D2: RegAAl Resources L | E2: RegAAl Resources L | F2: =_xlfn.XLOOKUP(E2,MARKET_PRICE__2[Column2],MARKET_PRICE__2[Column3],"Not found") -> Not found | G2: =_xlfn.XLOOKUP(D2,MARKET_PRICE__2[Column12],MARKET_PRICE__2[Column3],"Not found") -> Not found | H2: 306 | I2: {=_xlfn.IFS( H2<50,"0-50", H2<100,"50-100", H2<150,"100-150", H2<200,"150-200", H2<250,"200-250", H2<300,"250-300", H2<350,"300-350", H2<400,"350-400", H2<450,"400-450", H2<=500,"450-500", TRUE,"Above 500" )} -> 300-350 | K2: =H2/10 -> 30.6 | N2: {=_xlfn.IFS(H2<500,"0-500",H2<1000,"500-1000",H2<1500,"1000-1500",H2<2000,"1500-2000",H2<2500,"2000-2500",H2<3000,"2500-3000",H2<3500,"3000-3500",H2<4000,"3500-4000",H2<4500,"4000-4500",H2<=5000,"4500-5000",TRUE,"Hbove 5000")} -> 0-500 | O2: 190.97 | P2: 356.73 | Q2: 57.75 | R2: 159.88 | S2: {=_xlfn.IFS( R2<0,"< 0", R2<5,"0 to 5", R2<10,"5 to 10", R2<15,"10 to 15", R2<20,"15 to 20", R2<25,"20 to 25", R2<50,"25 to 50", R2<75,"50 to 75", R2<100,"75 to 100", R2<125,"100 to 125", R2<150,"125 to 150", R2<175,"150 to 175", R2<200,"175 to 200", TRUE,"> 200" )} -> 150 to 175 | T2: 102 | U2: 141.8 | V2: 39.02 | W2: {=_xlfn.IFS( V2<-15,"< -15%", V2<-10,"-15% to -10%", V2<-5,"-10% to -5%", V2<0,"-5% to 0%", V2<10,"0% to 10%", V2<20,"10% to 20%", V2<30,"20% to 30%", V2<40,"30% to 40%", V2<50,"40% to 50%", V2<60,"50% to 60%", V2<70,"60% to 70%", V2<80,"70% to 80%", V2<90,"80% to 90%", V2<100,"90% to 100%", TRUE,"> 100%" )} -> 30% to 40% | X2: 124.15 | Y2: 124.08 | Z2: =IF(V2>0, ">0", IF(V2<0, "<0", "=0")) -> >0 | AA2: {=_xlfn.IFS( AND(O2>=0,O2<5),"0-5", AND(O2>=5,O2<15),"5-15", AND(O2>=15,O2<30),"15-30", AND(O2>=30,O2<60),"30-60", AND(O2>=60,O2<90),"60-90", AND(O2>=90,O2<120),"90-120", AND(O2>=120,O2<160),"120-160", AND(O2>=160,O2<200),"160-200", AND(O2>=200,O2<250),"200-250", AND(O2>=250,O2<300),"250-300", O2>=300,">300", TRUE,"Below 0" )} -> 160-200 | AB2: 21.72
A3: 45888 | B3: =TEXT(A3,"yyyy") -> 2025 | C3: Bluestone Jeweller | D3: =IFERROR(LEFT(C3,FIND(" ",C3)-1),C3) -> Bluestone | E3: =TRIM(SUBSTITUTE(SUBSTITUTE(C3,"Ltd",""),"Lt","")) -> Bluestone Jeweller | F3: =_xlfn.XLOOKUP(E3,MARKET_PRICE__2[Column2],MARKET_PRICE__2[Column3],"Not found") -> Not found | G3: =_xlfn.XLOOKUP(D3,MARKET_PRICE__2[Column12],MARKET_PRICE__2[Column3],"Not found") -> 758.00 | H3: 1540.65 | K3: =H3/10 -> 154.065 | M3: {=_xlfn.IFS( AND(H3>=1000,H3<1050),"1000-1050", AND(H3>=1050,H3<1100),"1050-1100", AND(H3>=1100,H3<1150),"1100-1150", AND(H3>=1150,H3<1200),"1150-1200", AND(H3>=1200,H3<1250),"1200-1250", AND(H3>=1250,H3<1300),"1250-1300", AND(H3>=1300,H3<1350),"1300-1350", AND(H3>=1350,H3<1400),"1350-1400", AND(H3>=1400,H3<1450),"1400-1450", AND(H3>=1450,H3<1500),"1450-1500", AND(H3>=1500,H3<1550),"1500-1550", AND(H3>=1550,H3<1600),"1550-1600", AND(H3>=1600,H3<1650),"1600-1650", AND(H3>=1650,H3<1700),"1650-1700", AND(H3>=1700,H3<1750),"1700-1750", AND(H3>=1750,H3<1800),"1750-1800", AND(H3>=1800,H3<1850),"1800-1850", AND(H3>=1850,H3<1900),"1850-1900", AND(H3>=1900,H3<1950),"1900-1950", AND(H3>=1950,H3<=2000),"1950-2000", H3<1000,"Below 1000", TRUE,"Above 2000" )} -> 1500-1550 | N3: {=_xlfn.IFS(H3<500,"0-500",H3<1000,"500-1000",H3<1500,"1000-1500",H3<2000,"1500-2000",H3<2500,"2000-2500",H3<3000,"2500-3000",H3<3500,"3000-3500",H3<4000,"3500-4000",H3<4500,"4000-4500",H3<=5000,"4500-5000",TRUE,"Hbove 5000")} -> 1500-2000 | O3: 4.28 | P3: 0.55 | Q3: 1.35 | R3: 2.7 | S3: {=_xlfn.IFS( R3<0,"< 0", R3<5,"0 to 5", R3<10,"5 to 10", R3<15,"10 to 15", R3<20,"15 to 20", R3<25,"20 to 25", R3<50,"25 to 50", R3<75,"50 to 75", R3<100,"75 to 100", R3<125,"100 to 125", R3<150,"125 to 150", R3<175,"150 to 175", R3<200,"175 to 200", TRUE,"> 200" )} -> 0 to 5 | T3: 517 | U3: 508.8 | V3: -1.59 | W3: {=_xlfn.IFS( V3<-15,"< -15%", V3<-10,"-15% to -10%", V3<-5,"-10% to -5%", V3<0,"-5% to 0%", V3<10,"0% to 10%", V3<20,"10% to 20%", V3<30,"20% to 30%", V3<40,"30% to 40%", V3<50,"40% to 50%", V3<60,"50% to 60%", V3<70,"60% to 70%", V3<80,"70% to 80%", V3<90,"80% to 90%", V3<100,"90% to 100%", TRUE,"> 100%" )} -> -5% to 0% | X3: 545.55 | Y3: 546.35 | Z3: =IF(V3>0, ">0", IF(V3<0, "<0", "=0")) -> <0 | AA3: {=_xlfn.IFS( AND(O3>=0,O3<5),"0-5", AND(O3>=5,O3<15),"5-15", AND(O3>=15,O3<30),"15-30", AND(O3>=30,O3<60),"30-60", AND(O3>=60,O3<90),"60-90", AND(O3>=90,O3<120),"90-120", AND(O3>=120,O3<160),"120-160", AND(O3>=160,O3<200),"160-200", AND(O3>=200,O3<250),"200-250", AND(O3>=250,O3<300),"250-300", O3>=300,">300", TRUE,"Below 0" )} -> 0-5 | AB3: 5.52
A4: 45883 | B4: =TEXT(A4,"yyyy") -> 2025 | C4: JSW Cement Ltd | D4: =IFERROR(LEFT(C4,FIND(" ",C4)-1),C4) -> JSW | E4: =TRIM(SUBSTITUTE(SUBSTITUTE(C4,"Ltd",""),"Lt","")) -> JSW Cement | F4: =_xlfn.XLOOKUP(E4,MARKET_PRICE__2[Column2],MARKET_PRICE__2[Column3],"Not found") -> 137.85 | G4: =_xlfn.XLOOKUP(D4,MARKET_PRICE__2[Column12],MARKET_PRICE__2[Column3],"Not found") -> 307.00 | H4: 3600 | K4: =H4/10 -> 360 | N4: {=_xlfn.IFS(H4<500,"0-500",H4<1000,"500-1000",H4<1500,"1000-1500",H4<2000,"1500-2000",H4<2500,"2000-2500",H4<3000,"2500-3000",H4<3500,"3000-3500",H4<4000,"3500-4000",H4<4500,"4000-4500",H4<=5000,"4500-5000",TRUE,"Hbove 5000")} -> 3500-4000 | O4: 15.8 | P4: 10.97 | Q4: 1.81 | R4: 7.77 | S4: {=_xlfn.IFS( R4<0,"< 0", R4<5,"0 to 5", R4<10,"5 to 10", R4<15,"10 to 15", R4<20,"15 to 20", R4<25,"20 to 25", R4<50,"25 to 50", R4<75,"50 to 75", R4<100,"75 to 100", R4<125,"100 to 125", R4<150,"125 to 150", R4<175,"150 to 175", R4<200,"175 to 200", TRUE,"> 200" )} -> 5 to 10 | T4: 147 | U4: 153 | V4: 4.08 | W4: {=_xlfn.IFS( V4<-15,"< -15%", V4<-10,"-15% to -10%", V4<-5,"-10% to -5%", V4<0,"-5% to 0%", V4<10,"0% to 10%", V4<20,"10% to 20%", V4<30,"20% to 30%", V4<40,"30% to 40%", V4<50,"40% to 50%", V4<60,"50% to 60%", V4<70,"60% to 70%", V4<80,"70% to 80%", V4<90,"80% to 90%", V4<100,"90% to 100%", TRUE,"> 100%" )} -> 0% to 10% | X4: 153.15 | Y4: 153.12 | Z4: =IF(V4>0, ">0", IF(V4<0, "<0", "=0")) -> >0 | AA4: {=_xlfn.IFS( AND(O4>=0,O4<5),"0-5", AND(O4>=5,O4<15),"5-15", AND(O4>=15,O4<30),"15-30", AND(O4>=30,O4<60),"30-60", AND(O4>=60,O4<90),"60-90", AND(O4>=90,O4<120),"90-120", AND(O4>=120,O4<160),"120-160", AND(O4>=160,O4<200),"160-200", AND(O4>=200,O4<250),"200-250", AND(O4>=250,O4<300),"250-300", O4>=300,">300", TRUE,"Below 0" )} -> 15-30 | AB4: 4.18
A5: 45883 | B5: =TEXT(A5,"yyyy") -> 2025 | C5: All Time Plastics | D5: =IFERROR(LEFT(C5,FIND(" ",C5)-1),C5) -> All | E5: =TRIM(SUBSTITUTE(SUBSTITUTE(C5,"Ltd",""),"Lt","")) -> All Time Plastics | F5: =_xlfn.XLOOKUP(E5,MARKET_PRICE__2[Column2],MARKET_PRICE__2[Column3],"Not found") -> Not found | G5: =_xlfn.XLOOKUP(D5,MARKET_PRICE__2[Column12],MARKET_PRICE__2[Column3],"Not found") -> 259.55 | H5: 400.6 | I5: {=_xlfn.IFS( H5<50,"0-50", H5<100,"50-100", H5<150,"100-150", H5<200,"150-200", H5<250,"200-250", H5<300,"250-300", H5<350,"300-350", H5<400,"350-400", H5<450,"400-450", H5<=500,"450-500", TRUE,"Above 500" )} -> 400-450 | K5: =H5/10 -> 40.06 | N5: {=_xlfn.IFS(H5<500,"0-500",H5<1000,"500-1000",H5<1500,"1000-1500",H5<2000,"1500-2000",H5<2500,"2000-2500",H5<3000,"2500-3000",H5<3500,"3000-3500",H5<4000,"3500-4000",H5<4500,"4000-4500",H5<=5000,"4500-5000",TRUE,"Hbove 5000")} -> 0-500 | O5: 10.15 | P5: 13.47 | Q5: 5.14 | R5: 8.34 | S5: {=_xlfn.IFS( R5<0,"< 0", R5<5,"0 to 5", R5<10,"5 to 10", R5<15,"10 to 15", R5<20,"15 to 20", R5<25,"20 to 25", R5<50,"25 to 50", R5<75,"50 to 75", R5<100,"75 to 100", R5<125,"100 to 125", R5<150,"125 to 150", R5<175,"150 to 175", R5<200,"175 to 200", TRUE,"> 200" )} -> 5 to 10 | T5: 275 | U5: 314.3 | V5: 14.29 | W5: {=_xlfn.IFS( V5<-15,"< -15%", V5<-10,"-15% to -10%", V5<-5,"-10% to -5%", V5<0,"-5% to 0%", V5<10,"0% to 10%", V5<20,"10% to 20%", V5<30,"20% to 30%", V5<40,"30% to 40%", V5<50,"40% to 50%", V5<60,"50% to 60%", V5<70,"60% to 70%", V5<80,"70% to 80%", V5<90,"80% to 90%", V5<100,"90% to 100%", TRUE,"> 100%" )} -> 10% to 20% | X5: 315.45 | Y5: 315.25 | Z5: =IF(V5>0, ">0", IF(V5<0, "<0", "=0")) -> >0 | AA5: {=_xlfn.IFS( AND(O5>=0,O5<5),"0-5", AND(O5>=5,O5<15),"5-15", AND(O5>=15,O5<30),"15-30", AND(O5>=30,O5<60),"30-60", AND(O5>=60,O5<90),"60-90", AND(O5>=90,O5<120),"90-120", AND(O5>=120,O5<160),"120-160", AND(O5>=160,O5<200),"160-200", AND(O5>=200,O5<250),"200-250", AND(O5>=250,O5<300),"250-300", O5>=300,">300", TRUE,"Below 0" )} -> 5-15 | AB5: 14.71
A6: 45881 | B6: =TEXT(A6,"yyyy") -> 2025 | C6: Highway Infrastruc | D6: =IFERROR(LEFT(C6,FIND(" ",C6)-1),C6) -> Highway | E6: =TRIM(SUBSTITUTE(SUBSTITUTE(C6,"Ltd",""),"Lt","")) -> Highway Infrastruc | F6: =_xlfn.XLOOKUP(E6,MARKET_PRICE__2[Column2],MARKET_PRICE__2[Column3],"Not found") -> Not found | G6: =_xlfn.XLOOKUP(D6,MARKET_PRICE__2[Column12],MARKET_PRICE__2[Column3],"Not found") -> 80.01 | H6: 130 | I6: {=_xlfn.IFS( H6<50,"0-50", H6<100,"50-100", H6<150,"100-150", H6<200,"150-200", H6<250,"200-250", H6<300,"250-300", H6<350,"300-350", H6<400,"350-400", H6<450,"400-450", H6<=500,"450-500", TRUE,"Above 500" )} -> 100-150 | K6: =H6/10 -> 13 | N6: {=_xlfn.IFS(H6<500,"0-500",H6<1000,"500-1000",H6<1500,"1000-1500",H6<2000,"1500-2000",H6<2500,"2000-2500",H6<3000,"2500-3000",H6<3500,"3000-3500",H6<4000,"3500-4000",H6<4500,"4000-4500",H6<=5000,"4500-5000",TRUE,"Hbove 5000")} -> 0-500 | O6: 420.57 | P6: 447.32 | Q6: 155.58 | R6: 300.61 | S6: {=_xlfn.IFS( R6<0,"< 0", R6<5,"0 to 5", R6<10,"5 to 10", R6<15,"10 to 15", R6<20,"15 to 20", R6<25,"20 to 25", R6<50,"25 to 50", R6<75,"50 to 75", R6<100,"75 to 100", R6<125,"100 to 125", R6<150,"125 to 150", R6<175,"150 to 175", R6<200,"175 to 200", TRUE,"> 200" )} -> > 200 | T6: 70 | U6: 117 | V6: 67.14 | W6: {=_xlfn.IFS( V6<-15,"< -15%", V6<-10,"-15% to -10%", V6<-5,"-10% to -5%", V6<0,"-5% to 0%", V6<10,"0% to 10%", V6<20,"10% to 20%", V6<30,"20% to 30%", V6<40,"30% to 40%", V6<50,"40% to 50%", V6<60,"50% to 60%", V6<70,"60% to 70%", V6<80,"70% to 80%", V6<90,"80% to 90%", V6<100,"90% to 100%", TRUE,"> 100%" )} -> 60% to 70% | X6: 99.2 | Y6: 99.15 | Z6: =IF(V6>0, ">0", IF(V6<0, "<0", "=0")) -> >0 | AA6: {=_xlfn.IFS( AND(O6>=0,O6<5),"0-5", AND(O6>=5,O6<15),"5-15", AND(O6>=15,O6<30),"15-30", AND(O6>=30,O6<60),"30-60", AND(O6>=60,O6<90),"60-90", AND(O6>=90,O6<120),"90-120", AND(O6>=120,O6<160),"120-160", AND(O6>=160,O6<200),"160-200", AND(O6>=200,O6<250),"200-250", AND(O6>=250,O6<300),"250-300", O6>=300,">300", TRUE,"Below 0" )} -> >300 | AB6: 41.71
A7: 45887 | B7: =TEXT(A7,"yyyy") -> 2025 | C7: Knowledge Realty T | D7: =IFERROR(LEFT(C7,FIND(" ",C7)-1),C7) -> Knowledge | E7: =TRIM(SUBSTITUTE(SUBSTITUTE(C7,"Ltd",""),"Lt","")) -> Knowledge Realty T | F7: =_xlfn.XLOOKUP(E7,MARKET_PRICE__2[Column2],MARKET_PRICE__2[Column3],"Not found") -> Not found | G7: =_xlfn.XLOOKUP(D7,MARKET_PRICE__2[Column12],MARKET_PRICE__2[Column3],"Not found") -> 2340.00 | H7: 4800 | K7: =H7/10 -> 480 | N7: {=_xlfn.IFS(H7<500,"0-500",H7<1000,"500-1000",H7<1500,"1000-1500",H7<2000,"1500-2000",H7<2500,"2000-2500",H7<3000,"2500-3000",H7<3500,"3000-3500",H7<4000,"3500-4000",H7<4500,"4000-4500",H7<=5000,"4500-5000",TRUE,"Hbove 5000")} -> 4500-5000 | O7: 6.75 | P7: 15.51 | Q7: 0 | R7: 10.73 | S7: {=_xlfn.IFS( R7<0,"< 0", R7<5,"0 to 5", R7<10,"5 to 10", R7<15,"10 to 15", R7<20,"15 to 20", R7<25,"20 to 25", R7<50,"25 to 50", R7<75,"50 to 75", R7<100,"75 to 100", R7<125,"100 to 125", R7<150,"125 to 150", R7<175,"150 to 175", R7<200,"175 to 200", TRUE,"> 200" )} -> 10 to 15 | T7: 100 | U7: 104 | V7: 4 | W7: {=_xlfn.IFS( V7<-15,"< -15%", V7<-10,"-15% to -10%", V7<-5,"-10% to -5%", V7<0,"-5% to 0%", V7<10,"0% to 10%", V7<20,"10% to 20%", V7<30,"20% to 30%", V7<40,"30% to 40%", V7<50,"40% to 50%", V7<60,"50% to 60%", V7<70,"60% to 70%", V7<80,"70% to 80%", V7<90,"80% to 90%", V7<100,"90% to 100%", TRUE,"> 100%" )} -> 0% to 10% | X7: 107.09 | Y7: 107.06 | Z7: =IF(V7>0, ">0", IF(V7<0, "<0", "=0")) -> >0 | AA7: {=_xlfn.IFS( AND(O7>=0,O7<5),"0-5", AND(O7>=5,O7<15),"5-15", AND(O7>=15,O7<30),"15-30", AND(O7>=30,O7<60),"30-60", AND(O7>=60,O7<90),"60-90", AND(O7>=90,O7<120),"90-120", AND(O7>=120,O7<160),"120-160", AND(O7>=160,O7<200),"160-200", AND(O7>=200,O7<250),"200-250", AND(O7>=250,O7<300),"250-300", O7>=300,">300", TRUE,"Below 0" )} -> 5-15 | AB7: 7.09
A8: 45875 | B8: =TEXT(A8,"yyyy") -> 2025 | C8: M & B Engineering | D8: =IFERROR(LEFT(C8,FIND(" ",C8)-1),C8) -> M | E8: =TRIM(SUBSTITUTE(SUBSTITUTE(C8,"Ltd",""),"Lt","")) -> M & B Engineering | F8: =_xlfn.XLOOKUP(E8,MARKET_PRICE__2[Column2],MARKET_PRICE__2[Column3],"Not found") -> Not found | G8: =_xlfn.XLOOKUP(D8,MARKET_PRICE__2[Column12],MARKET_PRICE__2[Column3],"Not found") -> 64.70 | H8: 650 | J8: {=_xlfn.IFS( AND(H8>=500,H8<550),"500-550", AND(H8>=550,H8<600),"550-600", AND(H8>=600,H8<650),"600-650", AND(H8>=650,H8<700),"650-700", AND(H8>=700,H8<750),"700-750", AND(H8>=750,H8<800),"750-800", AND(H8>=800,H8<850),"800-850", AND(H8>=850,H8<900),"850-900", AND(H8>=900,H8<950),"900-950", AND(H8>=950,H8<=1000),"950-1000", H8<500,"Below 500", TRUE,"Above 1000" )} -> 650-700 | K8: {=_xlfn.IFS( AND(I8>=500,I8<550),"500-550", AND(I8>=550,I8<600),"550-600", AND(I8>=600,I8<650),"600-650", AND(I8>=650,I8<700),"650-700", AND(I8>=700,I8<750),"700-750", AND(I8>=750,I8<800),"750-800", AND(I8>=800,I8<850),"800-850", AND(I8>=850,I8<900),"850-900", AND(I8>=900,I8<950),"900-950", AND(I8>=950,I8<=1000),"950-1000", I8<500,"Below 500", TRUE,"Above 1000" )} -> Below 500 | N8: {=_xlfn.IFS(H8<500,"0-500",H8<1000,"500-1000",H8<1500,"1000-1500",H8<2000,"1500-2000",H8<2500,"2000-2500",H8<3000,"2500-3000",H8<3500,"3000-3500",H8<4000,"3500-4000",H8<4500,"4000-4500",H8<=5000,"4500-5000",TRUE,"Hbove 5000")} -> 500-1000 | O8: 36.72 | P8: 38.24 | Q8: 32.55 | R8: 36.2 | S8: {=_xlfn.IFS( R8<0,"< 0", R8<5,"0 to 5", R8<10,"5 to 10", R8<15,"10 to 15", R8<20,"15 to 20", R8<25,"20 to 25", R8<50,"25 to 50", R8<75,"50 to 75", R8<100,"75 to 100", R8<125,"100 to 125", R8<150,"125 to 150", R8<175,"150 to 175", R8<200,"175 to 200", TRUE,"> 200" )} -> 25 to 50 | T8: 385 | U8: 386 | V8: 0.26 | W8: {=_xlfn.IFS( V8<-15,"< -15%", V8<-10,"-15% to -10%", V8<-5,"-10% to -5%", V8<0,"-5% to 0%", V8<10,"0% to 10%", V8<20,"10% to 20%", V8<30,"20% to 30%", V8<40,"30% to 40%", V8<50,"40% to 50%", V8<60,"50% to 60%", V8<70,"60% to 70%", V8<80,"70% to 80%", V8<90,"80% to 90%", V8<100,"90% to 100%", TRUE,"> 100%" )} -> 0% to 10% | X8: 465.7 | Y8: 465.2 | Z8: =IF(V8>0, ">0", IF(V8<0, "<0", "=0")) -> >0 | AA8: {=_xlfn.IFS( AND(O8>=0,O8<5),"0-5", AND(O8>=5,O8<15),"5-15", AND(O8>=15,O8<30),"15-30", AND(O8>=30,O8<60),"30-60", AND(O8>=60,O8<90),"60-90", AND(O8>=90,O8<120),"90-120", AND(O8>=120,O8<160),"120-160", AND(O8>=160,O8<200),"160-200", AND(O8>=200,O8<250),"200-250", AND(O8>=250,O8<300),"250-300", O8>=300,">300", TRUE,"Below 0" )} -> 30-60 | AB8: 20.96
A9: 45875 | B9: =TEXT(A9,"yyyy") -> 2025 | C9: Sri Lotus Develope | D9: =IFERROR(LEFT(C9,FIND(" ",C9)-1),C9) -> Sri | E9: =TRIM(SUBSTITUTE(SUBSTITUTE(C9,"Ltd",""),"Lt","")) -> Sri Lotus Develope | F9: =_xlfn.XLOOKUP(E9,MARKET_PRICE__2[Column2],MARKET_PRICE__2[Column3],"Not found") -> Not found | G9: =_xlfn.XLOOKUP(D9,MARKET_PRICE__2[Column12],MARKET_PRICE__2[Column3],"Not found") -> 863.90 | H9: 792 | J9: {=_xlfn.IFS( AND(H9>=500,H9<550),"500-550", AND(H9>=550,H9<600),"550-600", AND(H9>=600,H9<650),"600-650", AND(H9>=650,H9<700),"650-700", AND(H9>=700,H9<750),"700-750", AND(H9>=750,H9<800),"750-800", AND(H9>=800,H9<850),"800-850", AND(H9>=850,H9<900),"850-900", AND(H9>=900,H9<950),"900-950", AND(H9>=950,H9<=1000),"950-1000", H9<500,"Below 500", TRUE,"Above 1000" )} -> 750-800 | K9: =H9/10 -> 79.2 | N9: {=_xlfn.IFS(H9<500,"0-500",H9<1000,"500-1000",H9<1500,"1000-1500",H9<2000,"1500-2000",H9<2500,"2000-2500",H9<3000,"2500-3000",H9<3500,"3000-3500",H9<4000,"3500-4000",H9<4500,"4000-4500",H9<=5000,"4500-5000",TRUE,"Hbove 5000")} -> 500-1000 | O9: 163.9 | P9: 57.71 | Q9: 20.28 | R9: 69.14 | S9: {=_xlfn.IFS( R9<0,"< 0", R9<5,"0 to 5", R9<10,"5 to 10", R9<15,"10 to 15", R9<20,"15 to 20", R9<25,"20 to 25", R9<50,"25 to 50", R9<75,"50 to 75", R9<100,"75 to 100", R9<125,"100 to 125", R9<150,"125 to 150", R9<175,"150 to 175", R9<200,"175 to 200", TRUE,"> 200" )} -> 50 to 75 | T9: 150 | U9: 179.1 | V9: 19.4 | W9: {=_xlfn.IFS( V9<-15,"< -15%", V9<-10,"-15% to -10%", V9<-5,"-10% to -5%", V9<0,"-5% to 0%", V9<10,"0% to 10%", V9<20,"10% to 20%", V9<30,"20% to 30%", V9<40,"30% to 40%", V9<50,"40% to 50%", V9<60,"50% to 60%", V9<70,"60% to 70%", V9<80,"70% to 80%", V9<90,"80% to 90%", V9<100,"90% to 100%", TRUE,"> 100%" )} -> 10% to 20% | X9: 192.2 | Y9: 191.81 | Z9: =IF(V9>0, ">0", IF(V9<0, "<0", "=0")) -> >0 | AA9: {=_xlfn.IFS( AND(O9>=0,O9<5),"0-5", AND(O9>=5,O9<15),"5-15", AND(O9>=15,O9<30),"15-30", AND(O9>=30,O9<60),"30-60", AND(O9>=60,O9<90),"60-90", AND(O9>=90,O9<120),"90-120", AND(O9>=120,O9<160),"120-160", AND(O9>=160,O9<200),"160-200", AND(O9>=200,O9<250),"200-250", AND(O9>=250,O9<300),"250-300", O9>=300,">300", TRUE,"Below 0" )} -> 160-200 | AB9: 28.13
A10: 45875 | B10: =TEXT(A10,"yyyy") -> 2025 | C10: National Securitie | D10: =IFERROR(LEFT(C10,FIND(" ",C10)-1),C10) -> National | E10: =TRIM(SUBSTITUTE(SUBSTITUTE(C10,"Ltd",""),"Lt","")) -> National Securitie | F10: =_xlfn.XLOOKUP(E10,MARKET_PRICE__2[Column2],MARKET_PRICE__2[Column3],"Not found") -> Not found | G10: =_xlfn.XLOOKUP(D10,MARKET_PRICE__2[Column12],MARKET_PRICE__2[Column3],"Not found") -> 244.00 | H10: 4011.6 | K10: =H10/10 -> 401.16 | N10: {=_xlfn.IFS(H10<500,"0-500",H10<1000,"500-1000",H10<1500,"1000-1500",H10<2000,"1500-2000",H10<2500,"2000-2500",H10<3000,"2500-3000",H10<3500,"3000-3500",H10<4000,"3500-4000",H10<4500,"4000-4500",H10<=5000,"4500-5000",TRUE,"Hbove 5000")} -> 4000-4500 | O10: 103.97 | P10: 34.98 | Q10: 7.73 | R10: 41.01 | S10: {=_xlfn.IFS( R10<0,"< 0", R10<5,"0 to 5", R10<10,"5 to 10", R10<15,"10 to 15", R10<20,"15 to 20", R10<25,"20 to 25", R10<50,"25 to 50", R10<75,"50 to 75", R10<100,"75 to 100", R10<125,"100 to 125", R10<150,"125 to 150", R10<175,"150 to 175", R10<200,"175 to 200", TRUE,"> 200" )} -> 25 to 50 | T10: 800 | U10: 880 | V10: 10 | W10: {=_xlfn.IFS( V10<-15,"< -15%", V10<-10,"-15% to -10%", V10<-5,"-10% to -5%", V10<0,"-5% to 0%", V10<10,"0% to 10%", V10<20,"10% to 20%", V10<30,"20% to 30%", V10<40,"30% to 40%", V10<50,"40% to 50%", V10<60,"50% to 60%", V10<70,"60% to 70%", V10<80,"70% to 80%", V10<90,"80% to 90%", V10<100,"90% to 100%", TRUE,"> 100%" )} -> 10% to 20% | X10: 1275.4 | Z10: =IF(V10>0, ">0", IF(V10<0, "<0", "=0")) -> >0 | AA10: {=_xlfn.IFS( AND(O10>=0,O10<5),"0-5", AND(O10>=5,O10<15),"5-15", AND(O10>=15,O10<30),"15-30", AND(O10>=30,O10<60),"30-60", AND(O10>=60,O10<90),"60-90", AND(O10>=90,O10<120),"90-120", AND(O10>=120,O10<160),"120-160", AND(O10>=160,O10<200),"160-200", AND(O10>=200,O10<250),"200-250", AND(O10>=250,O10<300),"250-300", O10>=300,">300", TRUE,"Below 0" )} -> 90-120 | AB10: 59.43
A11: 45874 | B11: =TEXT(A11,"yyyy") -> 2025 | C11: Aditya Infotech Lt | D11: =IFERROR(LEFT(C11,FIND(" ",C11)-1),C11) -> Aditya | E11: =TRIM(SUBSTITUTE(SUBSTITUTE(C11,"Ltd",""),"Lt","")) -> Aditya Infotech | F11: =_xlfn.XLOOKUP(E11,MARKET_PRICE__2[Column2],MARKET_PRICE__2[Column3],"Not found") -> 1354.50 | G11: =_xlfn.XLOOKUP(D11,MARKET_PRICE__2[Column12],MARKET_PRICE__2[Column3],"Not found") -> 804.45 | H11: 1300 | K11: =H11/10 -> 130 | N11: {=_xlfn.IFS(H11<500,"0-500",H11<1000,"500-1000",H11<1500,"1000-1500",H11<2000,"1500-2000",H11<2500,"2000-2500",H11<3000,"2500-3000",H11<3500,"3000-3500",H11<4000,"3500-4000",H11<4500,"4000-4500",H11<=5000,"4500-5000",TRUE,"Hbove 5000")} -> 1000-1500 | O11: 133.21 | P11: 72 | Q11: 50.87 | R11: 100.69 | S11: {=_xlfn.IFS( R11<0,"< 0", R11<5,"0 to 5", R11<10,"5 to 10", R11<15,"10 to 15", R11<20,"15 to 20", R11<25,"20 to 25", R11<50,"25 to 50", R11<75,"50 to 75", R11<100,"75 to 100", R11<125,"100 to 125", R11<150,"125 to 150", R11<175,"150 to 175", R11<200,"175 to 200", TRUE,"> 200" )} -> 100 to 125 | T11: 675 | U11: 1018 | V11: 50.81 | W11: {=_xlfn.IFS( V11<-15,"< -15%", V11<-10,"-15% to -10%", V11<-5,"-10% to -5%", V11<0,"-5% to 0%", V11<10,"0% to 10%", V11<20,"10% to 20%", V11<30,"20% to 30%", V11<40,"30% to 40%", V11<50,"40% to 50%", V11<60,"50% to 60%", V11<70,"60% to 70%", V11<80,"70% to 80%", V11<90,"80% to 90%", V11<100,"90% to 100%", TRUE,"> 100%" )} -> 50% to 60% | X11: 1361.1 | Y11: 1360.45 | Z11: =IF(V11>0, ">0", IF(V11<0, "<0", "=0")) -> >0 | AA11: {=_xlfn.IFS( AND(O11>=0,O11<5),"0-5", AND(O11>=5,O11<15),"5-15", AND(O11>=15,O11<30),"15-30", AND(O11>=30,O11<60),"30-60", AND(O11>=60,O11<90),"60-90", AND(O11>=90,O11<120),"90-120", AND(O11>=120,O11<160),"120-160", AND(O11>=160,O11<200),"160-200", AND(O11>=200,O11<250),"200-250", AND(O11>=250,O11<300),"250-300", O11>=300,">300", TRUE,"Below 0" )} -> 120-160 | AB11: 101.64
A12: 45874 | B12: =TEXT(A12,"yyyy") -> 2025 | C12: Laxmi India Financ | D12: =IFERROR(LEFT(C12,FIND(" ",C12)-1),C12) -> Laxmi | E12: =TRIM(SUBSTITUTE(SUBSTITUTE(C12,"Ltd",""),"Lt","")) -> Laxmi India Financ | F12: =_xlfn.XLOOKUP(E12,MARKET_PRICE__2[Column2],MARKET_PRICE__2[Column3],"Not found") -> Not found | G12: =_xlfn.XLOOKUP(D12,MARKET_PRICE__2[Column12],MARKET_PRICE__2[Column3],"Not found") -> 320.00 | H12: 254.26 | I12: {=_xlfn.IFS( H12<50,"0-50", H12<100,"50-100", H12<150,"100-150", H12<200,"150-200", H12<250,"200-250", H12<300,"250-300", H12<350,"300-350", H12<400,"350-400", H12<450,"400-450", H12<=500,"450-500", TRUE,"Above 500" )} -> 250-300 | K12: =H12/10 -> 25.426 | N12: {=_xlfn.IFS(H12<500,"0-500",H12<1000,"500-1000",H12<1500,"1000-1500",H12<2000,"1500-2000",H12<2500,"2000-2500",H12<3000,"2500-3000",H12<3500,"3000-3500",H12<4000,"3500-4000",H12<4500,"4000-4500",H12<=5000,"4500-5000",TRUE,"Hbove 5000")} -> 0-500 | O12: 1.3 | P12: 1.84 | Q12: 2.22 | R12: 1.87 | S12: {=_xlfn.IFS( R12<0,"< 0", R12<5,"0 to 5", R12<10,"5 to 10", R12<15,"10 to 15", R12<20,"15 to 20", R12<25,"20 to 25", R12<50,"25 to 50", R12<75,"50 to 75", R12<100,"75 to 100", R12<125,"100 to 125", R12<150,"125 to 150", R12<175,"150 to 175", R12<200,"175 to 200", TRUE,"> 200" )} -> 0 to 5 | T12: 158 | U12: 136 | V12: -13.92 | W12: {=_xlfn.IFS( V12<-15,"< -15%", V12<-10,"-15% to -10%", V12<-5,"-10% to -5%", V12<0,"-5% to 0%", V12<10,"0% to 10%", V12<20,"10% to 20%", V12<30,"20% to 30%", V12<40,"30% to 40%", V12<50,"40% to 50%", V12<60,"50% to 60%", V12<70,"60% to 70%", V12<80,"70% to 80%", V12<90,"80% to 90%", V12<100,"90% to 100%", TRUE,"> 100%" )} -> -15% to -10% | X12: 140.75 | Y12: 141.13 | Z12: =IF(V12>0, ">0", IF(V12<0, "<0", "=0")) -> <0 | AA12: {=_xlfn.IFS( AND(O12>=0,O12<5),"0-5", AND(O12>=5,O12<15),"5-15", AND(O12>=15,O12<30),"15-30", AND(O12>=30,O12<60),"30-60", AND(O12>=60,O12<90),"60-90", AND(O12>=90,O12<120),"90-120", AND(O12>=120,O12<160),"120-160", AND(O12>=160,O12<200),"160-200", AND(O12>=200,O12<250),"200-250", AND(O12>=250,O12<300),"250-300", O12>=300,">300", TRUE,"Below 0" )} -> 0-5 | AB12: -10.92
A13: 45870 | B13: =TEXT(A13,"yyyy") -> 2025 | C13: Shanti Gold Intern | D13: =IFERROR(LEFT(C13,FIND(" ",C13)-1),C13) -> Shanti | E13: =TRIM(SUBSTITUTE(SUBSTITUTE(C13,"Ltd",""),"Lt","")) -> Shanti Gold Intern | F13: =_xlfn.XLOOKUP(E13,MARKET_PRICE__2[Column2],MARKET_PRICE__2[Column3],"Not found") -> Not found | G13: =_xlfn.XLOOKUP(D13,MARKET_PRICE__2[Column12],MARKET_PRICE__2[Column3],"Not found") -> 210.00 | H13: 360.11 | I13: {=_xlfn.IFS( H13<50,"0-50", H13<100,"50-100", H13<150,"100-150", H13<200,"150-200", H13<250,"200-250", H13<300,"250-300", H13<350,"300-350", H13<400,"350-400", H13<450,"400-450", H13<=500,"450-500", TRUE,"Above 500" )} -> 350-400 | K13: =H13/10 -> 36.011 | N13: {=_xlfn.IFS(H13<500,"0-500",H13<1000,"500-1000",H13<1500,"1000-1500",H13<2000,"1500-2000",H13<2500,"2000-2500",H13<3000,"2500-3000",H13<3500,"3000-3500",H13<4000,"3500-4000",H13<4500,"4000-4500",H13<=5000,"4500-5000",TRUE,"Hbove 5000")} -> 0-500 | O13: 117.33 | P13: 151.48 | Q13: 30.37 | R13: 81.17 | S13: {=_xlfn.IFS( R13<0,"< 0", R13<5,"0 to 5", R13<10,"5 to 10", R13<15,"10 to 15", R13<20,"15 to 20", R13<25,"20 to 25", R13<50,"25 to 50", R13<75,"50 to 75", R13<100,"75 to 100", R13<125,"100 to 125", R13<150,"125 to 150", R13<175,"150 to 175", R13<200,"175 to 200", TRUE,"> 200" )} -> 75 to 100 | T13: 199 | U13: 229.1 | V13: 15.13 | W13: {=_xlfn.IFS( V13<-15,"< -15%", V13<-10,"-15% to -10%", V13<-5,"-10% to -5%", V13<0,"-5% to 0%", V13<10,"0% to 10%", V13<20,"10% to 20%", V13<30,"20% to 30%", V13<40,"30% to 40%", V13<50,"40% to 50%", V13<60,"50% to 60%", V13<70,"60% to 70%", V13<80,"70% to 80%", V13<90,"80% to 90%", V13<100,"90% to 100%", TRUE,"> 100%" )} -> 10% to 20% | X13: 246.25 | Y13: 246.22 | Z13: =IF(V13>0, ">0", IF(V13<0, "<0", "=0")) -> >0 | AA13: {=_xlfn.IFS( AND(O13>=0,O13<5),"0-5", AND(O13>=5,O13<15),"5-15", AND(O13>=15,O13<30),"15-30", AND(O13>=30,O13<60),"30-60", AND(O13>=60,O13<90),"60-90", AND(O13>=90,O13<120),"90-120", AND(O13>=120,O13<160),"120-160", AND(O13>=160,O13<200),"160-200", AND(O13>=200,O13<250),"200-250", AND(O13>=250,O13<300),"250-300", O13>=300,">300", TRUE,"Below 0" )} -> 90-120 | AB13: 23.74
A14: 45869 | B14: =TEXT(A14,"yyyy") -> 2025 | C14: Brigade Hotel Vent | D14: =IFERROR(LEFT(C14,FIND(" ",C14)-1),C14) -> Brigade | E14: =TRIM(SUBSTITUTE(SUBSTITUTE(C14,"Ltd",""),"Lt","")) -> Brigade Hotel Vent | F14: =_xlfn.XLOOKUP(E14,MARKET_PRICE__2[Column2],MARKET_PRICE__2[Column3],"Not found") -> Not found | G14: =_xlfn.XLOOKUP(D14,MARKET_PRICE__2[Column12],MARKET_PRICE__2[Column3],"Not found") -> 81.05 | H14: 759.6 | J14: {=_xlfn.IFS( AND(H14>=500,H14<550),"500-550", AND(H14>=550,H14<600),"550-600", AND(H14>=600,H14<650),"600-650", AND(H14>=650,H14<700),"650-700", AND(H14>=700,H14<750),"700-750", AND(H14>=750,H14<800),"750-800", AND(H14>=800,H14<850),"800-850", AND(H14>=850,H14<900),"850-900", AND(H14>=900,H14<950),"900-950", AND(H14>=950,H14<=1000),"950-1000", H14<500,"Below 500", TRUE,"Above 1000" )} -> 750-800 | K14: =H14/10 -> 75.96 | N14: {=_xlfn.IFS(H14<500,"0-500",H14<1000,"500-1000",H14<1500,"1000-1500",H14<2000,"1500-2000",H14<2500,"2000-2500",H14<3000,"2500-3000",H14<3500,"3000-3500",H14<4000,"3500-4000",H14<4500,"4000-4500",H14<=5000,"4500-5000",TRUE,"Hbove 5000")} -> 500-1000 | O14: 5.42 | P14: 1.92 | Q14: 6.4 | R14: 4.48 | S14: {=_xlfn.IFS( R14<0,"< 0", R14<5,"0 to 5", R14<10,"5 to 10", R14<15,"10 to 15", R14<20,"15 to 20", R14<25,"20 to 25", R14<50,"25 to 50", R14<75,"50 to 75", R14<100,"75 to 100", R14<125,"100 to 125", R14<150,"125 to 150", R14<175,"150 to 175", R14<200,"175 to 200", TRUE,"> 200" )} -> 0 to 5 | T14: 90 | U14: 82 | V14: -8.89 | W14: {=_xlfn.IFS( V14<-15,"< -15%", V14<-10,"-15% to -10%", V14<-5,"-10% to -5%", V14<0,"-5% to 0%", V14<10,"0% to 10%", V14<20,"10% to 20%", V14<30,"20% to 30%", V14<40,"30% to 40%", V14<50,"40% to 50%", V14<60,"50% to 60%", V14<70,"60% to 70%", V14<80,"70% to 80%", V14<90,"80% to 90%", V14<100,"90% to 100%", TRUE,"> 100%" )} -> -10% to -5% | X14: 86.34 | Y14: 86.35 | Z14: =IF(V14>0, ">0", IF(V14<0, "<0", "=0")) -> <0 | AA14: {=_xlfn.IFS( AND(O14>=0,O14<5),"0-5", AND(O14>=5,O14<15),"5-15", AND(O14>=15,O14<30),"15-30", AND(O14>=30,O14<60),"30-60", AND(O14>=60,O14<90),"60-90", AND(O14>=90,O14<120),"90-120", AND(O14>=120,O14<160),"120-160", AND(O14>=160,O14<200),"160-200", AND(O14>=200,O14<250),"200-250", AND(O14>=250,O14<300),"250-300", O14>=300,">300", TRUE,"Below 0" )} -> 5-15 | AB14: -4.07
A15: 45868 | B15: =TEXT(A15,"yyyy") -> 2025 | C15: GNG Electronics Lt | D15: =IFERROR(LEFT(C15,FIND(" ",C15)-1),C15) -> GNG | E15: =TRIM(SUBSTITUTE(SUBSTITUTE(C15,"Ltd",""),"Lt","")) -> GNG Electronics | F15: =_xlfn.XLOOKUP(E15,MARKET_PRICE__2[Column2],MARKET_PRICE__2[Column3],"Not found") -> 344.00 | G15: =_xlfn.XLOOKUP(D15,MARKET_PRICE__2[Column12],MARKET_PRICE__2[Column3],"Not found") -> 344.00 | H15: 460.44 | I15: {=_xlfn.IFS( H15<50,"0-50", H15<100,"50-100", H15<150,"100-150", H15<200,"150-200", H15<250,"200-250", H15<300,"250-300", H15<350,"300-350", H15<400,"350-400", H15<450,"400-450", H15<=500,"450-500", TRUE,"Above 500" )} -> 450-500 | K15: =H15/10 -> 46.044 | N15: {=_xlfn.IFS(H15<500,"0-500",H15<1000,"500-1000",H15<1500,"1000-1500",H15<2000,"1500-2000",H15<2500,"2000-2500",H15<3000,"2500-3000",H15<3500,"3000-3500",H15<4000,"3500-4000",H15<4500,"4000-4500",H15<=5000,"4500-5000",TRUE,"Hbove 5000")} -> 0-500 | O15: 266.21 | P15: 227.67 | Q15: 46.84 | R15: 147.93 | S15: {=_xlfn.IFS( R15<0,"< 0", R15<5,"0 to 5", R15<10,"5 to 10", R15<15,"10 to 15", R15<20,"15 to 20", R15<25,"20 to 25", R15<50,"25 to 50", R15<75,"50 to 75", R15<100,"75 to 100", R15<125,"100 to 125", R15<150,"125 to 150", R15<175,"150 to 175", R15<200,"175 to 200", TRUE,"> 200" )} -> 125 to 150 | T15: 237 | U15: 350 | V15: 47.68 | W15: {=_xlfn.IFS( V15<-15,"< -15%", V15<-10,"-15% to -10%", V15<-5,"-10% to -5%", V15<0,"-5% to 0%", V15<10,"0% to 10%", V15<20,"10% to 20%", V15<30,"20% to 30%", V15<40,"30% to 40%", V15<50,"40% to 50%", V15<60,"50% to 60%", V15<70,"60% to 70%", V15<80,"70% to 80%", V15<90,"80% to 90%", V15<100,"90% to 100%", TRUE,"> 100%" )} -> 40% to 50% | X15: 345.3 | Y15: 344.85 | Z15: =IF(V15>0, ">0", IF(V15<0, "<0", "=0")) -> >0 | AA15: {=_xlfn.IFS( AND(O15>=0,O15<5),"0-5", AND(O15>=5,O15<15),"5-15", AND(O15>=15,O15<30),"15-30", AND(O15>=30,O15<60),"30-60", AND(O15>=60,O15<90),"60-90", AND(O15>=90,O15<120),"90-120", AND(O15>=120,O15<160),"120-160", AND(O15>=160,O15<200),"160-200", AND(O15>=200,O15<250),"200-250", AND(O15>=250,O15<300),"250-300", O15>=300,">300", TRUE,"Below 0" )} -> 250-300 | AB15: 45.7
A16: 45868 | B16: =TEXT(A16,"yyyy") -> 2025 | C16: Indiqube Spaces Lt | D16: =IFERROR(LEFT(C16,FIND(" ",C16)-1),C16) -> Indiqube | E16: =TRIM(SUBSTITUTE(SUBSTITUTE(C16,"Ltd",""),"Lt","")) -> Indiqube Spaces | F16: =_xlfn.XLOOKUP(E16,MARKET_PRICE__2[Column2],MARKET_PRICE__2[Column3],"Not found") -> 225.25 | G16: =_xlfn.XLOOKUP(D16,MARKET_PRICE__2[Column12],MARKET_PRICE__2[Column3],"Not found") -> 225.25 | H16: 700 | J16: {=_xlfn.IFS( AND(H16>=500,H16<550),"500-550", AND(H16>=550,H16<600),"550-600", AND(H16>=600,H16<650),"600-650", AND(H16>=650,H16<700),"650-700", AND(H16>=700,H16<750),"700-750", AND(H16>=750,H16<800),"750-800", AND(H16>=800,H16<850),"800-850", AND(H16>=850,H16<900),"850-900", AND(H16>=900,H16<950),"900-950", AND(H16>=950,H16<=1000),"950-1000", H16<500,"Below 500", TRUE,"Above 1000" )} -> 700-750 | K16: =H16/10 -> 70 | N16: {=_xlfn.IFS(H16<500,"0-500",H16<1000,"500-1000",H16<1500,"1000-1500",H16<2000,"1500-2000",H16<2500,"2000-2500",H16<3000,"2500-3000",H16<3500,"3000-3500",H16<4000,"3500-4000",H16<4500,"4000-4500",H16<=5000,"4500-5000",TRUE,"Hbove 5000")} -> 500-1000 | O16: 14.35 | P16: 8.27 | Q16: 12.9 | R16: 12.41 | S16: {=_xlfn.IFS( R16<0,"< 0", R16<5,"0 to 5", R16<10,"5 to 10", R16<15,"10 to 15", R16<20,"15 to 20", R16<25,"20 to 25", R16<50,"25 to 50", R16<75,"50 to 75", R16<100,"75 to 100", R16<125,"100 to 125", R16<150,"125 to 150", R16<175,"150 to 175", R16<200,"175 to 200", TRUE,"> 200" )} -> 10 to 15 | T16: 237 | U16: 218.7 | V16: -7.72 | W16: {=_xlfn.IFS( V16<-15,"< -15%", V16<-10,"-15% to -10%", V16<-5,"-10% to -5%", V16<0,"-5% to 0%", V16<10,"0% to 10%", V16<20,"10% to 20%", V16<30,"20% to 30%", V16<40,"30% to 40%", V16<50,"40% to 50%", V16<60,"50% to 60%", V16<70,"60% to 70%", V16<80,"70% to 80%", V16<90,"80% to 90%", V16<100,"90% to 100%", TRUE,"> 100%" )} -> -10% to -5% | X16: 227.15 | Y16: 227.23 | Z16: =IF(V16>0, ">0", IF(V16<0, "<0", "=0")) -> <0 | AA16: {=_xlfn.IFS( AND(O16>=0,O16<5),"0-5", AND(O16>=5,O16<15),"5-15", AND(O16>=15,O16<30),"15-30", AND(O16>=30,O16<60),"30-60", AND(O16>=60,O16<90),"60-90", AND(O16>=90,O16<120),"90-120", AND(O16>=120,O16<160),"120-160", AND(O16>=160,O16<200),"160-200", AND(O16>=200,O16<250),"200-250", AND(O16>=250,O16<300),"250-300", O16>=300,">300", TRUE,"Below 0" )} -> 5-15 | AB16: -4.16
A17: 45859 | B17: =TEXT(A17,"yyyy") -> 2025 | C17: Anthem Biosciences | D17: =IFERROR(LEFT(C17,FIND(" ",C17)-1),C17) -> Anthem | E17: =TRIM(SUBSTITUTE(SUBSTITUTE(C17,"Ltd",""),"Lt","")) -> Anthem Biosciences | F17: =_xlfn.XLOOKUP(E17,MARKET_PRICE__2[Column2],MARKET_PRICE__2[Column3],"Not found") -> Not found | G17: =_xlfn.XLOOKUP(D17,MARKET_PRICE__2[Column12],MARKET_PRICE__2[Column3],"Not found") -> 773.80 | H17: 3395 | K17: =H17/10 -> 339.5 | N17: {=_xlfn.IFS(H17<500,"0-500",H17<1000,"500-1000",H17<1500,"1000-1500",H17<2000,"1500-2000",H17<2500,"2000-2500",H17<3000,"2500-3000",H17<3500,"3000-3500",H17<4000,"3500-4000",H17<4500,"4000-4500",H17<=5000,"4500-5000",TRUE,"Hbove 5000")} -> 3000-3500 | O17: 182.65 | P17: 42.36 | Q17: 5.64 | R17: 63.86 | S17: {=_xlfn.IFS( R17<0,"< 0", R17<5,"0 to 5", R17<10,"5 to 10", R17<15,"10 to 15", R17<20,"15 to 20", R17<25,"20 to 25", R17<50,"25 to 50", R17<75,"50 to 75", R17<100,"75 to 100", R17<125,"100 to 125", R17<150,"125 to 150", R17<175,"150 to 175", R17<200,"175 to 200", TRUE,"> 200" )} -> 50 to 75 | T17: 570 | U17: 723.1 | V17: 26.86 | W17: {=_xlfn.IFS( V17<-15,"< -15%", V17<-10,"-15% to -10%", V17<-5,"-10% to -5%", V17<0,"-5% to 0%", V17<10,"0% to 10%", V17<20,"10% to 20%", V17<30,"20% to 30%", V17<40,"30% to 40%", V17<50,"40% to 50%", V17<60,"50% to 60%", V17<70,"60% to 70%", V17<80,"70% to 80%", V17<90,"80% to 90%", V17<100,"90% to 100%", TRUE,"> 100%" )} -> 20% to 30% | X17: 822.7 | Y17: 822.9 | Z17: =IF(V17>0, ">0", IF(V17<0, "<0", "=0")) -> >0 | AA17: {=_xlfn.IFS( AND(O17>=0,O17<5),"0-5", AND(O17>=5,O17<15),"5-15", AND(O17>=15,O17<30),"15-30", AND(O17>=30,O17<60),"30-60", AND(O17>=60,O17<90),"60-90", AND(O17>=90,O17<120),"90-120", AND(O17>=120,O17<160),"120-160", AND(O17>=160,O17<200),"160-200", AND(O17>=200,O17<250),"200-250", AND(O17>=250,O17<300),"250-300", O17>=300,">300", TRUE,"Below 0" )} -> 160-200 | AB17: 44.33
A18: 45855 | B18: =TEXT(A18,"yyyy") -> 2025 | C18: Smartworks Coworki | D18: =IFERROR(LEFT(C18,FIND(" ",C18)-1),C18) -> Smartworks | E18: =TRIM(SUBSTITUTE(SUBSTITUTE(C18,"Ltd",""),"Lt","")) -> Smartworks Coworki | F18: =_xlfn.XLOOKUP(E18,MARKET_PRICE__2[Column2],MARKET_PRICE__2[Column3],"Not found") -> Not found | G18: =_xlfn.XLOOKUP(D18,MARKET_PRICE__2[Column12],MARKET_PRICE__2[Column3],"Not found") -> 603.60 | H18: 582.56 | J18: {=_xlfn.IFS( AND(H18>=500,H18<550),"500-550", AND(H18>=550,H18<600),"550-600", AND(H18>=600,H18<650),"600-650", AND(H18>=650,H18<700),"650-700", AND(H18>=700,H18<750),"700-750", AND(H18>=750,H18<800),"750-800", AND(H18>=800,H18<850),"800-850", AND(H18>=850,H18<900),"850-900", AND(H18>=900,H18<950),"900-950", AND(H18>=950,H18<=1000),"950-1000", H18<500,"Below 500", TRUE,"Above 1000" )} -> 550-600 | K18: =H18/10 -> 58.256 | N18: {=_xlfn.IFS(H18<500,"0-500",H18<1000,"500-1000",H18<1500,"1000-1500",H18<2000,"1500-2000",H18<2500,"2000-2500",H18<3000,"2500-3000",H18<3500,"3000-3500",H18<4000,"3500-4000",H18<4500,"4000-4500",H18<=5000,"4500-5000",TRUE,"Hbove 5000")} -> 500-1000 | O18: 24.41 | P18: 22.78 | Q18: 3.53 | R18: 13.45 | S18: {=_xlfn.IFS( R18<0,"< 0", R18<5,"0 to 5", R18<10,"5 to 10", R18<15,"10 to 15", R18<20,"15 to 20", R18<25,"20 to 25", R18<50,"25 to 50", R18<75,"50 to 75", R18<100,"75 to 100", R18<125,"100 to 125", R18<150,"125 to 150", R18<175,"150 to 175", R18<200,"175 to 200", TRUE,"> 200" )} -> 10 to 15 | T18: 407 | U18: 436.1 | V18: 7.15 | W18: {=_xlfn.IFS( V18<-15,"< -15%", V18<-10,"-15% to -10%", V18<-5,"-10% to -5%", V18<0,"-5% to 0%", V18<10,"0% to 10%", V18<20,"10% to 20%", V18<30,"20% to 30%", V18<40,"30% to 40%", V18<50,"40% to 50%", V18<60,"50% to 60%", V18<70,"60% to 70%", V18<80,"70% to 80%", V18<90,"80% to 90%", V18<100,"90% to 100%", TRUE,"> 100%" )} -> 0% to 10% | X18: 489.85 | Y18: 491.1 | Z18: =IF(V18>0, ">0", IF(V18<0, "<0", "=0")) -> >0 | AA18: {=_xlfn.IFS( AND(O18>=0,O18<5),"0-5", AND(O18>=5,O18<15),"5-15", AND(O18>=15,O18<30),"15-30", AND(O18>=30,O18<60),"30-60", AND(O18>=60,O18<90),"60-90", AND(O18>=90,O18<120),"90-120", AND(O18>=120,O18<160),"120-160", AND(O18>=160,O18<200),"160-200", AND(O18>=200,O18<250),"200-250", AND(O18>=250,O18<300),"250-300", O18>=300,">300", TRUE,"Below 0" )} -> 15-30 | AB18: 20.36
A19: 45852 | B19: =TEXT(A19,"yyyy") -> 2025 | C19: Travel Food Servic | D19: =IFERROR(LEFT(C19,FIND(" ",C19)-1),C19) -> Travel | E19: =TRIM(SUBSTITUTE(SUBSTITUTE(C19,"Ltd",""),"Lt","")) -> Travel Food Servic | F19: =_xlfn.XLOOKUP(E19,MARKET_PRICE__2[Column2],MARKET_PRICE__2[Column3],"Not found") -> Not found | G19: =_xlfn.XLOOKUP(D19,MARKET_PRICE__2[Column12],MARKET_PRICE__2[Column3],"Not found") -> 1346.35 | H19: 2000 | K19: =H19/10 -> 200 | N19: {=_xlfn.IFS(H19<500,"0-500",H19<1000,"500-1000",H19<1500,"1000-1500",H19<2000,"1500-2000",H19<2500,"2000-2500",H19<3000,"2500-3000",H19<3500,"3000-3500",H19<4000,"3500-4000",H19<4500,"4000-4500",H19<=5000,"4500-5000",TRUE,"Hbove 5000")} -> 2000-2500 | O19: 7.7 | P19: 1.58 | Q19: 0.69 | R19: 2.88 | S19: {=_xlfn.IFS( R19<0,"< 0", R19<5,"0 to 5", R19<10,"5 to 10", R19<15,"10 to 15", R19<20,"15 to 20", R19<25,"20 to 25", R19<50,"25 to 50", R19<75,"50 to 75", R19<100,"75 to 100", R19<125,"100 to 125", R19<150,"125 to 150", R19<175,"150 to 175", R19<200,"175 to 200", TRUE,"> 200" )} -> 0 to 5 | T19: 1100 | U19: 1126.2 | V19: 2.38 | W19: {=_xlfn.IFS( V19<-15,"< -15%", V19<-10,"-15% to -10%", V19<-5,"-10% to -5%", V19<0,"-5% to 0%", V19<10,"0% to 10%", V19<20,"10% to 20%", V19<30,"20% to 30%", V19<40,"30% to 40%", V19<50,"40% to 50%", V19<60,"50% to 60%", V19<70,"60% to 70%", V19<80,"70% to 80%", V19<90,"80% to 90%", V19<100,"90% to 100%", TRUE,"> 100%" )} -> 0% to 10% | X19: 1219.4 | Y19: 1220.6 | Z19: =IF(V19>0, ">0", IF(V19<0, "<0", "=0")) -> >0 | AA19: {=_xlfn.IFS( AND(O19>=0,O19<5),"0-5", AND(O19>=5,O19<15),"5-15", AND(O19>=15,O19<30),"15-30", AND(O19>=30,O19<60),"30-60", AND(O19>=60,O19<90),"60-90", AND(O19>=90,O19<120),"90-120", AND(O19>=120,O19<160),"120-160", AND(O19>=160,O19<200),"160-200", AND(O19>=200,O19<250),"200-250", AND(O19>=250,O19<300),"250-300", O19>=300,">300", TRUE,"Below 0" )} -> 5-15 | AB19: 10.85
A20: 45847 | B20: =TEXT(A20,"yyyy") -> 2025 | C20: Crizac Ltd | D20: =IFERROR(LEFT(C20,FIND(" ",C20)-1),C20) -> Crizac | E20: =TRIM(SUBSTITUTE(SUBSTITUTE(C20,"Ltd",""),"Lt","")) -> Crizac | F20: =_xlfn.XLOOKUP(E20,MARKET_PRICE__2[Column2],MARKET_PRICE__2[Column3],"Not found") -> 281.00 | G20: =_xlfn.XLOOKUP(D20,MARKET_PRICE__2[Column12],MARKET_PRICE__2[Column3],"Not found") -> 281.00 | H20: 860 | J20: {=_xlfn.IFS( AND(H20>=500,H20<550),"500-550", AND(H20>=550,H20<600),"550-600", AND(H20>=600,H20<650),"600-650", AND(H20>=650,H20<700),"650-700", AND(H20>=700,H20<750),"700-750", AND(H20>=750,H20<800),"750-800", AND(H20>=800,H20<850),"800-850", AND(H20>=850,H20<900),"850-900", AND(H20>=900,H20<950),"900-950", AND(H20>=950,H20<=1000),"950-1000", H20<500,"Below 500", TRUE,"Above 1000" )} -> 850-900 | K20: =H20/10 -> 86 | N20: {=_xlfn.IFS(H20<500,"0-500",H20<1000,"500-1000",H20<1500,"1000-1500",H20<2000,"1500-2000",H20<2500,"2000-2500",H20<3000,"2500-3000",H20<3500,"3000-3500",H20<4000,"3500-4000",H20<4500,"4000-4500",H20<=5000,"4500-5000",TRUE,"Hbove 5000")} -> 500-1000 | O20: 134.35 | P20: 76.15 | Q20: 10.24 | R20: 59.82 | S20: {=_xlfn.IFS( R20<0,"< 0", R20<5,"0 to 5", R20<10,"5 to 10", R20<15,"10 to 15", R20<20,"15 to 20", R20<25,"20 to 25", R20<50,"25 to 50", R20<75,"50 to 75", R20<100,"75 to 100", R20<125,"100 to 125", R20<150,"125 to 150", R20<175,"150 to 175", R20<200,"175 to 200", TRUE,"> 200" )} -> 50 to 75 | T20: 245 | U20: 280 | V20: 14.29 | W20: {=_xlfn.IFS( V20<-15,"< -15%", V20<-10,"-15% to -10%", V20<-5,"-10% to -5%", V20<0,"-5% to 0%", V20<10,"0% to 10%", V20<20,"10% to 20%", V20<30,"20% to 30%", V20<40,"30% to 40%", V20<50,"40% to 50%", V20<60,"50% to 60%", V20<70,"60% to 70%", V20<80,"70% to 80%", V20<90,"80% to 90%", V20<100,"90% to 100%", TRUE,"> 100%" )} -> 10% to 20% | X20: 351.7 | Y20: 351.6 | Z20: =IF(V20>0, ">0", IF(V20<0, "<0", "=0")) -> >0 | AA20: {=_xlfn.IFS( AND(O20>=0,O20<5),"0-5", AND(O20>=5,O20<15),"5-15", AND(O20>=15,O20<30),"15-30", AND(O20>=30,O20<60),"30-60", AND(O20>=60,O20<90),"60-90", AND(O20>=90,O20<120),"90-120", AND(O20>=120,O20<160),"120-160", AND(O20>=160,O20<200),"160-200", AND(O20>=200,O20<250),"200-250", AND(O20>=250,O20<300),"250-300", O20>=300,">300", TRUE,"Below 0" )} -> 120-160 | AB20: 43.55
A21: 45841 | B21: =TEXT(A21,"yyyy") -> 2025 | C21: Indogulf Cropscien | D21: =IFERROR(LEFT(C21,FIND(" ",C21)-1),C21) -> Indogulf | E21: =TRIM(SUBSTITUTE(SUBSTITUTE(C21,"Ltd",""),"Lt","")) -> Indogulf Cropscien | F21: =_xlfn.XLOOKUP(E21,MARKET_PRICE__2[Column2],MARKET_PRICE__2[Column3],"Not found") -> Not found | G21: =_xlfn.XLOOKUP(D21,MARKET_PRICE__2[Column12],MARKET_PRICE__2[Column3],"Not found") -> 103.10 | H21: 200 | I21: {=_xlfn.IFS( H21<50,"0-50", H21<100,"50-100", H21<150,"100-150", H21<200,"150-200", H21<250,"200-250", H21<300,"250-300", H21<350,"300-350", H21<400,"350-400", H21<450,"400-450", H21<=500,"450-500", TRUE,"Above 500" )} -> 200-250 | K21: =H21/10 -> 20 | N21: {=_xlfn.IFS(H21<500,"0-500",H21<1000,"500-1000",H21<1500,"1000-1500",H21<2000,"1500-2000",H21<2500,"2000-2500",H21<3000,"2500-3000",H21<3500,"3000-3500",H21<4000,"3500-4000",H21<4500,"4000-4500",H21<=5000,"4500-5000",TRUE,"Hbove 5000")} -> 0-500 | O21: 33.26 | P21: 48.39 | Q21: 14.78 | R21: 25.98 | S21: {=_xlfn.IFS( R21<0,"< 0", R21<5,"0 to 5", R21<10,"5 to 10", R21<15,"10 to 15", R21<20,"15 to 20", R21<25,"20 to 25", R21<50,"25 to 50", R21<75,"50 to 75", R21<100,"75 to 100", R21<125,"100 to 125", R21<150,"125 to 150", R21<175,"150 to 175", R21<200,"175 to 200", TRUE,"> 200" )} -> 25 to 50 | T21: 111 | U21: 111 | V21: 0 | W21: {=_xlfn.IFS( V21<-15,"< -15%", V21<-10,"-15% to -10%", V21<-5,"-10% to -5%", V21<0,"-5% to 0%", V21<10,"0% to 10%", V21<20,"10% to 20%", V21<30,"20% to 30%", V21<40,"30% to 40%", V21<50,"40% to 50%", V21<60,"50% to 60%", V21<70,"60% to 70%", V21<80,"70% to 80%", V21<90,"80% to 90%", V21<100,"90% to 100%", TRUE,"> 100%" )} -> 0% to 10% | X21: 115 | Y21: 115.03 | Z21: =IF(V21>0, ">0", IF(V21<0, "<0", "=0")) -> =0 | AA21: {=_xlfn.IFS( AND(O21>=0,O21<5),"0-5", AND(O21>=5,O21<15),"5-15", AND(O21>=15,O21<30),"15-30", AND(O21>=30,O21<60),"30-60", AND(O21>=60,O21<90),"60-90", AND(O21>=90,O21<120),"90-120", AND(O21>=120,O21<160),"120-160", AND(O21>=160,O21<200),"160-200", AND(O21>=200,O21<250),"200-250", AND(O21>=250,O21<300),"250-300", O21>=300,">300", TRUE,"Below 0" )} -> 30-60 | AB21: 3.6
A22: 45840 | B22: =TEXT(A22,"yyyy") -> 2025 | C22: HDB Financial Serv | D22: =IFERROR(LEFT(C22,FIND(" ",C22)-1),C22) -> HDB | E22: =TRIM(SUBSTITUTE(SUBSTITUTE(C22,"Ltd",""),"Lt","")) -> HDB Financial Serv | F22: =_xlfn.XLOOKUP(E22,MARKET_PRICE__2[Column2],MARKET_PRICE__2[Column3],"Not found") -> Not found | G22: =_xlfn.XLOOKUP(D22,MARKET_PRICE__2[Column12],MARKET_PRICE__2[Column3],"Not found") -> 733.05 | H22: 12500 | K22: =H22/10 -> 1250 | N22: {=_xlfn.IFS(H22<500,"0-500",H22<1000,"500-1000",H22<1500,"1000-1500",H22<2000,"1500-2000",H22<2500,"2000-2500",H22<3000,"2500-3000",H22<3500,"3000-3500",H22<4000,"3500-4000",H22<4500,"4000-4500",H22<=5000,"4500-5000",TRUE,"Hbove 5000")} -> Hbove 5000 | O22: 55.47 | P22: 9.99 | Q22: 1.41 | R22: 16.69 | S22: {=_xlfn.IFS( R22<0,"< 0", R22<5,"0 to 5", R22<10,"5 to 10", R22<15,"10 to 15", R22<20,"15 to 20", R22<25,"20 to 25", R22<50,"25 to 50", R22<75,"50 to 75", R22<100,"75 to 100", R22<125,"100 to 125", R22<150,"125 to 150", R22<175,"150 to 175", R22<200,"175 to 200", TRUE,"> 200" )} -> 15 to 20 | T22: 740 | U22: 835 | V22: 12.84 | W22: {=_xlfn.IFS( V22<-15,"< -15%", V22<-10,"-15% to -10%", V22<-5,"-10% to -5%", V22<0,"-5% to 0%", V22<10,"0% to 10%", V22<20,"10% to 20%", V22<30,"20% to 30%", V22<40,"30% to 40%", V22<50,"40% to 50%", V22<60,"50% to 60%", V22<70,"60% to 70%", V22<80,"70% to 80%", V22<90,"80% to 90%", V22<100,"90% to 100%", TRUE,"> 100%" )} -> 10% to 20% | X22: 795.3 | Y22: 795.3 | Z22: =IF(V22>0, ">0", IF(V22<0, "<0", "=0")) -> >0 | AA22: {=_xlfn.IFS( AND(O22>=0,O22<5),"0-5", AND(O22>=5,O22<15),"5-15", AND(O22>=15,O22<30),"15-30", AND(O22>=30,O22<60),"30-60", AND(O22>=60,O22<90),"60-90", AND(O22>=90,O22<120),"90-120", AND(O22>=120,O22<160),"120-160", AND(O22>=160,O22<200),"160-200", AND(O22>=200,O22<250),"200-250", AND(O22>=250,O22<300),"250-300", O22>=300,">300", TRUE,"Below 0" )} -> 30-60 | AB22: 7.47
A23: 45840 | B23: =TEXT(A23,"yyyy") -> 2025 | C23: Sambhv Steel Tubes | D23: =IFERROR(LEFT(C23,FIND(" ",C23)-1),C23) -> Sambhv | E23: =TRIM(SUBSTITUTE(SUBSTITUTE(C23,"Ltd",""),"Lt","")) -> Sambhv Steel Tubes | F23: =_xlfn.XLOOKUP(E23,MARKET_PRICE__2[Column2],MARKET_PRICE__2[Column3],"Not found") -> Not found | G23: =_xlfn.XLOOKUP(D23,MARKET_PRICE__2[Column12],MARKET_PRICE__2[Column3],"Not found") -> 115.35 | H23: 540 | J23: {=_xlfn.IFS( AND(H23>=500,H23<550),"500-550", AND(H23>=550,H23<600),"550-600", AND(H23>=600,H23<650),"600-650", AND(H23>=650,H23<700),"650-700", AND(H23>=700,H23<750),"700-750", AND(H23>=750,H23<800),"750-800", AND(H23>=800,H23<850),"800-850", AND(H23>=850,H23<900),"850-900", AND(H23>=900,H23<950),"900-950", AND(H23>=950,H23<=1000),"950-1000", H23<500,"Below 500", TRUE,"Above 1000" )} -> 500-550 | K23: =H23/10 -> 54 | N23: {=_xlfn.IFS(H23<500,"0-500",H23<1000,"500-1000",H23<1500,"1000-1500",H23<2000,"1500-2000",H23<2500,"2000-2500",H23<3000,"2500-3000",H23<3500,"3000-3500",H23<4000,"3500-4000",H23<4500,"4000-4500",H23<=5000,"4500-5000",TRUE,"Hbove 5000")} -> 500-1000 | O23: 62.32 | P23: 31.82 | Q23: 7.99 | R23: 28.46 | S23: {=_xlfn.IFS( R23<0,"< 0", R23<5,"0 to 5", R23<10,"5 to 10", R23<15,"10 to 15", R23<20,"15 to 20", R23<25,"20 to 25", R23<50,"25 to 50", R23<75,"50 to 75", R23<100,"75 to 100", R23<125,"100 to 125", R23<150,"125 to 150", R23<175,"150 to 175", R23<200,"175 to 200", TRUE,"> 200" )} -> 25 to 50 | T23: 82 | U23: 110.1 | V23: 34.27 | W23: {=_xlfn.IFS( V23<-15,"< -15%", V23<-10,"-15% to -10%", V23<-5,"-10% to -5%", V23<0,"-5% to 0%", V23<10,"0% to 10%", V23<20,"10% to 20%", V23<30,"20% to 30%", V23<40,"30% to 40%", V23<50,"40% to 50%", V23<60,"50% to 60%", V23<70,"60% to 70%", V23<80,"70% to 80%", V23<90,"80% to 90%", V23<100,"90% to 100%", TRUE,"> 100%" )} -> 30% to 40% | X23: 129.65 | Y23: 129.56 | Z23: =IF(V23>0, ">0", IF(V23<0, "<0", "=0")) -> >0 | AA23: {=_xlfn.IFS( AND(O23>=0,O23<5),"0-5", AND(O23>=5,O23<15),"5-15", AND(O23>=15,O23<30),"15-30", AND(O23>=30,O23<60),"30-60", AND(O23>=60,O23<90),"60-90", AND(O23>=90,O23<120),"90-120", AND(O23>=120,O23<160),"120-160", AND(O23>=160,O23<200),"160-200", AND(O23>=200,O23<250),"200-250", AND(O23>=250,O23<300),"250-300", O23>=300,">300", TRUE,"Below 0" )} -> 60-90 | AB23: 58.11
A24: 45839 | B24: =TEXT(A24,"yyyy") -> 2025 | C24: Globe Civil Projec | D24: =IFERROR(LEFT(C24,FIND(" ",C24)-1),C24) -> Globe | E24: =TRIM(SUBSTITUTE(SUBSTITUTE(C24,"Ltd",""),"Lt","")) -> Globe Civil Projec | F24: =_xlfn.XLOOKUP(E24,MARKET_PRICE__2[Column2],MARKET_PRICE__2[Column3],"Not found") -> Not found | G24: =_xlfn.XLOOKUP(D24,MARKET_PRICE__2[Column12],MARKET_PRICE__2[Column3],"Not found") -> 25.30 | H24: 119 | I24: {=_xlfn.IFS( H24<50,"0-50", H24<100,"50-100", H24<150,"100-150", H24<200,"150-200", H24<250,"200-250", H24<300,"250-300", H24<350,"300-350", H24<400,"350-400", H24<450,"400-450", H24<=500,"450-500", TRUE,"Above 500" )} -> 100-150 | K24: =H24/10 -> 11.9 | N24: {=_xlfn.IFS(H24<500,"0-500",H24<1000,"500-1000",H24<1500,"1000-1500",H24<2000,"1500-2000",H24<2500,"2000-2500",H24<3000,"2500-3000",H24<3500,"3000-3500",H24<4000,"3500-4000",H24<4500,"4000-4500",H24<=5000,"4500-5000",TRUE,"Hbove 5000")} -> 0-500 | O24: 99.76 | P24: 143.15 | Q24: 53.72 | R24: 86.04 | S24: {=_xlfn.IFS( R24<0,"< 0", R24<5,"0 to 5", R24<10,"5 to 10", R24<15,"10 to 15", R24<20,"15 to 20", R24<25,"20 to 25", R24<50,"25 to 50", R24<75,"50 to 75", R24<100,"75 to 100", R24<125,"100 to 125", R24<150,"125 to 150", R24<175,"150 to 175", R24<200,"175 to 200", TRUE,"> 200" )} -> 75 to 100 | T24: 71 | U24: 91.1 | V24: 28.31 | W24: {=_xlfn.IFS( V24<-15,"< -15%", V24<-10,"-15% to -10%", V24<-5,"-10% to -5%", V24<0,"-5% to 0%", V24<10,"0% to 10%", V24<20,"10% to 20%", V24<30,"20% to 30%", V24<40,"30% to 40%", V24<50,"40% to 50%", V24<60,"50% to 60%", V24<70,"60% to 70%", V24<80,"70% to 80%", V24<90,"80% to 90%", V24<100,"90% to 100%", TRUE,"> 100%" )} -> 20% to 30% | X24: 80.14 | Y24: 80.19 | Z24: =IF(V24>0, ">0", IF(V24<0, "<0", "=0")) -> >0 | AA24: {=_xlfn.IFS( AND(O24>=0,O24<5),"0-5", AND(O24>=5,O24<15),"5-15", AND(O24>=15,O24<30),"15-30", AND(O24>=30,O24<60),"30-60", AND(O24>=60,O24<90),"60-90", AND(O24>=90,O24<120),"90-120", AND(O24>=120,O24<160),"120-160", AND(O24>=160,O24<200),"160-200", AND(O24>=200,O24<250),"200-250", AND(O24>=250,O24<300),"250-300", O24>=300,">300", TRUE,"Below 0" )} -> 90-120 | AB24: 12.87
A25: 45839 | B25: =TEXT(A25,"yyyy") -> 2025 | C25: Kalpataru Ltd | D25: =IFERROR(LEFT(C25,FIND(" ",C25)-1),C25) -> Kalpataru | E25: =TRIM(SUBSTITUTE(SUBSTITUTE(C25,"Ltd",""),"Lt","")) -> Kalpataru | F25: =_xlfn.XLOOKUP(E25,MARKET_PRICE__2[Column2],MARKET_PRICE__2[Column3],"Not found") -> Not found | G25: =_xlfn.XLOOKUP(D25,MARKET_PRICE__2[Column12],MARKET_PRICE__2[Column3],"Not found") -> 1251.60 | H25: 1590 | K25: =H25/10 -> 159 | M25: {=_xlfn.IFS( AND(H25>=1000,H25<1050),"1000-1050", AND(H25>=1050,H25<1100),"1050-1100", AND(H25>=1100,H25<1150),"1100-1150", AND(H25>=1150,H25<1200),"1150-1200", AND(H25>=1200,H25<1250),"1200-1250", AND(H25>=1250,H25<1300),"1250-1300", AND(H25>=1300,H25<1350),"1300-1350", AND(H25>=1350,H25<1400),"1350-1400", AND(H25>=1400,H25<1450),"1400-1450", AND(H25>=1450,H25<1500),"1450-1500", AND(H25>=1500,H25<1550),"1500-1550", AND(H25>=1550,H25<1600),"1550-1600", AND(H25>=1600,H25<1650),"1600-1650", AND(H25>=1650,H25<1700),"1650-1700", AND(H25>=1700,H25<1750),"1700-1750", AND(H25>=1750,H25<1800),"1750-1800", AND(H25>=1800,H25<1850),"1800-1850", AND(H25>=1850,H25<1900),"1850-1900", AND(H25>=1900,H25<1950),"1900-1950", AND(H25>=1950,H25<=2000),"1950-2000", H25<1000,"Below 1000", TRUE,"Above 2000" )} -> 1550-1600 | N25: {=_xlfn.IFS(H25<500,"0-500",H25<1000,"500-1000",H25<1500,"1000-1500",H25<2000,"1500-2000",H25<2500,"2000-2500",H25<3000,"2500-3000",H25<3500,"3000-3500",H25<4000,"3500-4000",H25<4500,"4000-4500",H25<=5000,"4500-5000",TRUE,"Hbove 5000")} -> 1500-2000 | O25: 3.12 | P25: 1.31 | Q25: 1.29 | R25: 2.26 | S25: {=_xlfn.IFS( R25<0,"< 0", R25<5,"0 to 5", R25<10,"5 to 10", R25<15,"10 to 15", R25<20,"15 to 20", R25<25,"20 to 25", R25<50,"25 to 50", R25<75,"50 to 75", R25<100,"75 to 100", R25<125,"100 to 125", R25<150,"125 to 150", R25<175,"150 to 175", R25<200,"175 to 200", TRUE,"> 200" )} -> 0 to 5 | T25: 414 | U25: 414.1 | V25: 0.02 | W25: {=_xlfn.IFS( V25<-15,"< -15%", V25<-10,"-15% to -10%", V25<-5,"-10% to -5%", V25<0,"-5% to 0%", V25<10,"0% to 10%", V25<20,"10% to 20%", V25<30,"20% to 30%", V25<40,"30% to 40%", V25<50,"40% to 50%", V25<60,"50% to 60%", V25<70,"60% to 70%", V25<80,"70% to 80%", V25<90,"80% to 90%", V25<100,"90% to 100%", TRUE,"> 100%" )} -> 0% to 10% | X25: 386.3 | Y25: 386.2 | Z25: =IF(V25>0, ">0", IF(V25<0, "<0", "=0")) -> >0 | AA25: {=_xlfn.IFS( AND(O25>=0,O25<5),"0-5", AND(O25>=5,O25<15),"5-15", AND(O25>=15,O25<30),"15-30", AND(O25>=30,O25<60),"30-60", AND(O25>=60,O25<90),"60-90", AND(O25>=90,O25<120),"90-120", AND(O25>=120,O25<160),"120-160", AND(O25>=160,O25<200),"160-200", AND(O25>=200,O25<250),"200-250", AND(O25>=250,O25<300),"250-300", O25>=300,">300", TRUE,"Below 0" )} -> 0-5 | AB25: -6.69
A26: 45839 | B26: =TEXT(A26,"yyyy") -> 2025 | C26: Ellenbarrie Indust | D26: =IFERROR(LEFT(C26,FIND(" ",C26)-1),C26) -> Ellenbarrie | E26: =TRIM(SUBSTITUTE(SUBSTITUTE(C26,"Ltd",""),"Lt","")) -> Ellenbarrie Indust | F26: =_xlfn.XLOOKUP(E26,MARKET_PRICE__2[Column2],MARKET_PRICE__2[Column3],"Not found") -> Not found | G26: =_xlfn.XLOOKUP(D26,MARKET_PRICE__2[Column12],MARKET_PRICE__2[Column3],"Not found") -> Not found | H26: 852.53 | J26: {=_xlfn.IFS( AND(H26>=500,H26<550),"500-550", AND(H26>=550,H26<600),"550-600", AND(H26>=600,H26<650),"600-650", AND(H26>=650,H26<700),"650-700", AND(H26>=700,H26<750),"700-750", AND(H26>=750,H26<800),"750-800", AND(H26>=800,H26<850),"800-850", AND(H26>=850,H26<900),"850-900", AND(H26>=900,H26<950),"900-950", AND(H26>=950,H26<=1000),"950-1000", H26<500,"Below 500", TRUE,"Above 1000" )} -> 850-900 | K26: =H26/10 -> 85.253 | N26: {=_xlfn.IFS(H26<500,"0-500",H26<1000,"500-1000",H26<1500,"1000-1500",H26<2000,"1500-2000",H26<2500,"2000-2500",H26<3000,"2500-3000",H26<3500,"3000-3500",H26<4000,"3500-4000",H26<4500,"4000-4500",H26<=5000,"4500-5000",TRUE,"Hbove 5000")} -> 500-1000 | O26: 64.23 | P26: 15.21 | Q26: 2.14 | R26: 22.19 | S26: {=_xlfn.IFS( R26<0,"< 0", R26<5,"0 to 5", R26<10,"5 to 10", R26<15,"10 to 15", R26<20,"15 to 20", R26<25,"20 to 25", R26<50,"25 to 50", R26<75,"50 to 75", R26<100,"75 to 100", R26<125,"100 to 125", R26<150,"125 to 150", R26<175,"150 to 175", R26<200,"175 to 200", TRUE,"> 200" )} -> 20 to 25 | T26: 400 | U26: 492 | V26: 23 | W26: {=_xlfn.IFS( V26<-15,"< -15%", V26<-10,"-15% to -10%", V26<-5,"-10% to -5%", V26<0,"-5% to 0%", V26<10,"0% to 10%", V26<20,"10% to 20%", V26<30,"20% to 30%", V26<40,"30% to 40%", V26<50,"40% to 50%", V26<60,"50% to 60%", V26<70,"60% to 70%", V26<80,"70% to 80%", V26<90,"80% to 90%", V26<100,"90% to 100%", TRUE,"> 100%" )} -> 20% to 30% | X26: 527.3 | Y26: 527.4 | Z26: =IF(V26>0, ">0", IF(V26<0, "<0", "=0")) -> >0 | AA26: {=_xlfn.IFS( AND(O26>=0,O26<5),"0-5", AND(O26>=5,O26<15),"5-15", AND(O26>=15,O26<30),"15-30", AND(O26>=30,O26<60),"30-60", AND(O26>=60,O26<90),"60-90", AND(O26>=90,O26<120),"90-120", AND(O26>=120,O26<160),"120-160", AND(O26>=160,O26<200),"160-200", AND(O26>=200,O26<250),"200-250", AND(O26>=250,O26<300),"250-300", O26>=300,">300", TRUE,"Below 0" )} -> 60-90 | AB26: 31.83
A27: 45833 | B27: =TEXT(A27,"yyyy") -> 2025 | C27: Arisinfra Solution | D27: =IFERROR(LEFT(C27,FIND(" ",C27)-1),C27) -> Arisinfra | E27: =TRIM(SUBSTITUTE(SUBSTITUTE(C27,"Ltd",""),"Lt","")) -> Arisinfra Solution | F27: =_xlfn.XLOOKUP(E27,MARKET_PRICE__2[Column2],MARKET_PRICE__2[Column3],"Not found") -> Not found | G27: =_xlfn.XLOOKUP(D27,MARKET_PRICE__2[Column12],MARKET_PRICE__2[Column3],"Not found") -> 158.50 | H27: 499.6 | I27: {=_xlfn.IFS( H27<50,"0-50", H27<100,"50-100", H27<150,"100-150", H27<200,"150-200", H27<250,"200-250", H27<300,"250-300", H27<350,"300-350", H27<400,"350-400", H27<450,"400-450", H27<=500,"450-500", TRUE,"Above 500" )} -> 450-500 | K27: =H27/10 -> 49.96 | N27: {=_xlfn.IFS(H27<500,"0-500",H27<1000,"500-1000",H27<1500,"1000-1500",H27<2000,"1500-2000",H27<2500,"2000-2500",H27<3000,"2500-3000",H27<3500,"3000-3500",H27<4000,"3500-4000",H27<4500,"4000-4500",H27<=5000,"4500-5000",TRUE,"Hbove 5000")} -> 0-500 | O27: 1.42 | P27: 3.14 | Q27: 5.59 | R27: 2.65 | S27: {=_xlfn.IFS( R27<0,"< 0", R27<5,"0 to 5", R27<10,"5 to 10", R27<15,"10 to 15", R27<20,"15 to 20", R27<25,"20 to 25", R27<50,"25 to 50", R27<75,"50 to 75", R27<100,"75 to 100", R27<125,"100 to 125", R27<150,"125 to 150", R27<175,"150 to 175", R27<200,"175 to 200", TRUE,"> 200" )} -> 0 to 5 | T27: 222 | U27: 209.1 | V27: -5.81 | W27: {=_xlfn.IFS( V27<-15,"< -15%", V27<-10,"-15% to -10%", V27<-5,"-10% to -5%", V27<0,"-5% to 0%", V27<10,"0% to 10%", V27<20,"10% to 20%", V27<30,"20% to 30%", V27<40,"30% to 40%", V27<50,"40% to 50%", V27<60,"50% to 60%", V27<70,"60% to 70%", V27<80,"70% to 80%", V27<90,"80% to 90%", V27<100,"90% to 100%", TRUE,"> 100%" )} -> -10% to -5% | X27: 144.4 | Y27: 143.91 | Z27: =IF(V27>0, ">0", IF(V27<0, "<0", "=0")) -> <0 | AA27: {=_xlfn.IFS( AND(O27>=0,O27<5),"0-5", AND(O27>=5,O27<15),"5-15", AND(O27>=15,O27<30),"15-30", AND(O27>=30,O27<60),"30-60", AND(O27>=60,O27<90),"60-90", AND(O27>=90,O27<120),"90-120", AND(O27>=120,O27<160),"120-160", AND(O27>=160,O27<200),"160-200", AND(O27>=200,O27<250),"200-250", AND(O27>=250,O27<300),"250-300", O27>=300,">300", TRUE,"Below 0" )} -> 0-5 | AB27: -34.95
A28: 45828 | B28: =TEXT(A28,"yyyy") -> 2025 | C28: Oswal Pumps Ltd | D28: =IFERROR(LEFT(C28,FIND(" ",C28)-1),C28) -> Oswal | E28: =TRIM(SUBSTITUTE(SUBSTITUTE(C28,"Ltd",""),"Lt","")) -> Oswal Pumps | F28: =_xlfn.XLOOKUP(E28,MARKET_PRICE__2[Column2],MARKET_PRICE__2[Column3],"Not found") -> 729.00 | G28: =_xlfn.XLOOKUP(D28,MARKET_PRICE__2[Column12],MARKET_PRICE__2[Column3],"Not found") -> 729.00 | H28: 1387.34 | K28: =H28/10 -> 138.734 | L28: {=_xlfn.IFS( AND(H28>=1000,H28<1050),"1000-1050", AND(H28>=1050,H28<1100),"1050-1100", AND(H28>=1100,H28<1150),"1100-1150", AND(H28>=1150,H28<1200),"1150-1200", AND(H28>=1200,H28<1250),"1200-1250", AND(H28>=1250,H28<1300),"1250-1300", AND(H28>=1300,H28<1350),"1300-1350", AND(H28>=1350,H28<1400),"1350-1400", AND(H28>=1400,H28<1450),"1400-1450", AND(H28>=1450,H28<=1500),"1450-1500", H28<1000,"Below 1000", TRUE,"Above 1500" )} -> 1350-1400 | N28: {=_xlfn.IFS(H28<500,"0-500",H28<1000,"500-1000",H28<1500,"1000-1500",H28<2000,"1500-2000",H28<2500,"2000-2500",H28<3000,"2500-3000",H28<3500,"3000-3500",H28<4000,"3500-4000",H28<4500,"4000-4500",H28<=5000,"4500-5000",TRUE,"Hbove 5000")} -> 1000-1500 | O28: 88.08 | P28: 36.7 | Q28: 3.6 | R28: 34.42 | S28: {=_xlfn.IFS( R28<0,"< 0", R28<5,"0 to 5", R28<10,"5 to 10", R28<15,"10 to 15", R28<20,"15 to 20", R28<25,"20 to 25", R28<50,"25 to 50", R28<75,"50 to 75", R28<100,"75 to 100", R28<125,"100 to 125", R28<150,"125 to 150", R28<175,"150 to 175", R28<200,"175 to 200", TRUE,"> 200" )} -> 25 to 50 | T28: 614 | U28: 632 | V28: 2.93 | W28: {=_xlfn.IFS( V28<-15,"< -15%", V28<-10,"-15% to -10%", V28<-5,"-10% to -5%", V28<0,"-5% to 0%", V28<10,"0% to 10%", V28<20,"10% to 20%", V28<30,"20% to 30%", V28<40,"30% to 40%", V28<50,"40% to 50%", V28<60,"50% to 60%", V28<70,"60% to 70%", V28<80,"70% to 80%", V28<90,"80% to 90%", V28<100,"90% to 100%", TRUE,"> 100%" )} -> 0% to 10% | X28: 873.8 | Y28: 873.8 | Z28: =IF(V28>0, ">0", IF(V28<0, "<0", "=0")) -> >0 | AA28: {=_xlfn.IFS( AND(O28>=0,O28<5),"0-5", AND(O28>=5,O28<15),"5-15", AND(O28>=15,O28<30),"15-30", AND(O28>=30,O28<60),"30-60", AND(O28>=60,O28<90),"60-90", AND(O28>=90,O28<120),"90-120", AND(O28>=120,O28<160),"120-160", AND(O28>=160,O28<200),"160-200", AND(O28>=200,O28<250),"200-250", AND(O28>=250,O28<300),"250-300", O28>=300,">300", TRUE,"Below 0" )} -> 60-90 | AB28: 42.31
A29: 45812 | B29: =TEXT(A29,"yyyy") -> 2025 | C29: Scoda Tubes Ltd | D29: =IFERROR(LEFT(C29,FIND(" ",C29)-1),C29) -> Scoda | E29: =TRIM(SUBSTITUTE(SUBSTITUTE(C29,"Ltd",""),"Lt","")) -> Scoda Tubes | F29: =_xlfn.XLOOKUP(E29,MARKET_PRICE__2[Column2],MARKET_PRICE__2[Column3],"Not found") -> 172.00 | G29: =_xlfn.XLOOKUP(D29,MARKET_PRICE__2[Column12],MARKET_PRICE__2[Column3],"Not found") -> 172.00 | H29: 220 | I29: {=_xlfn.IFS( H29<50,"0-50", H29<100,"50-100", H29<150,"100-150", H29<200,"150-200", H29<250,"200-250", H29<300,"250-300", H29<350,"300-350", H29<400,"350-400", H29<450,"400-450", H29<=500,"450-500", TRUE,"Above 500" )} -> 200-250 | K29: =H29/10 -> 22 | N29: {=_xlfn.IFS(H29<500,"0-500",H29<1000,"500-1000",H29<1500,"1000-1500",H29<2000,"1500-2000",H29<2500,"2000-2500",H29<3000,"2500-3000",H29<3500,"3000-3500",H29<4000,"3500-4000",H29<4500,"4000-4500",H29<=5000,"4500-5000",TRUE,"Hbove 5000")} -> 0-500 | O29: 69.51 | P29: 113.03 | Q29: 19.4 | R29: 53.78 | S29: {=_xlfn.IFS( R29<0,"< 0", R29<5,"0 to 5", R29<10,"5 to 10", R29<15,"10 to 15", R29<20,"15 to 20", R29<25,"20 to 25", R29<50,"25 to 50", R29<75,"50 to 75", R29<100,"75 to 100", R29<125,"100 to 125", R29<150,"125 to 150", R29<175,"150 to 175", R29<200,"175 to 200", TRUE,"> 200" )} -> 50 to 75 | T29: 140 | U29: 140 | V29: 0 | W29: {=_xlfn.IFS( V29<-15,"< -15%", V29<-10,"-15% to -10%", V29<-5,"-10% to -5%", V29<0,"-5% to 0%", V29<10,"0% to 10%", V29<20,"10% to 20%", V29<30,"20% to 30%", V29<40,"30% to 40%", V29<50,"40% to 50%", V29<60,"50% to 60%", V29<70,"60% to 70%", V29<80,"70% to 80%", V29<90,"80% to 90%", V29<100,"90% to 100%", TRUE,"> 100%" )} -> 0% to 10% | X29: 171.65 | Y29: 171.11 | Z29: =IF(V29>0, ">0", IF(V29<0, "<0", "=0")) -> =0 | AA29: {=_xlfn.IFS( AND(O29>=0,O29<5),"0-5", AND(O29>=5,O29<15),"5-15", AND(O29>=15,O29<30),"15-30", AND(O29>=30,O29<60),"30-60", AND(O29>=60,O29<90),"60-90", AND(O29>=90,O29<120),"90-120", AND(O29>=120,O29<160),"120-160", AND(O29>=160,O29<200),"160-200", AND(O29>=200,O29<250),"200-250", AND(O29>=250,O29<300),"250-300", O29>=300,">300", TRUE,"Below 0" )} -> 60-90 | AB29: 22.61
A30: 45811 | B30: =TEXT(A30,"yyyy") -> 2025 | C30: Prostarm Info Syst | D30: =IFERROR(LEFT(C30,FIND(" ",C30)-1),C30) -> Prostarm | E30: =TRIM(SUBSTITUTE(SUBSTITUTE(C30,"Ltd",""),"Lt","")) -> Prostarm Info Syst | F30: =_xlfn.XLOOKUP(E30,MARKET_PRICE__2[Column2],MARKET_PRICE__2[Column3],"Not found") -> Not found | G30: =_xlfn.XLOOKUP(D30,MARKET_PRICE__2[Column12],MARKET_PRICE__2[Column3],"Not found") -> 193.85 | H30: 168 | I30: {=_xlfn.IFS( H30<50,"0-50", H30<100,"50-100", H30<150,"100-150", H30<200,"150-200", H30<250,"200-250", H30<300,"250-300", H30<350,"300-350", H30<400,"350-400", H30<450,"400-450", H30<=500,"450-500", TRUE,"Above 500" )} -> 150-200 | K30: =H30/10 -> 16.8 | N30: {=_xlfn.IFS(H30<500,"0-500",H30<1000,"500-1000",H30<1500,"1000-1500",H30<2000,"1500-2000",H30<2500,"2000-2500",H30<3000,"2500-3000",H30<3500,"3000-3500",H30<4000,"3500-4000",H30<4500,"4000-4500",H30<=5000,"4500-5000",TRUE,"Hbove 5000")} -> 0-500 | O30: 104.49 | P30: 222.14 | Q30: 39.49 | R30: 97.2 | S30: {=_xlfn.IFS( R30<0,"< 0", R30<5,"0 to 5", R30<10,"5 to 10", R30<15,"10 to 15", R30<20,"15 to 20", R30<25,"20 to 25", R30<50,"25 to 50", R30<75,"50 to 75", R30<100,"75 to 100", R30<125,"100 to 125", R30<150,"125 to 150", R30<175,"150 to 175", R30<200,"175 to 200", TRUE,"> 200" )} -> 75 to 100 | T30: 105 | U30: 125 | V30: 19.05 | W30: {=_xlfn.IFS( V30<-15,"< -15%", V30<-10,"-15% to -10%", V30<-5,"-10% to -5%", V30<0,"-5% to 0%", V30<10,"0% to 10%", V30<20,"10% to 20%", V30<30,"20% to 30%", V30<40,"30% to 40%", V30<50,"40% to 50%", V30<60,"50% to 60%", V30<70,"60% to 70%", V30<80,"70% to 80%", V30<90,"80% to 90%", V30<100,"90% to 100%", TRUE,"> 100%" )} -> 10% to 20% | X30: 203.45 | Y30: 203.26 | Z30: =IF(V30>0, ">0", IF(V30<0, "<0", "=0")) -> >0 | AA30: {=_xlfn.IFS( AND(O30>=0,O30<5),"0-5", AND(O30>=5,O30<15),"5-15", AND(O30>=15,O30<30),"15-30", AND(O30>=30,O30<60),"30-60", AND(O30>=60,O30<90),"60-90", AND(O30>=90,O30<120),"90-120", AND(O30>=120,O30<160),"120-160", AND(O30>=160,O30<200),"160-200", AND(O30>=200,O30<250),"200-250", AND(O30>=250,O30<300),"250-300", O30>=300,">300", TRUE,"Below 0" )} -> 90-120 | AB30: 93.76
A31: 45810 | B31: =TEXT(A31,"yyyy") -> 2025 | C31: Aegis Vopak Termin | D31: =IFERROR(LEFT(C31,FIND(" ",C31)-1),C31) -> Aegis | E31: =TRIM(SUBSTITUTE(SUBSTITUTE(C31,"Ltd",""),"Lt","")) -> Aegis Vopak Termin | F31: =_xlfn.XLOOKUP(E31,MARKET_PRICE__2[Column2],MARKET_PRICE__2[Column3],"Not found") -> Not found | G31: =_xlfn.XLOOKUP(D31,MARKET_PRICE__2[Column12],MARKET_PRICE__2[Column3],"Not found") -> 804.90 | H31: 2800 | K31: =H31/10 -> 280 | N31: {=_xlfn.IFS(H31<500,"0-500",H31<1000,"500-1000",H31<1500,"1000-1500",H31<2000,"1500-2000",H31<2500,"2000-2500",H31<3000,"2500-3000",H31<3500,"3000-3500",H31<4000,"3500-4000",H31<4500,"4000-4500",H31<=5000,"4500-5000",TRUE,"Hbove 5000")} -> 2500-3000 | O31: 3.3 | P31: 0.56 | Q31: 0.77 | R31: 2.09 | S31: {=_xlfn.IFS( R31<0,"< 0", R31<5,"0 to 5", R31<10,"5 to 10", R31<15,"10 to 15", R31<20,"15 to 20", R31<25,"20 to 25", R31<50,"25 to 50", R31<75,"50 to 75", R31<100,"75 to 100", R31<125,"100 to 125", R31<150,"125 to 150", R31<175,"150 to 175", R31<200,"175 to 200", TRUE,"> 200" )} -> 0 to 5 | T31: 235 | U31: 220 | V31: -6.38 | W31: {=_xlfn.IFS( V31<-15,"< -15%", V31<-10,"-15% to -10%", V31<-5,"-10% to -5%", V31<0,"-5% to 0%", V31<10,"0% to 10%", V31<20,"10% to 20%", V31<30,"20% to 30%", V31<40,"30% to 40%", V31<50,"40% to 50%", V31<60,"50% to 60%", V31<70,"60% to 70%", V31<80,"70% to 80%", V31<90,"80% to 90%", V31<100,"90% to 100%", TRUE,"> 100%" )} -> -10% to -5% | X31: 252.85 | Y31: 253.58 | Z31: =IF(V31>0, ">0", IF(V31<0, "<0", "=0")) -> <0 | AA31: {=_xlfn.IFS( AND(O31>=0,O31<5),"0-5", AND(O31>=5,O31<15),"5-15", AND(O31>=15,O31<30),"15-30", AND(O31>=30,O31<60),"30-60", AND(O31>=60,O31<90),"60-90", AND(O31>=90,O31<120),"90-120", AND(O31>=120,O31<160),"120-160", AND(O31>=160,O31<200),"160-200", AND(O31>=200,O31<250),"200-250", AND(O31>=250,O31<300),"250-300", O31>=300,">300", TRUE,"Below 0" )} -> 0-5 | AB31: 7.6
A32: 45810 | B32: =TEXT(A32,"yyyy") -> 2025 | C32: Schloss Bangalore | D32: =IFERROR(LEFT(C32,FIND(" ",C32)-1),C32) -> Schloss | E32: =TRIM(SUBSTITUTE(SUBSTITUTE(C32,"Ltd",""),"Lt","")) -> Schloss Bangalore | F32: =_xlfn.XLOOKUP(E32,MARKET_PRICE__2[Column2],MARKET_PRICE__2[Column3],"Not found") -> Not found | G32: =_xlfn.XLOOKUP(D32,MARKET_PRICE__2[Column12],MARKET_PRICE__2[Column3],"Not found") -> 447.70 | H32: 3500 | K32: =H32/10 -> 350 | N32: {=_xlfn.IFS(H32<500,"0-500",H32<1000,"500-1000",H32<1500,"1000-1500",H32<2000,"1500-2000",H32<2500,"2000-2500",H32<3000,"2500-3000",H32<3500,"3000-3500",H32<4000,"3500-4000",H32<4500,"4000-4500",H32<=5000,"4500-5000",TRUE,"Hbove 5000")} -> 3500-4000 | O32: 7.46 | P32: 1.02 | Q32: 0.83 | R32: 4.5 | S32: {=_xlfn.IFS( R32<0,"< 0", R32<5,"0 to 5", R32<10,"5 to 10", R32<15,"10 to 15", R32<20,"15 to 20", R32<25,"20 to 25", R32<50,"25 to 50", R32<75,"50 to 75", R32<100,"75 to 100", R32<125,"100 to 125", R32<150,"125 to 150", R32<175,"150 to 175", R32<200,"175 to 200", TRUE,"> 200" )} -> 0 to 5 | T32: 435 | U32: 406.5 | V32: -6.55 | W32: {=_xlfn.IFS( V32<-15,"< -15%", V32<-10,"-15% to -10%", V32<-5,"-10% to -5%", V32<0,"-5% to 0%", V32<10,"0% to 10%", V32<20,"10% to 20%", V32<30,"20% to 30%", V32<40,"30% to 40%", V32<50,"40% to 50%", V32<60,"50% to 60%", V32<70,"60% to 70%", V32<80,"70% to 80%", V32<90,"80% to 90%", V32<100,"90% to 100%", TRUE,"> 100%" )} -> -10% to -5% | X32: 420.3 | Y32: 420.65 | Z32: =IF(V32>0, ">0", IF(V32<0, "<0", "=0")) -> <0 | AA32: {=_xlfn.IFS( AND(O32>=0,O32<5),"0-5", AND(O32>=5,O32<15),"5-15", AND(O32>=15,O32<30),"15-30", AND(O32>=30,O32<60),"30-60", AND(O32>=60,O32<90),"60-90", AND(O32>=90,O32<120),"90-120", AND(O32>=120,O32<160),"120-160", AND(O32>=160,O32<200),"160-200", AND(O32>=200,O32<250),"200-250", AND(O32>=250,O32<300),"250-300", O32>=300,">300", TRUE,"Below 0" )} -> 5-15 | AB32: -3.38
A33: 45805 | B33: =TEXT(A33,"yyyy") -> 2025 | C33: Belrise Industries | D33: =IFERROR(LEFT(C33,FIND(" ",C33)-1),C33) -> Belrise | E33: =TRIM(SUBSTITUTE(SUBSTITUTE(C33,"Ltd",""),"Lt","")) -> Belrise Industries | F33: =_xlfn.XLOOKUP(E33,MARKET_PRICE__2[Column2],MARKET_PRICE__2[Column3],"Not found") -> Not found | G33: =_xlfn.XLOOKUP(D33,MARKET_PRICE__2[Column12],MARKET_PRICE__2[Column3],"Not found") -> 157.45 | H33: 2150 | K33: =H33/10 -> 215 | N33: {=_xlfn.IFS(H33<500,"0-500",H33<1000,"500-1000",H33<1500,"1000-1500",H33<2000,"1500-2000",H33<2500,"2000-2500",H33<3000,"2500-3000",H33<3500,"3000-3500",H33<4000,"3500-4000",H33<4500,"4000-4500",H33<=5000,"4500-5000",TRUE,"Hbove 5000")} -> 2000-2500 | O33: 108.35 | P33: 38.33 | Q33: 4.27 | R33: 41.3 | S33: {=_xlfn.IFS( R33<0,"< 0", R33<5,"0 to 5", R33<10,"5 to 10", R33<15,"10 to 15", R33<20,"15 to 20", R33<25,"20 to 25", R33<50,"25 to 50", R33<75,"50 to 75", R33<100,"75 to 100", R33<125,"100 to 125", R33<150,"125 to 150", R33<175,"150 to 175", R33<200,"175 to 200", TRUE,"> 200" )} -> 25 to 50 | T33: 90 | U33: 98.5 | V33: 9.44 | W33: {=_xlfn.IFS( V33<-15,"< -15%", V33<-10,"-15% to -10%", V33<-5,"-10% to -5%", V33<0,"-5% to 0%", V33<10,"0% to 10%", V33<20,"10% to 20%", V33<30,"20% to 30%", V33<40,"30% to 40%", V33<50,"40% to 50%", V33<60,"50% to 60%", V33<70,"60% to 70%", V33<80,"70% to 80%", V33<90,"80% to 90%", V33<100,"90% to 100%", TRUE,"> 100%" )} -> 0% to 10% | X33: 146.65 | Y33: 146.58 | Z33: =IF(V33>0, ">0", IF(V33<0, "<0", "=0")) -> >0 | AA33: {=_xlfn.IFS( AND(O33>=0,O33<5),"0-5", AND(O33>=5,O33<15),"5-15", AND(O33>=15,O33<30),"15-30", AND(O33>=30,O33<60),"30-60", AND(O33>=60,O33<90),"60-90", AND(O33>=90,O33<120),"90-120", AND(O33>=120,O33<160),"120-160", AND(O33>=160,O33<200),"160-200", AND(O33>=200,O33<250),"200-250", AND(O33>=250,O33<300),"250-300", O33>=300,">300", TRUE,"Below 0" )} -> 90-120 | AB33: 62.94
A34: 45804 | B34: =TEXT(A34,"yyyy") -> 2025 | C34: Borana Weaves Ltd | D34: =IFERROR(LEFT(C34,FIND(" ",C34)-1),C34) -> Borana | E34: =TRIM(SUBSTITUTE(SUBSTITUTE(C34,"Ltd",""),"Lt","")) -> Borana Weaves | F34: =_xlfn.XLOOKUP(E34,MARKET_PRICE__2[Column2],MARKET_PRICE__2[Column3],"Not found") -> 226.40 | G34: =_xlfn.XLOOKUP(D34,MARKET_PRICE__2[Column12],MARKET_PRICE__2[Column3],"Not found") -> 226.40 | H34: 144.89 | I34: {=_xlfn.IFS( H34<50,"0-50", H34<100,"50-100", H34<150,"100-150", H34<200,"150-200", H34<250,"200-250", H34<300,"250-300", H34<350,"300-350", H34<400,"350-400", H34<450,"400-450", H34<=500,"450-500", TRUE,"Above 500" )} -> 100-150 | K34: =H34/10 -> 14.489 | N34: {=_xlfn.IFS(H34<500,"0-500",H34<1000,"500-1000",H34<1500,"1000-1500",H34<2000,"1500-2000",H34<2500,"2000-2500",H34<3000,"2500-3000",H34<3500,"3000-3500",H34<4000,"3500-4000",H34<4500,"4000-4500",H34<=5000,"4500-5000",TRUE,"Hbove 5000")} -> 0-500 | O34: 87.21 | P34: 237.42 | Q34: 200.53 | R34: 148.78 | S34: {=_xlfn.IFS( R34<0,"< 0", R34<5,"0 to 5", R34<10,"5 to 10", R34<15,"10 to 15", R34<20,"15 to 20", R34<25,"20 to 25", R34<50,"25 to 50", R34<75,"50 to 75", R34<100,"75 to 100", R34<125,"100 to 125", R34<150,"125 to 150", R34<175,"150 to 175", R34<200,"175 to 200", TRUE,"> 200" )} -> 125 to 150 | T34: 216 | U34: 243 | V34: 12.5 | W34: {=_xlfn.IFS( V34<-15,"< -15%", V34<-10,"-15% to -10%", V34<-5,"-10% to -5%", V34<0,"-5% to 0%", V34<10,"0% to 10%", V34<20,"10% to 20%", V34<30,"20% to 30%", V34<40,"30% to 40%", V34<50,"40% to 50%", V34<60,"50% to 60%", V34<70,"60% to 70%", V34<80,"70% to 80%", V34<90,"80% to 90%", V34<100,"90% to 100%", TRUE,"> 100%" )} -> 10% to 20% | X34: 216.75 | Y34: 216.8 | Z34: =IF(V34>0, ">0", IF(V34<0, "<0", "=0")) -> >0 | AA34: {=_xlfn.IFS( AND(O34>=0,O34<5),"0-5", AND(O34>=5,O34<15),"5-15", AND(O34>=15,O34<30),"15-30", AND(O34>=30,O34<60),"30-60", AND(O34>=60,O34<90),"60-90", AND(O34>=90,O34<120),"90-120", AND(O34>=120,O34<160),"120-160", AND(O34>=160,O34<200),"160-200", AND(O34>=200,O34<250),"200-250", AND(O34>=250,O34<300),"250-300", O34>=300,">300", TRUE,"Below 0" )} -> 60-90 | AB34: 0.35
A35: 45783 | B35: =TEXT(A35,"yyyy") -> 2025 | C35: Ather Energy Ltd | D35: =IFERROR(LEFT(C35,FIND(" ",C35)-1),C35) -> Ather | E35: =TRIM(SUBSTITUTE(SUBSTITUTE(C35,"Ltd",""),"Lt","")) -> Ather Energy | F35: =_xlfn.XLOOKUP(E35,MARKET_PRICE__2[Column2],MARKET_PRICE__2[Column3],"Not found") -> 623.95 | G35: =_xlfn.XLOOKUP(D35,MARKET_PRICE__2[Column12],MARKET_PRICE__2[Column3],"Not found") -> 623.95 | H35: 2980.8 | K35: =H35/10 -> 298.08 | N35: {=_xlfn.IFS(H35<500,"0-500",H35<1000,"500-1000",H35<1500,"1000-1500",H35<2000,"1500-2000",H35<2500,"2000-2500",H35<3000,"2500-3000",H35<3500,"3000-3500",H35<4000,"3500-4000",H35<4500,"4000-4500",H35<=5000,"4500-5000",TRUE,"Hbove 5000")} -> 2500-3000 | O35: 1.7 | P35: 0.66 | Q35: 1.78 | R35: 1.43 | S35: {=_xlfn.IFS( R35<0,"< 0", R35<5,"0 to 5", R35<10,"5 to 10", R35<15,"10 to 15", R35<20,"15 to 20", R35<25,"20 to 25", R35<50,"25 to 50", R35<75,"50 to 75", R35<100,"75 to 100", R35<125,"100 to 125", R35<150,"125 to 150", R35<175,"150 to 175", R35<200,"175 to 200", TRUE,"> 200" )} -> 0 to 5 | T35: 321 | U35: 326.05 | V35: 1.57 | W35: {=_xlfn.IFS( V35<-15,"< -15%", V35<-10,"-15% to -10%", V35<-5,"-10% to -5%", V35<0,"-5% to 0%", V35<10,"0% to 10%", V35<20,"10% to 20%", V35<30,"20% to 30%", V35<40,"30% to 40%", V35<50,"40% to 50%", V35<60,"50% to 60%", V35<70,"60% to 70%", V35<80,"70% to 80%", V35<90,"80% to 90%", V35<100,"90% to 100%", TRUE,"> 100%" )} -> 0% to 10% | X35: 416.8 | Y35: 417.25 | Z35: =IF(V35>0, ">0", IF(V35<0, "<0", "=0")) -> >0 | AA35: {=_xlfn.IFS( AND(O35>=0,O35<5),"0-5", AND(O35>=5,O35<15),"5-15", AND(O35>=15,O35<30),"15-30", AND(O35>=30,O35<60),"30-60", AND(O35>=60,O35<90),"60-90", AND(O35>=90,O35<120),"90-120", AND(O35>=120,O35<160),"120-160", AND(O35>=160,O35<200),"160-200", AND(O35>=200,O35<250),"200-250", AND(O35>=250,O35<300),"250-300", O35>=300,">300", TRUE,"Below 0" )} -> 0-5 | AB35: 29.84
A36: 45712 | B36: =TEXT(A36,"yyyy") -> 2025 | C36: Quality Power Elec | D36: =IFERROR(LEFT(C36,FIND(" ",C36)-1),C36) -> Quality | E36: =TRIM(SUBSTITUTE(SUBSTITUTE(C36,"Ltd",""),"Lt","")) -> Quality Power Elec | F36: =_xlfn.XLOOKUP(E36,MARKET_PRICE__2[Column2],MARKET_PRICE__2[Column3],"Not found") -> Not found | G36: =_xlfn.XLOOKUP(D36,MARKET_PRICE__2[Column12],MARKET_PRICE__2[Column3],"Not found") -> 1009.25 | H36: 858.7 | J36: {=_xlfn.IFS( AND(H36>=500,H36<550),"500-550", AND(H36>=550,H36<600),"550-600", AND(H36>=600,H36<650),"600-650", AND(H36>=650,H36<700),"650-700", AND(H36>=700,H36<750),"700-750", AND(H36>=750,H36<800),"750-800", AND(H36>=800,H36<850),"800-850", AND(H36>=850,H36<900),"850-900", AND(H36>=900,H36<950),"900-950", AND(H36>=950,H36<=1000),"950-1000", H36<500,"Below 500", TRUE,"Above 1000" )} -> 850-900 | K36: =H36/10 -> 85.87 | N36: {=_xlfn.IFS(H36<500,"0-500",H36<1000,"500-1000",H36<1500,"1000-1500",H36<2000,"1500-2000",H36<2500,"2000-2500",H36<3000,"2500-3000",H36<3500,"3000-3500",H36<4000,"3500-4000",H36<4500,"4000-4500",H36<=5000,"4500-5000",TRUE,"Hbove 5000")} -> 500-1000 | O36: 1.03 | P36: 1.45 | Q36: 1.83 | R36: 1.29 | S36: {=_xlfn.IFS( R36<0,"< 0", R36<5,"0 to 5", R36<10,"5 to 10", R36<15,"10 to 15", R36<20,"15 to 20", R36<25,"20 to 25", R36<50,"25 to 50", R36<75,"50 to 75", R36<100,"75 to 100", R36<125,"100 to 125", R36<150,"125 to 150", R36<175,"150 to 175", R36<200,"175 to 200", TRUE,"> 200" )} -> 0 to 5 | T36: 425 | U36: 432.05 | V36: 1.66 | W36: {=_xlfn.IFS( V36<-15,"< -15%", V36<-10,"-15% to -10%", V36<-5,"-10% to -5%", V36<0,"-5% to 0%", V36<10,"0% to 10%", V36<20,"10% to 20%", V36<30,"20% to 30%", V36<40,"30% to 40%", V36<50,"40% to 50%", V36<60,"50% to 60%", V36<70,"60% to 70%", V36<80,"70% to 80%", V36<90,"80% to 90%", V36<100,"90% to 100%", TRUE,"> 100%" )} -> 0% to 10% | X36: 788.2 | Y36: 788.7 | Z36: =IF(V36>0, ">0", IF(V36<0, "<0", "=0")) -> >0 | AA36: {=_xlfn.IFS( AND(O36>=0,O36<5),"0-5", AND(O36>=5,O36<15),"5-15", AND(O36>=15,O36<30),"15-30", AND(O36>=30,O36<60),"30-60", AND(O36>=60,O36<90),"60-90", AND(O36>=90,O36<120),"90-120", AND(O36>=120,O36<160),"120-160", AND(O36>=160,O36<200),"160-200", AND(O36>=200,O36<250),"200-250", AND(O36>=250,O36<300),"250-300", O36>=300,">300", TRUE,"Below 0" )} -> 0-5 | AB36: 85.46
A37: 45707 | B37: =TEXT(A37,"yyyy") -> 2025 | C37: Hexaware Technolog | D37: =IFERROR(LEFT(C37,FIND(" ",C37)-1),C37) -> Hexaware | E37: =TRIM(SUBSTITUTE(SUBSTITUTE(C37,"Ltd",""),"Lt","")) -> Hexaware Technolog | F37: =_xlfn.XLOOKUP(E37,MARKET_PRICE__2[Column2],MARKET_PRICE__2[Column3],"Not found") -> Not found | G37: =_xlfn.XLOOKUP(D37,MARKET_PRICE__2[Column12],MARKET_PRICE__2[Column3],"Not found") -> 717.60 | H37: 8750 | K37: =H37/10 -> 875 | N37: {=_xlfn.IFS(H37<500,"0-500",H37<1000,"500-1000",H37<1500,"1000-1500",H37<2000,"1500-2000",H37<2500,"2000-2500",H37<3000,"2500-3000",H37<3500,"3000-3500",H37<4000,"3500-4000",H37<4500,"4000-4500",H37<=5000,"4500-5000",TRUE,"Hbove 5000")} -> Hbove 5000 | O37: 9.09 | P37: 0.2 | Q37: 0.11 | R37: 2.66 | S37: {=_xlfn.IFS( R37<0,"< 0", R37<5,"0 to 5", R37<10,"5 to 10", R37<15,"10 to 15", R37<20,"15 to 20", R37<25,"20 to 25", R37<50,"25 to 50", R37<75,"50 to 75", R37<100,"75 to 100", R37<125,"100 to 125", R37<150,"125 to 150", R37<175,"150 to 175", R37<200,"175 to 200", TRUE,"> 200" )} -> 0 to 5 | T37: 708 | U37: 731 | V37: 3.25 | W37: {=_xlfn.IFS( V37<-15,"< -15%", V37<-10,"-15% to -10%", V37<-5,"-10% to -5%", V37<0,"-5% to 0%", V37<10,"0% to 10%", V37<20,"10% to 20%", V37<30,"20% to 30%", V37<40,"30% to 40%", V37<50,"40% to 50%", V37<60,"50% to 60%", V37<70,"60% to 70%", V37<80,"70% to 80%", V37<90,"80% to 90%", V37<100,"90% to 100%", TRUE,"> 100%" )} -> 0% to 10% | X37: 799.95 | Y37: 799.4 | Z37: =IF(V37>0, ">0", IF(V37<0, "<0", "=0")) -> >0 | AA37: {=_xlfn.IFS( AND(O37>=0,O37<5),"0-5", AND(O37>=5,O37<15),"5-15", AND(O37>=15,O37<30),"15-30", AND(O37>=30,O37<60),"30-60", AND(O37>=60,O37<90),"60-90", AND(O37>=90,O37<120),"90-120", AND(O37>=120,O37<160),"120-160", AND(O37>=160,O37<200),"160-200", AND(O37>=200,O37<250),"200-250", AND(O37>=250,O37<300),"250-300", O37>=300,">300", TRUE,"Below 0" )} -> 5-15 | AB37: 12.99
A38: 45705 | B38: =TEXT(A38,"yyyy") -> 2025 | C38: Ajax Engineering L | D38: =IFERROR(LEFT(C38,FIND(" ",C38)-1),C38) -> Ajax | E38: =TRIM(SUBSTITUTE(SUBSTITUTE(C38,"Ltd",""),"Lt","")) -> Ajax Engineering L | F38: =_xlfn.XLOOKUP(E38,MARKET_PRICE__2[Column2],MARKET_PRICE__2[Column3],"Not found") -> Not found | G38: =_xlfn.XLOOKUP(D38,MARKET_PRICE__2[Column12],MARKET_PRICE__2[Column3],"Not found") -> 630.00 | H38: 1268.88 | K38: =H38/10 -> 126.888 | L38: {=_xlfn.IFS( AND(H38>=1000,H38<1050),"1000-1050", AND(H38>=1050,H38<1100),"1050-1100", AND(H38>=1100,H38<1150),"1100-1150", AND(H38>=1150,H38<1200),"1150-1200", AND(H38>=1200,H38<1250),"1200-1250", AND(H38>=1250,H38<1300),"1250-1300", AND(H38>=1300,H38<1350),"1300-1350", AND(H38>=1350,H38<1400),"1350-1400", AND(H38>=1400,H38<1450),"1400-1450", AND(H38>=1450,H38<=1500),"1450-1500", H38<1000,"Below 1000", TRUE,"Above 1500" )} -> 1250-1300 | N38: {=_xlfn.IFS(H38<500,"0-500",H38<1000,"500-1000",H38<1500,"1000-1500",H38<2000,"1500-2000",H38<2500,"2000-2500",H38<3000,"2500-3000",H38<3500,"3000-3500",H38<4000,"3500-4000",H38<4500,"4000-4500",H38<=5000,"4500-5000",TRUE,"Hbove 5000")} -> 1000-1500 | O38: 14.41 | P38: 6.46 | Q38: 1.92 | R38: 6.44 | S38: {=_xlfn.IFS( R38<0,"< 0", R38<5,"0 to 5", R38<10,"5 to 10", R38<15,"10 to 15", R38<20,"15 to 20", R38<25,"20 to 25", R38<50,"25 to 50", R38<75,"50 to 75", R38<100,"75 to 100", R38<125,"100 to 125", R38<150,"125 to 150", R38<175,"150 to 175", R38<200,"175 to 200", TRUE,"> 200" )} -> 5 to 10 | T38: 629 | U38: 593 | V38: -5.72 | W38: {=_xlfn.IFS( V38<-15,"< -15%", V38<-10,"-15% to -10%", V38<-5,"-10% to -5%", V38<0,"-5% to 0%", V38<10,"0% to 10%", V38<20,"10% to 20%", V38<30,"20% to 30%", V38<40,"30% to 40%", V38<50,"40% to 50%", V38<60,"50% to 60%", V38<70,"60% to 70%", V38<80,"70% to 80%", V38<90,"80% to 90%", V38<100,"90% to 100%", TRUE,"> 100%" )} -> -10% to -5% | X38: 680.1 | Y38: 679.85 | Z38: =IF(V38>0, ">0", IF(V38<0, "<0", "=0")) -> <0 | AA38: {=_xlfn.IFS( AND(O38>=0,O38<5),"0-5", AND(O38>=5,O38<15),"5-15", AND(O38>=15,O38<30),"15-30", AND(O38>=30,O38<60),"30-60", AND(O38>=60,O38<90),"60-90", AND(O38>=90,O38<120),"90-120", AND(O38>=120,O38<160),"120-160", AND(O38>=160,O38<200),"160-200", AND(O38>=200,O38<250),"200-250", AND(O38>=250,O38<300),"250-300", O38>=300,">300", TRUE,"Below 0" )} -> 5-15 | AB38: 8.12
A39: 45692 | B39: =TEXT(A39,"yyyy") -> 2025 | C39: Dr Agarwal's Healt | D39: =IFERROR(LEFT(C39,FIND(" ",C39)-1),C39) -> Dr | E39: =TRIM(SUBSTITUTE(SUBSTITUTE(C39,"Ltd",""),"Lt","")) -> Dr Agarwal's Healt | F39: =_xlfn.XLOOKUP(E39,MARKET_PRICE__2[Column2],MARKET_PRICE__2[Column3],"Not found") -> Not found | G39: =_xlfn.XLOOKUP(D39,MARKET_PRICE__2[Column12],MARKET_PRICE__2[Column3],"Not found") -> 3086.15 | H39: 3027.26 | K39: =H39/10 -> 302.726 | N39: {=_xlfn.IFS(H39<500,"0-500",H39<1000,"500-1000",H39<1500,"1000-1500",H39<2000,"1500-2000",H39<2500,"2000-2500",H39<3000,"2500-3000",H39<3500,"3000-3500",H39<4000,"3500-4000",H39<4500,"4000-4500",H39<=5000,"4500-5000",TRUE,"Hbove 5000")} -> 3000-3500 | O39: 4.64 | P39: 0.4 | Q39: 0.41 | R39: 1.55 | S39: {=_xlfn.IFS( R39<0,"< 0", R39<5,"0 to 5", R39<10,"5 to 10", R39<15,"10 to 15", R39<20,"15 to 20", R39<25,"20 to 25", R39<50,"25 to 50", R39<75,"50 to 75", R39<100,"75 to 100", R39<125,"100 to 125", R39<150,"125 to 150", R39<175,"150 to 175", R39<200,"175 to 200", TRUE,"> 200" )} -> 0 to 5 | T39: 402 | U39: 396.9 | V39: -1.27 | W39: {=_xlfn.IFS( V39<-15,"< -15%", V39<-10,"-15% to -10%", V39<-5,"-10% to -5%", V39<0,"-5% to 0%", V39<10,"0% to 10%", V39<20,"10% to 20%", V39<30,"20% to 30%", V39<40,"30% to 40%", V39<50,"40% to 50%", V39<60,"50% to 60%", V39<70,"60% to 70%", V39<80,"70% to 80%", V39<90,"80% to 90%", V39<100,"90% to 100%", TRUE,"> 100%" )} -> -5% to 0% | X39: 455.5 | Y39: 455.65 | Z39: =IF(V39>0, ">0", IF(V39<0, "<0", "=0")) -> <0 | AA39: {=_xlfn.IFS( AND(O39>=0,O39<5),"0-5", AND(O39>=5,O39<15),"5-15", AND(O39>=15,O39<30),"15-30", AND(O39>=30,O39<60),"30-60", AND(O39>=60,O39<90),"60-90", AND(O39>=90,O39<120),"90-120", AND(O39>=120,O39<160),"120-160", AND(O39>=160,O39<200),"160-200", AND(O39>=200,O39<250),"200-250", AND(O39>=250,O39<300),"250-300", O39>=300,">300", TRUE,"Below 0" )} -> 0-5 | AB39: 13.31
A40: 45686 | B40: =TEXT(A40,"yyyy") -> 2025 | C40: Denta Water & Infr | D40: =IFERROR(LEFT(C40,FIND(" ",C40)-1),C40) -> Denta | E40: =TRIM(SUBSTITUTE(SUBSTITUTE(C40,"Ltd",""),"Lt","")) -> Denta Water & Infr | F40: =_xlfn.XLOOKUP(E40,MARKET_PRICE__2[Column2],MARKET_PRICE__2[Column3],"Not found") -> Not found | G40: =_xlfn.XLOOKUP(D40,MARKET_PRICE__2[Column12],MARKET_PRICE__2[Column3],"Not found") -> 434.75 | H40: 220.5 | I40: {=_xlfn.IFS( H40<50,"0-50", H40<100,"50-100", H40<150,"100-150", H40<200,"150-200", H40<250,"200-250", H40<300,"250-300", H40<350,"300-350", H40<400,"350-400", H40<450,"400-450", H40<=500,"450-500", TRUE,"Above 500" )} -> 200-250 | K40: =H40/10 -> 22.05 | N40: {=_xlfn.IFS(H40<500,"0-500",H40<1000,"500-1000",H40<1500,"1000-1500",H40<2000,"1500-2000",H40<2500,"2000-2500",H40<3000,"2500-3000",H40<3500,"3000-3500",H40<4000,"3500-4000",H40<4500,"4000-4500",H40<=5000,"4500-5000",TRUE,"Hbove 5000")} -> 0-500 | O40: 236.94 | P40: 507.27 | Q40: 90.56 | R40: 221.68 | S40: {=_xlfn.IFS( R40<0,"< 0", R40<5,"0 to 5", R40<10,"5 to 10", R40<15,"10 to 15", R40<20,"15 to 20", R40<25,"20 to 25", R40<50,"25 to 50", R40<75,"50 to 75", R40<100,"75 to 100", R40<125,"100 to 125", R40<150,"125 to 150", R40<175,"150 to 175", R40<200,"175 to 200", TRUE,"> 200" )} -> > 200 | T40: 294 | U40: 330 | V40: 12.24 | W40: {=_xlfn.IFS( V40<-15,"< -15%", V40<-10,"-15% to -10%", V40<-5,"-10% to -5%", V40<0,"-5% to 0%", V40<10,"0% to 10%", V40<20,"10% to 20%", V40<30,"20% to 30%", V40<40,"30% to 40%", V40<50,"40% to 50%", V40<60,"50% to 60%", V40<70,"60% to 70%", V40<80,"70% to 80%", V40<90,"80% to 90%", V40<100,"90% to 100%", TRUE,"> 100%" )} -> 10% to 20% | X40: 423.8 | Y40: 423.4 | Z40: =IF(V40>0, ">0", IF(V40<0, "<0", "=0")) -> >0 | AA40: {=_xlfn.IFS( AND(O40>=0,O40<5),"0-5", AND(O40>=5,O40<15),"5-15", AND(O40>=15,O40<30),"15-30", AND(O40>=30,O40<60),"30-60", AND(O40>=60,O40<90),"60-90", AND(O40>=90,O40<120),"90-120", AND(O40>=120,O40<160),"120-160", AND(O40>=160,O40<200),"160-200", AND(O40>=200,O40<250),"200-250", AND(O40>=250,O40<300),"250-300", O40>=300,">300", TRUE,"Below 0" )} -> 200-250 | AB40: 44.15
A41: 45680 | B41: =TEXT(A41,"yyyy") -> 2025 | C41: Stallion India Flu | D41: =IFERROR(LEFT(C41,FIND(" ",C41)-1),C41) -> Stallion | E41: =TRIM(SUBSTITUTE(SUBSTITUTE(C41,"Ltd",""),"Lt","")) -> Stallion India Flu | F41: =_xlfn.XLOOKUP(E41,MARKET_PRICE__2[Column2],MARKET_PRICE__2[Column3],"Not found") -> Not found | G41: =_xlfn.XLOOKUP(D41,MARKET_PRICE__2[Column12],MARKET_PRICE__2[Column3],"Not found") -> 330.10 | H41: 199.45 | I41: {=_xlfn.IFS( H41<50,"0-50", H41<100,"50-100", H41<150,"100-150", H41<200,"150-200", H41<250,"200-250", H41<300,"250-300", H41<350,"300-350", H41<400,"350-400", H41<450,"400-450", H41<=500,"450-500", TRUE,"Above 500" )} -> 150-200 | K41: =H41/10 -> 19.945 | N41: {=_xlfn.IFS(H41<500,"0-500",H41<1000,"500-1000",H41<1500,"1000-1500",H41<2000,"1500-2000",H41<2500,"2000-2500",H41<3000,"2500-3000",H41<3500,"3000-3500",H41<4000,"3500-4000",H41<4500,"4000-4500",H41<=5000,"4500-5000",TRUE,"Hbove 5000")} -> 0-500 | O41: 172.93 | P41: 422.42 | Q41: 96.89 | R41: 188.37 | S41: {=_xlfn.IFS( R41<0,"< 0", R41<5,"0 to 5", R41<10,"5 to 10", R41<15,"10 to 15", R41<20,"15 to 20", R41<25,"20 to 25", R41<50,"25 to 50", R41<75,"50 to 75", R41<100,"75 to 100", R41<125,"100 to 125", R41<150,"125 to 150", R41<175,"150 to 175", R41<200,"175 to 200", TRUE,"> 200" )} -> 175 to 200 | T41: 90 | U41: 120 | V41: 33.33 | W41: {=_xlfn.IFS( V41<-15,"< -15%", V41<-10,"-15% to -10%", V41<-5,"-10% to -5%", V41<0,"-5% to 0%", V41<10,"0% to 10%", V41<20,"10% to 20%", V41<30,"20% to 30%", V41<40,"30% to 40%", V41<50,"40% to 50%", V41<60,"50% to 60%", V41<70,"60% to 70%", V41<80,"70% to 80%", V41<90,"80% to 90%", V41<100,"90% to 100%", TRUE,"> 100%" )} -> 30% to 40% | X41: 147.65 | Y41: 147.51 | Z41: =IF(V41>0, ">0", IF(V41<0, "<0", "=0")) -> >0 | AA41: {=_xlfn.IFS( AND(O41>=0,O41<5),"0-5", AND(O41>=5,O41<15),"5-15", AND(O41>=15,O41<30),"15-30", AND(O41>=30,O41<60),"30-60", AND(O41>=60,O41<90),"60-90", AND(O41>=90,O41<120),"90-120", AND(O41>=120,O41<160),"120-160", AND(O41>=160,O41<200),"160-200", AND(O41>=200,O41<250),"200-250", AND(O41>=250,O41<300),"250-300", O41>=300,">300", TRUE,"Below 0" )} -> 160-200 | AB41: 64.06
A42: 45677 | B42: =TEXT(A42,"yyyy") -> 2025 | C42: Laxmi Dental Ltd | D42: =IFERROR(LEFT(C42,FIND(" ",C42)-1),C42) -> Laxmi | E42: =TRIM(SUBSTITUTE(SUBSTITUTE(C42,"Ltd",""),"Lt","")) -> Laxmi Dental | F42: =_xlfn.XLOOKUP(E42,MARKET_PRICE__2[Column2],MARKET_PRICE__2[Column3],"Not found") -> 320.00 | G42: =_xlfn.XLOOKUP(D42,MARKET_PRICE__2[Column12],MARKET_PRICE__2[Column3],"Not found") -> 320.00 | H42: 698.06 | J42: {=_xlfn.IFS( AND(H42>=500,H42<550),"500-550", AND(H42>=550,H42<600),"550-600", AND(H42>=600,H42<650),"600-650", AND(H42>=650,H42<700),"650-700", AND(H42>=700,H42<750),"700-750", AND(H42>=750,H42<800),"750-800", AND(H42>=800,H42<850),"800-850", AND(H42>=850,H42<900),"850-900", AND(H42>=900,H42<950),"900-950", AND(H42>=950,H42<=1000),"950-1000", H42<500,"Below 500", TRUE,"Above 1000" )} -> 650-700 | K42: =H42/10 -> 69.806 | N42: {=_xlfn.IFS(H42<500,"0-500",H42<1000,"500-1000",H42<1500,"1000-1500",H42<2000,"1500-2000",H42<2500,"2000-2500",H42<3000,"2500-3000",H42<3500,"3000-3500",H42<4000,"3500-4000",H42<4500,"4000-4500",H42<=5000,"4500-5000",TRUE,"Hbove 5000")} -> 500-1000 | O42: 110.38 | P42: 147.95 | Q42: 76.24 | R42: 114.42 | S42: {=_xlfn.IFS( R42<0,"< 0", R42<5,"0 to 5", R42<10,"5 to 10", R42<15,"10 to 15", R42<20,"15 to 20", R42<25,"20 to 25", R42<50,"25 to 50", R42<75,"50 to 75", R42<100,"75 to 100", R42<125,"100 to 125", R42<150,"125 to 150", R42<175,"150 to 175", R42<200,"175 to 200", TRUE,"> 200" )} -> 100 to 125 | T42: 428 | U42: 528 | V42: 23.36 | W42: {=_xlfn.IFS( V42<-15,"< -15%", V42<-10,"-15% to -10%", V42<-5,"-10% to -5%", V42<0,"-5% to 0%", V42<10,"0% to 10%", V42<20,"10% to 20%", V42<30,"20% to 30%", V42<40,"30% to 40%", V42<50,"40% to 50%", V42<60,"50% to 60%", V42<70,"60% to 70%", V42<80,"70% to 80%", V42<90,"80% to 90%", V42<100,"90% to 100%", TRUE,"> 100%" )} -> 20% to 30% | X42: 349.95 | Y42: 349.85 | Z42: =IF(V42>0, ">0", IF(V42<0, "<0", "=0")) -> >0 | AA42: {=_xlfn.IFS( AND(O42>=0,O42<5),"0-5", AND(O42>=5,O42<15),"5-15", AND(O42>=15,O42<30),"15-30", AND(O42>=30,O42<60),"30-60", AND(O42>=60,O42<90),"60-90", AND(O42>=90,O42<120),"90-120", AND(O42>=120,O42<160),"120-160", AND(O42>=160,O42<200),"160-200", AND(O42>=200,O42<250),"200-250", AND(O42>=250,O42<300),"250-300", O42>=300,">300", TRUE,"Below 0" )} -> 90-120 | AB42: -18.24
A43: 45674 | B43: =TEXT(A43,"yyyy") -> 2025 | C43: Capital Infra Trus | D43: =IFERROR(LEFT(C43,FIND(" ",C43)-1),C43) -> Capital | E43: =TRIM(SUBSTITUTE(SUBSTITUTE(C43,"Ltd",""),"Lt","")) -> Capital Infra Trus | F43: =_xlfn.XLOOKUP(E43,MARKET_PRICE__2[Column2],MARKET_PRICE__2[Column3],"Not found") -> Not found | G43: =_xlfn.XLOOKUP(D43,MARKET_PRICE__2[Column12],MARKET_PRICE__2[Column3],"Not found") -> 45.23 | H43: 1578 | K43: =H43/10 -> 157.8 | M43: {=_xlfn.IFS( AND(H43>=1000,H43<1050),"1000-1050", AND(H43>=1050,H43<1100),"1050-1100", AND(H43>=1100,H43<1150),"1100-1150", AND(H43>=1150,H43<1200),"1150-1200", AND(H43>=1200,H43<1250),"1200-1250", AND(H43>=1250,H43<1300),"1250-1300", AND(H43>=1300,H43<1350),"1300-1350", AND(H43>=1350,H43<1400),"1350-1400", AND(H43>=1400,H43<1450),"1400-1450", AND(H43>=1450,H43<1500),"1450-1500", AND(H43>=1500,H43<1550),"1500-1550", AND(H43>=1550,H43<1600),"1550-1600", AND(H43>=1600,H43<1650),"1600-1650", AND(H43>=1650,H43<1700),"1650-1700", AND(H43>=1700,H43<1750),"1700-1750", AND(H43>=1750,H43<1800),"1750-1800", AND(H43>=1800,H43<1850),"1800-1850", AND(H43>=1850,H43<1900),"1850-1900", AND(H43>=1900,H43<1950),"1900-1950", AND(H43>=1950,H43<=2000),"1950-2000", H43<1000,"Below 1000", TRUE,"Above 2000" )} -> 1550-1600 | N43: {=_xlfn.IFS(H43<500,"0-500",H43<1000,"500-1000",H43<1500,"1000-1500",H43<2000,"1500-2000",H43<2500,"2000-2500",H43<3000,"2500-3000",H43<3500,"3000-3500",H43<4000,"3500-4000",H43<4500,"4000-4500",H43<=5000,"4500-5000",TRUE,"Hbove 5000")} -> 1500-2000 | O43: 0.58 | P43: 4.24 | Q43: 0 | R43: 2.23 | S43: {=_xlfn.IFS( R43<0,"< 0", R43<5,"0 to 5", R43<10,"5 to 10", R43<15,"10 to 15", R43<20,"15 to 20", R43<25,"20 to 25", R43<50,"25 to 50", R43<75,"50 to 75", R43<100,"75 to 100", R43<125,"100 to 125", R43<150,"125 to 150", R43<175,"150 to 175", R43<200,"175 to 200", TRUE,"> 200" )} -> 0 to 5 | T43: 99 | U43: 99 | V43: 0 | W43: {=_xlfn.IFS( V43<-15,"< -15%", V43<-10,"-15% to -10%", V43<-5,"-10% to -5%", V43<0,"-5% to 0%", V43<10,"0% to 10%", V43<20,"10% to 20%", V43<30,"20% to 30%", V43<40,"30% to 40%", V43<50,"40% to 50%", V43<60,"50% to 60%", V43<70,"60% to 70%", V43<80,"70% to 80%", V43<90,"80% to 90%", V43<100,"90% to 100%", TRUE,"> 100%" )} -> 0% to 10% | X43: 79.93 | Y43: 79.76 | Z43: =IF(V43>0, ">0", IF(V43<0, "<0", "=0")) -> =0 | AA43: {=_xlfn.IFS( AND(O43>=0,O43<5),"0-5", AND(O43>=5,O43<15),"5-15", AND(O43>=15,O43<30),"15-30", AND(O43>=30,O43<60),"30-60", AND(O43>=60,O43<90),"60-90", AND(O43>=90,O43<120),"90-120", AND(O43>=120,O43<160),"120-160", AND(O43>=160,O43<200),"160-200", AND(O43>=200,O43<250),"200-250", AND(O43>=250,O43<300),"250-300", O43>=300,">300", TRUE,"Below 0" )} -> 0-5 | AB43: -19.26
A44: 45671 | B44: =TEXT(A44,"yyyy") -> 2025 | C44: Quadrant Future Te | D44: =IFERROR(LEFT(C44,FIND(" ",C44)-1),C44) -> Quadrant | E44: =TRIM(SUBSTITUTE(SUBSTITUTE(C44,"Ltd",""),"Lt","")) -> Quadrant Future Te | F44: =_xlfn.XLOOKUP(E44,MARKET_PRICE__2[Column2],MARKET_PRICE__2[Column3],"Not found") -> Not found | G44: =_xlfn.XLOOKUP(D44,MARKET_PRICE__2[Column12],MARKET_PRICE__2[Column3],"Not found") -> 382.80 | H44: 290 | I44: {=_xlfn.IFS( H44<50,"0-50", H44<100,"50-100", H44<150,"100-150", H44<200,"150-200", H44<250,"200-250", H44<300,"250-300", H44<350,"300-350", H44<400,"350-400", H44<450,"400-450", H44<=500,"450-500", TRUE,"Above 500" )} -> 250-300 | K44: =H44/10 -> 29 | N44: {=_xlfn.IFS(H44<500,"0-500",H44<1000,"500-1000",H44<1500,"1000-1500",H44<2000,"1500-2000",H44<2500,"2000-2500",H44<3000,"2500-3000",H44<3500,"3000-3500",H44<4000,"3500-4000",H44<4500,"4000-4500",H44<=5000,"4500-5000",TRUE,"Hbove 5000")} -> 0-500 | O44: 132.54 | P44: 254.71 | Q44: 246.94 | R44: 186.66 | S44: {=_xlfn.IFS( R44<0,"< 0", R44<5,"0 to 5", R44<10,"5 to 10", R44<15,"10 to 15", R44<20,"15 to 20", R44<25,"20 to 25", R44<50,"25 to 50", R44<75,"50 to 75", R44<100,"75 to 100", R44<125,"100 to 125", R44<150,"125 to 150", R44<175,"150 to 175", R44<200,"175 to 200", TRUE,"> 200" )} -> 175 to 200 | T44: 290 | U44: 374 | V44: 28.97 | W44: {=_xlfn.IFS( V44<-15,"< -15%", V44<-10,"-15% to -10%", V44<-5,"-10% to -5%", V44<0,"-5% to 0%", V44<10,"0% to 10%", V44<20,"10% to 20%", V44<30,"20% to 30%", V44<40,"30% to 40%", V44<50,"40% to 50%", V44<60,"50% to 60%", V44<70,"60% to 70%", V44<80,"70% to 80%", V44<90,"80% to 90%", V44<100,"90% to 100%", TRUE,"> 100%" )} -> 20% to 30% | X44: 410.8 | Y44: 410.65 | Z44: =IF(V44>0, ">0", IF(V44<0, "<0", "=0")) -> >0 | AA44: {=_xlfn.IFS( AND(O44>=0,O44<5),"0-5", AND(O44>=5,O44<15),"5-15", AND(O44>=15,O44<30),"15-30", AND(O44>=30,O44<60),"30-60", AND(O44>=60,O44<90),"60-90", AND(O44>=90,O44<120),"90-120", AND(O44>=120,O44<160),"120-160", AND(O44>=160,O44<200),"160-200", AND(O44>=200,O44<250),"200-250", AND(O44>=250,O44<300),"250-300", O44>=300,">300", TRUE,"Below 0" )} -> 120-160 | AB44: 41.66
A45: 45670 | B45: =TEXT(A45,"yyyy") -> 2025 | C45: Standard Glass Lin | D45: =IFERROR(LEFT(C45,FIND(" ",C45)-1),C45) -> Standard | E45: =TRIM(SUBSTITUTE(SUBSTITUTE(C45,"Ltd",""),"Lt","")) -> Standard Glass Lin | F45: =_xlfn.XLOOKUP(E45,MARKET_PRICE__2[Column2],MARKET_PRICE__2[Column3],"Not found") -> Not found | G45: =_xlfn.XLOOKUP(D45,MARKET_PRICE__2[Column12],MARKET_PRICE__2[Column3],"Not found") -> 58.00 | H45: 410.05 | I45: {=_xlfn.IFS( H45<50,"0-50", H45<100,"50-100", H45<150,"100-150", H45<200,"150-200", H45<250,"200-250", H45<300,"250-300", H45<350,"300-350", H45<400,"350-400", H45<450,"400-450", H45<=500,"450-500", TRUE,"Above 500" )} -> 400-450 | K45: =H45/10 -> 41.005 | N45: {=_xlfn.IFS(H45<500,"0-500",H45<1000,"500-1000",H45<1500,"1000-1500",H45<2000,"1500-2000",H45<2500,"2000-2500",H45<3000,"2500-3000",H45<3500,"3000-3500",H45<4000,"3500-4000",H45<4500,"4000-4500",H45<=5000,"4500-5000",TRUE,"Hbove 5000")} -> 0-500 | O45: 331.6 | P45: 268.5 | Q45: 64.99 | R45: 183.18 | S45: {=_xlfn.IFS( R45<0,"< 0", R45<5,"0 to 5", R45<10,"5 to 10", R45<15,"10 to 15", R45<20,"15 to 20", R45<25,"20 to 25", R45<50,"25 to 50", R45<75,"50 to 75", R45<100,"75 to 100", R45<125,"100 to 125", R45<150,"125 to 150", R45<175,"150 to 175", R45<200,"175 to 200", TRUE,"> 200" )} -> 175 to 200 | T45: 140 | U45: 176 | V45: 25.71 | W45: {=_xlfn.IFS( V45<-15,"< -15%", V45<-10,"-15% to -10%", V45<-5,"-10% to -5%", V45<0,"-5% to 0%", V45<10,"0% to 10%", V45<20,"10% to 20%", V45<30,"20% to 30%", V45<40,"30% to 40%", V45<50,"40% to 50%", V45<60,"50% to 60%", V45<70,"60% to 70%", V45<80,"70% to 80%", V45<90,"80% to 90%", V45<100,"90% to 100%", TRUE,"> 100%" )} -> 20% to 30% | X45: 180.1 | Y45: 181.06 | Z45: =IF(V45>0, ">0", IF(V45<0, "<0", "=0")) -> >0 | AA45: {=_xlfn.IFS( AND(O45>=0,O45<5),"0-5", AND(O45>=5,O45<15),"5-15", AND(O45>=15,O45<30),"15-30", AND(O45>=30,O45<60),"30-60", AND(O45>=60,O45<90),"60-90", AND(O45>=90,O45<120),"90-120", AND(O45>=120,O45<160),"120-160", AND(O45>=160,O45<200),"160-200", AND(O45>=200,O45<250),"200-250", AND(O45>=250,O45<300),"250-300", O45>=300,">300", TRUE,"Below 0" )} -> >300 | AB45: 28.64
A46: 45664 | B46: =TEXT(A46,"yyyy") -> 2025 | C46: Indo Farm Equipmen | D46: =IFERROR(LEFT(C46,FIND(" ",C46)-1),C46) -> Indo | E46: =TRIM(SUBSTITUTE(SUBSTITUTE(C46,"Ltd",""),"Lt","")) -> Indo Farm Equipmen | F46: =_xlfn.XLOOKUP(E46,MARKET_PRICE__2[Column2],MARKET_PRICE__2[Column3],"Not found") -> Not found | G46: =_xlfn.XLOOKUP(D46,MARKET_PRICE__2[Column12],MARKET_PRICE__2[Column3],"Not found") -> 2.15 | H46: 260.15 | I46: {=_xlfn.IFS( H46<50,"0-50", H46<100,"50-100", H46<150,"100-150", H46<200,"150-200", H46<250,"200-250", H46<300,"250-300", H46<350,"300-350", H46<400,"350-400", H46<450,"400-450", H46<=500,"450-500", TRUE,"Above 500" )} -> 250-300 | K46: =H46/10 -> 26.015 | N46: {=_xlfn.IFS(H46<500,"0-500",H46<1000,"500-1000",H46<1500,"1000-1500",H46<2000,"1500-2000",H46<2500,"2000-2500",H46<3000,"2500-3000",H46<3500,"3000-3500",H46<4000,"3500-4000",H46<4500,"4000-4500",H46<=5000,"4500-5000",TRUE,"Hbove 5000")} -> 0-500 | O46: 242.4 | P46: 503.83 | Q46: 104.92 | R46: 229.68 | S46: {=_xlfn.IFS( R46<0,"< 0", R46<5,"0 to 5", R46<10,"5 to 10", R46<15,"10 to 15", R46<20,"15 to 20", R46<25,"20 to 25", R46<50,"25 to 50", R46<75,"50 to 75", R46<100,"75 to 100", R46<125,"100 to 125", R46<150,"125 to 150", R46<175,"150 to 175", R46<200,"175 to 200", TRUE,"> 200" )} -> > 200 | T46: 215 | U46: 258.4 | V46: 20.19 | W46: {=_xlfn.IFS( V46<-15,"< -15%", V46<-10,"-15% to -10%", V46<-5,"-10% to -5%", V46<0,"-5% to 0%", V46<10,"0% to 10%", V46<20,"10% to 20%", V46<30,"20% to 30%", V46<40,"30% to 40%", V46<50,"40% to 50%", V46<60,"50% to 60%", V46<70,"60% to 70%", V46<80,"70% to 80%", V46<90,"80% to 90%", V46<100,"90% to 100%", TRUE,"> 100%" )} -> 20% to 30% | X46: 225.6 | Y46: 225.73 | Z46: =IF(V46>0, ">0", IF(V46<0, "<0", "=0")) -> >0 | AA46: {=_xlfn.IFS( AND(O46>=0,O46<5),"0-5", AND(O46>=5,O46<15),"5-15", AND(O46>=15,O46<30),"15-30", AND(O46>=30,O46<60),"30-60", AND(O46>=60,O46<90),"60-90", AND(O46>=90,O46<120),"90-120", AND(O46>=120,O46<160),"120-160", AND(O46>=160,O46<200),"160-200", AND(O46>=200,O46<250),"200-250", AND(O46>=250,O46<300),"250-300", O46>=300,">300", TRUE,"Below 0" )} -> 200-250 | AB46: 4.93
A47: 45657 | B47: =TEXT(A47,"yyyy") -> 2024 | C47: Unimech Aerospace | D47: =IFERROR(LEFT(C47,FIND(" ",C47)-1),C47) -> Unimech | E47: =TRIM(SUBSTITUTE(SUBSTITUTE(C47,"Ltd",""),"Lt","")) -> Unimech Aerospace | F47: =_xlfn.XLOOKUP(E47,MARKET_PRICE__2[Column2],MARKET_PRICE__2[Column3],"Not found") -> Not found | G47: =_xlfn.XLOOKUP(D47,MARKET_PRICE__2[Column12],MARKET_PRICE__2[Column3],"Not found") -> 950.00 | H47: 500 | J47: {=_xlfn.IFS( AND(H47>=500,H47<550),"500-550", AND(H47>=550,H47<600),"550-600", AND(H47>=600,H47<650),"600-650", AND(H47>=650,H47<700),"650-700", AND(H47>=700,H47<750),"700-750", AND(H47>=750,H47<800),"750-800", AND(H47>=800,H47<850),"800-850", AND(H47>=850,H47<900),"850-900", AND(H47>=900,H47<950),"900-950", AND(H47>=950,H47<=1000),"950-1000", H47<500,"Below 500", TRUE,"Above 1000" )} -> 500-550 | K47: =H47/10 -> 50 | N47: {=_xlfn.IFS(H47<500,"0-500",H47<1000,"500-1000",H47<1500,"1000-1500",H47<2000,"1500-2000",H47<2500,"2000-2500",H47<3000,"2500-3000",H47<3500,"3000-3500",H47<4000,"3500-4000",H47<4500,"4000-4500",H47<=5000,"4500-5000",TRUE,"Hbove 5000")} -> 500-1000 | O47: 317.63 | P47: 263.78 | Q47: 56.74 | R47: 175.31 | S47: {=_xlfn.IFS( R47<0,"< 0", R47<5,"0 to 5", R47<10,"5 to 10", R47<15,"10 to 15", R47<20,"15 to 20", R47<25,"20 to 25", R47<50,"25 to 50", R47<75,"50 to 75", R47<100,"75 to 100", R47<125,"100 to 125", R47<150,"125 to 150", R47<175,"150 to 175", R47<200,"175 to 200", TRUE,"> 200" )} -> 175 to 200 | T47: 785 | U47: 1491 | V47: 89.94 | W47: {=_xlfn.IFS( V47<-15,"< -15%", V47<-10,"-15% to -10%", V47<-5,"-10% to -5%", V47<0,"-5% to 0%", V47<10,"0% to 10%", V47<20,"10% to 20%", V47<30,"20% to 30%", V47<40,"30% to 40%", V47<50,"40% to 50%", V47<60,"50% to 60%", V47<70,"60% to 70%", V47<80,"70% to 80%", V47<90,"80% to 90%", V47<100,"90% to 100%", TRUE,"> 100%" )} -> 80% to 90% | X47: 1085.05 | Y47: 1082.3 | Z47: =IF(V47>0, ">0", IF(V47<0, "<0", "=0")) -> >0 | AA47: {=_xlfn.IFS( AND(O47>=0,O47<5),"0-5", AND(O47>=5,O47<15),"5-15", AND(O47>=15,O47<30),"15-30", AND(O47>=30,O47<60),"30-60", AND(O47>=60,O47<90),"60-90", AND(O47>=90,O47<120),"90-120", AND(O47>=120,O47<160),"120-160", AND(O47>=160,O47<200),"160-200", AND(O47>=200,O47<250),"200-250", AND(O47>=250,O47<300),"250-300", O47>=300,">300", TRUE,"Below 0" )} -> >300 | AB47: 38.22
A48: 45656 | B48: =TEXT(A48,"yyyy") -> 2024 | C48: Ventive Hospitalit | D48: =IFERROR(LEFT(C48,FIND(" ",C48)-1),C48) -> Ventive | E48: =TRIM(SUBSTITUTE(SUBSTITUTE(C48,"Ltd",""),"Lt","")) -> Ventive Hospitalit | F48: =_xlfn.XLOOKUP(E48,MARKET_PRICE__2[Column2],MARKET_PRICE__2[Column3],"Not found") -> Not found | G48: =_xlfn.XLOOKUP(D48,MARKET_PRICE__2[Column12],MARKET_PRICE__2[Column3],"Not found") -> 710.05 | H48: 1600 | K48: =H48/10 -> 160 | M48: {=_xlfn.IFS( AND(H48>=1000,H48<1050),"1000-1050", AND(H48>=1050,H48<1100),"1050-1100", AND(H48>=1100,H48<1150),"1100-1150", AND(H48>=1150,H48<1200),"1150-1200", AND(H48>=1200,H48<1250),"1200-1250", AND(H48>=1250,H48<1300),"1250-1300", AND(H48>=1300,H48<1350),"1300-1350", AND(H48>=1350,H48<1400),"1350-1400", AND(H48>=1400,H48<1450),"1400-1450", AND(H48>=1450,H48<1500),"1450-1500", AND(H48>=1500,H48<1550),"1500-1550", AND(H48>=1550,H48<1600),"1550-1600", AND(H48>=1600,H48<1650),"1600-1650", AND(H48>=1650,H48<1700),"1650-1700", AND(H48>=1700,H48<1750),"1700-1750", AND(H48>=1750,H48<1800),"1750-1800", AND(H48>=1800,H48<1850),"1800-1850", AND(H48>=1850,H48<1900),"1850-1900", AND(H48>=1900,H48<1950),"1900-1950", AND(H48>=1950,H48<=2000),"1950-2000", H48<1000,"Below 1000", TRUE,"Above 2000" )} -> 1600-1650 | N48: {=_xlfn.IFS(H48<500,"0-500",H48<1000,"500-1000",H48<1500,"1000-1500",H48<2000,"1500-2000",H48<2500,"2000-2500",H48<3000,"2500-3000",H48<3500,"3000-3500",H48<4000,"3500-4000",H48<4500,"4000-4500",H48<=5000,"4500-5000",TRUE,"Hbove 5000")} -> 1500-2000 | O48: 9.08 | P48: 13.85 | Q48: 5.87 | R48: 9.8 | S48: {=_xlfn.IFS( R48<0,"< 0", R48<5,"0 to 5", R48<10,"5 to 10", R48<15,"10 to 15", R48<20,"15 to 20", R48<25,"20 to 25", R48<50,"25 to 50", R48<75,"50 to 75", R48<100,"75 to 100", R48<125,"100 to 125", R48<150,"125 to 150", R48<175,"150 to 175", R48<200,"175 to 200", TRUE,"> 200" )} -> 5 to 10 | T48: 643 | U48: 718.15 | V48: 11.69 | W48: {=_xlfn.IFS( V48<-15,"< -15%", V48<-10,"-15% to -10%", V48<-5,"-10% to -5%", V48<0,"-5% to 0%", V48<10,"0% to 10%", V48<20,"10% to 20%", V48<30,"20% to 30%", V48<40,"30% to 40%", V48<50,"40% to 50%", V48<60,"50% to 60%", V48<70,"60% to 70%", V48<80,"70% to 80%", V48<90,"80% to 90%", V48<100,"90% to 100%", TRUE,"> 100%" )} -> 10% to 20% | X48: 749.75 | Y48: 749.95 | Z48: =IF(V48>0, ">0", IF(V48<0, "<0", "=0")) -> >0 | AA48: {=_xlfn.IFS( AND(O48>=0,O48<5),"0-5", AND(O48>=5,O48<15),"5-15", AND(O48>=15,O48<30),"15-30", AND(O48>=30,O48<60),"30-60", AND(O48>=60,O48<90),"60-90", AND(O48>=90,O48<120),"90-120", AND(O48>=120,O48<160),"120-160", AND(O48>=160,O48<200),"160-200", AND(O48>=200,O48<250),"200-250", AND(O48>=250,O48<300),"250-300", O48>=300,">300", TRUE,"Below 0" )} -> 5-15 | AB48: 16.6
A49: 45656 | B49: =TEXT(A49,"yyyy") -> 2024 | C49: Carraro India Ltd | D49: =IFERROR(LEFT(C49,FIND(" ",C49)-1),C49) -> Carraro | E49: =TRIM(SUBSTITUTE(SUBSTITUTE(C49,"Ltd",""),"Lt","")) -> Carraro India | F49: =_xlfn.XLOOKUP(E49,MARKET_PRICE__2[Column2],MARKET_PRICE__2[Column3],"Not found") -> 459.85 | G49: =_xlfn.XLOOKUP(D49,MARKET_PRICE__2[Column12],MARKET_PRICE__2[Column3],"Not found") -> 459.85 | H49: 1250 | K49: =H49/10 -> 125 | L49: {=_xlfn.IFS( AND(H49>=1000,H49<1050),"1000-1050", AND(H49>=1050,H49<1100),"1050-1100", AND(H49>=1100,H49<1150),"1100-1150", AND(H49>=1150,H49<1200),"1150-1200", AND(H49>=1200,H49<1250),"1200-1250", AND(H49>=1250,H49<1300),"1250-1300", AND(H49>=1300,H49<1350),"1300-1350", AND(H49>=1350,H49<1400),"1350-1400", AND(H49>=1400,H49<1450),"1400-1450", AND(H49>=1450,H49<=1500),"1450-1500", H49<1000,"Below 1000", TRUE,"Above 1500" )} -> 1250-1300 | N49: {=_xlfn.IFS(H49<500,"0-500",H49<1000,"500-1000",H49<1500,"1000-1500",H49<2000,"1500-2000",H49<2500,"2000-2500",H49<3000,"2500-3000",H49<3500,"3000-3500",H49<4000,"3500-4000",H49<4500,"4000-4500",H49<=5000,"4500-5000",TRUE,"Hbove 5000")} -> 1000-1500 | O49: 2.21 | P49: 0.6 | Q49: 0.71 | R49: 1.12 | S49: {=_xlfn.IFS( R49<0,"< 0", R49<5,"0 to 5", R49<10,"5 to 10", R49<15,"10 to 15", R49<20,"15 to 20", R49<25,"20 to 25", R49<50,"25 to 50", R49<75,"50 to 75", R49<100,"75 to 100", R49<125,"100 to 125", R49<150,"125 to 150", R49<175,"150 to 175", R49<200,"175 to 200", TRUE,"> 200" )} -> 0 to 5 | T49: 704 | U49: 660 | V49: -6.25 | W49: {=_xlfn.IFS( V49<-15,"< -15%", V49<-10,"-15% to -10%", V49<-5,"-10% to -5%", V49<0,"-5% to 0%", V49<10,"0% to 10%", V49<20,"10% to 20%", V49<30,"20% to 30%", V49<40,"30% to 40%", V49<50,"40% to 50%", V49<60,"50% to 60%", V49<70,"60% to 70%", V49<80,"70% to 80%", V49<90,"80% to 90%", V49<100,"90% to 100%", TRUE,"> 100%" )} -> -10% to -5% | X49: 426.4 | Y49: 426.4 | Z49: =IF(V49>0, ">0", IF(V49<0, "<0", "=0")) -> <0 | AA49: {=_xlfn.IFS( AND(O49>=0,O49<5),"0-5", AND(O49>=5,O49<15),"5-15", AND(O49>=15,O49<30),"15-30", AND(O49>=30,O49<60),"30-60", AND(O49>=60,O49<90),"60-90", AND(O49>=90,O49<120),"90-120", AND(O49>=120,O49<160),"120-160", AND(O49>=160,O49<200),"160-200", AND(O49>=200,O49<250),"200-250", AND(O49>=250,O49<300),"250-300", O49>=300,">300", TRUE,"Below 0" )} -> 0-5 | AB49: -39.43
A50: 45656 | B50: =TEXT(A50,"yyyy") -> 2024 | C50: Senores Pharmaceut | D50: =IFERROR(LEFT(C50,FIND(" ",C50)-1),C50) -> Senores | E50: =TRIM(SUBSTITUTE(SUBSTITUTE(C50,"Ltd",""),"Lt","")) -> Senores Pharmaceut | F50: =_xlfn.XLOOKUP(E50,MARKET_PRICE__2[Column2],MARKET_PRICE__2[Column3],"Not found") -> Not found | G50: =_xlfn.XLOOKUP(D50,MARKET_PRICE__2[Column12],MARKET_PRICE__2[Column3],"Not found") -> 719.85 | H50: 582.11 | J50: {=_xlfn.IFS( AND(H50>=500,H50<550),"500-550", AND(H50>=550,H50<600),"550-600", AND(H50>=600,H50<650),"600-650", AND(H50>=650,H50<700),"650-700", AND(H50>=700,H50<750),"700-750", AND(H50>=750,H50<800),"750-800", AND(H50>=800,H50<850),"800-850", AND(H50>=850,H50<900),"850-900", AND(H50>=900,H50<950),"900-950", AND(H50>=950,H50<=1000),"950-1000", H50<500,"Below 500", TRUE,"Above 1000" )} -> 550-600 | K50: =H50/10 -> 58.211 | N50: {=_xlfn.IFS(H50<500,"0-500",H50<1000,"500-1000",H50<1500,"1000-1500",H50<2000,"1500-2000",H50<2500,"2000-2500",H50<3000,"2500-3000",H50<3500,"3000-3500",H50<4000,"3500-4000",H50<4500,"4000-4500",H50<=5000,"4500-5000",TRUE,"Hbove 5000")} -> 500-1000 | O50: 94.66 | P50: 96.11 | Q50: 89.23 | R50: 93.41 | S50: {=_xlfn.IFS( R50<0,"< 0", R50<5,"0 to 5", R50<10,"5 to 10", R50<15,"10 to 15", R50<20,"15 to 20", R50<25,"20 to 25", R50<50,"25 to 50", R50<75,"50 to 75", R50<100,"75 to 100", R50<125,"100 to 125", R50<150,"125 to 150", R50<175,"150 to 175", R50<200,"175 to 200", TRUE,"> 200" )} -> 75 to 100 | T50: 391 | U50: 593.7 | V50: 51.84 | W50: {=_xlfn.IFS( V50<-15,"< -15%", V50<-10,"-15% to -10%", V50<-5,"-10% to -5%", V50<0,"-5% to 0%", V50<10,"0% to 10%", V50<20,"10% to 20%", V50<30,"20% to 30%", V50<40,"30% to 40%", V50<50,"40% to 50%", V50<60,"50% to 60%", V50<70,"60% to 70%", V50<80,"70% to 80%", V50<90,"80% to 90%", V50<100,"90% to 100%", TRUE,"> 100%" )} -> 50% to 60% | X50: 723.7 | Y50: 724.25 | Z50: =IF(V50>0, ">0", IF(V50<0, "<0", "=0")) -> >0 | AA50: {=_xlfn.IFS( AND(O50>=0,O50<5),"0-5", AND(O50>=5,O50<15),"5-15", AND(O50>=15,O50<30),"15-30", AND(O50>=30,O50<60),"30-60", AND(O50>=60,O50<90),"60-90", AND(O50>=90,O50<120),"90-120", AND(O50>=120,O50<160),"120-160", AND(O50>=160,O50<200),"160-200", AND(O50>=200,O50<250),"200-250", AND(O50>=250,O50<300),"250-300", O50>=300,">300", TRUE,"Below 0" )} -> 90-120 | AB50: 85.09
A51: 45653 | B51: =TEXT(A51,"yyyy") -> 2024 | C51: Transrail Lighting | D51: =IFERROR(LEFT(C51,FIND(" ",C51)-1),C51) -> Transrail | E51: =TRIM(SUBSTITUTE(SUBSTITUTE(C51,"Ltd",""),"Lt","")) -> Transrail Lighting | F51: =_xlfn.XLOOKUP(E51,MARKET_PRICE__2[Column2],MARKET_PRICE__2[Column3],"Not found") -> Not found | G51: =_xlfn.XLOOKUP(D51,MARKET_PRICE__2[Column12],MARKET_PRICE__2[Column3],"Not found") -> 759.10 | H51: 838.91 | J51: {=_xlfn.IFS( AND(H51>=500,H51<550),"500-550", AND(H51>=550,H51<600),"550-600", AND(H51>=600,H51<650),"600-650", AND(H51>=650,H51<700),"650-700", AND(H51>=700,H51<750),"700-750", AND(H51>=750,H51<800),"750-800", AND(H51>=800,H51<850),"800-850", AND(H51>=850,H51<900),"850-900", AND(H51>=900,H51<950),"900-950", AND(H51>=950,H51<=1000),"950-1000", H51<500,"Below 500", TRUE,"Above 1000" )} -> 800-850 | K51: =H51/10 -> 83.891 | N51: {=_xlfn.IFS(H51<500,"0-500",H51<1000,"500-1000",H51<1500,"1000-1500",H51<2000,"1500-2000",H51<2500,"2000-2500",H51<3000,"2500-3000",H51<3500,"3000-3500",H51<4000,"3500-4000",H51<4500,"4000-4500",H51<=5000,"4500-5000",TRUE,"Hbove 5000")} -> 500-1000 | O51: 201.06 | P51: 76.41 | Q51: 22.07 | R51: 80.8 | S51: {=_xlfn.IFS( R51<0,"< 0", R51<5,"0 to 5", R51<10,"5 to 10", R51<15,"10 to 15", R51<20,"15 to 20", R51<25,"20 to 25", R51<50,"25 to 50", R51<75,"50 to 75", R51<100,"75 to 100", R51<125,"100 to 125", R51<150,"125 to 150", R51<175,"150 to 175", R51<200,"175 to 200", TRUE,"> 200" )} -> 75 to 100 | T51: 432 | U51: 585.15 | V51: 35.45 | W51: {=_xlfn.IFS( V51<-15,"< -15%", V51<-10,"-15% to -10%", V51<-5,"-10% to -5%", V51<0,"-5% to 0%", V51<10,"0% to 10%", V51<20,"10% to 20%", V51<30,"20% to 30%", V51<40,"30% to 40%", V51<50,"40% to 50%", V51<60,"50% to 60%", V51<70,"60% to 70%", V51<80,"70% to 80%", V51<90,"80% to 90%", V51<100,"90% to 100%", TRUE,"> 100%" )} -> 30% to 40% | X51: 779.9 | Y51: 779.75 | Z51: =IF(V51>0, ">0", IF(V51<0, "<0", "=0")) -> >0 | AA51: {=_xlfn.IFS( AND(O51>=0,O51<5),"0-5", AND(O51>=5,O51<15),"5-15", AND(O51>=15,O51<30),"15-30", AND(O51>=30,O51<60),"30-60", AND(O51>=60,O51<90),"60-90", AND(O51>=90,O51<120),"90-120", AND(O51>=120,O51<160),"120-160", AND(O51>=160,O51<200),"160-200", AND(O51>=200,O51<250),"200-250", AND(O51>=250,O51<300),"250-300", O51>=300,">300", TRUE,"Below 0" )} -> 200-250 | AB51: 80.53
A52: 45653 | B52: =TEXT(A52,"yyyy") -> 2024 | C52: Dam Capital Adviso | D52: =IFERROR(LEFT(C52,FIND(" ",C52)-1),C52) -> Dam | E52: =TRIM(SUBSTITUTE(SUBSTITUTE(C52,"Ltd",""),"Lt","")) -> Dam Capital Adviso | F52: =_xlfn.XLOOKUP(E52,MARKET_PRICE__2[Column2],MARKET_PRICE__2[Column3],"Not found") -> Not found | G52: =_xlfn.XLOOKUP(D52,MARKET_PRICE__2[Column12],MARKET_PRICE__2[Column3],"Not found") -> 247.85 | H52: 840.25 | J52: {=_xlfn.IFS( AND(H52>=500,H52<550),"500-550", AND(H52>=550,H52<600),"550-600", AND(H52>=600,H52<650),"600-650", AND(H52>=650,H52<700),"650-700", AND(H52>=700,H52<750),"700-750", AND(H52>=750,H52<800),"750-800", AND(H52>=800,H52<850),"800-850", AND(H52>=850,H52<900),"850-900", AND(H52>=900,H52<950),"900-950", AND(H52>=950,H52<=1000),"950-1000", H52<500,"Below 500", TRUE,"Above 1000" )} -> 800-850 | K52: =H52/10 -> 84.025 | N52: {=_xlfn.IFS(H52<500,"0-500",H52<1000,"500-1000",H52<1500,"1000-1500",H52<2000,"1500-2000",H52<2500,"2000-2500",H52<3000,"2500-3000",H52<3500,"3000-3500",H52<4000,"3500-4000",H52<4500,"4000-4500",H52<=5000,"4500-5000",TRUE,"Hbove 5000")} -> 500-1000 | O52: 166.33 | P52: 98.62 | Q52: 27.13 | R52: 82.08 | S52: {=_xlfn.IFS( R52<0,"< 0", R52<5,"0 to 5", R52<10,"5 to 10", R52<15,"10 to 15", R52<20,"15 to 20", R52<25,"20 to 25", R52<50,"25 to 50", R52<75,"50 to 75", R52<100,"75 to 100", R52<125,"100 to 125", R52<150,"125 to 150", R52<175,"150 to 175", R52<200,"175 to 200", TRUE,"> 200" )} -> 75 to 100 | T52: 283 | U52: 392.9 | V52: 38.83 | W52: {=_xlfn.IFS( V52<-15,"< -15%", V52<-10,"-15% to -10%", V52<-5,"-10% to -5%", V52<0,"-5% to 0%", V52<10,"0% to 10%", V52<20,"10% to 20%", V52<30,"20% to 30%", V52<40,"30% to 40%", V52<50,"40% to 50%", V52<60,"50% to 60%", V52<70,"60% to 70%", V52<80,"70% to 80%", V52<90,"80% to 90%", V52<100,"90% to 100%", TRUE,"> 100%" )} -> 30% to 40% | X52: 223.8 | Y52: 224.08 | Z52: =IF(V52>0, ">0", IF(V52<0, "<0", "=0")) -> >0 | AA52: {=_xlfn.IFS( AND(O52>=0,O52<5),"0-5", AND(O52>=5,O52<15),"5-15", AND(O52>=15,O52<30),"15-30", AND(O52>=30,O52<60),"30-60", AND(O52>=60,O52<90),"60-90", AND(O52>=90,O52<120),"90-120", AND(O52>=120,O52<160),"120-160", AND(O52>=160,O52<200),"160-200", AND(O52>=200,O52<250),"200-250", AND(O52>=250,O52<300),"250-300", O52>=300,">300", TRUE,"Below 0" )} -> 160-200 | AB52: -20.92
A53: 45653 | B53: =TEXT(A53,"yyyy") -> 2024 | C53: Mamata Machinery L | D53: =IFERROR(LEFT(C53,FIND(" ",C53)-1),C53) -> Mamata | E53: =TRIM(SUBSTITUTE(SUBSTITUTE(C53,"Ltd",""),"Lt","")) -> Mamata Machinery L | F53: =_xlfn.XLOOKUP(E53,MARKET_PRICE__2[Column2],MARKET_PRICE__2[Column3],"Not found") -> Not found | G53: =_xlfn.XLOOKUP(D53,MARKET_PRICE__2[Column12],MARKET_PRICE__2[Column3],"Not found") -> 447.85 | H53: 179.35 | I53: {=_xlfn.IFS( H53<50,"0-50", H53<100,"50-100", H53<150,"100-150", H53<200,"150-200", H53<250,"200-250", H53<300,"250-300", H53<350,"300-350", H53<400,"350-400", H53<450,"400-450", H53<=500,"450-500", TRUE,"Above 500" )} -> 150-200 | K53: =H53/10 -> 17.935 | N53: {=_xlfn.IFS(H53<500,"0-500",H53<1000,"500-1000",H53<1500,"1000-1500",H53<2000,"1500-2000",H53<2500,"2000-2500",H53<3000,"2500-3000",H53<3500,"3000-3500",H53<4000,"3500-4000",H53<4500,"4000-4500",H53<=5000,"4500-5000",TRUE,"Hbove 5000")} -> 0-500 | O53: 235.88 | P53: 274.38 | Q53: 138.08 | R53: 194.95 | S53: {=_xlfn.IFS( R53<0,"< 0", R53<5,"0 to 5", R53<10,"5 to 10", R53<15,"10 to 15", R53<20,"15 to 20", R53<25,"20 to 25", R53<50,"25 to 50", R53<75,"50 to 75", R53<100,"75 to 100", R53<125,"100 to 125", R53<150,"125 to 150", R53<175,"150 to 175", R53<200,"175 to 200", TRUE,"> 200" )} -> 175 to 200 | T53: 243 | U53: 600 | V53: 146.91 | W53: {=_xlfn.IFS( V53<-15,"< -15%", V53<-10,"-15% to -10%", V53<-5,"-10% to -5%", V53<0,"-5% to 0%", V53<10,"0% to 10%", V53<20,"10% to 20%", V53<30,"20% to 30%", V53<40,"30% to 40%", V53<50,"40% to 50%", V53<60,"50% to 60%", V53<70,"60% to 70%", V53<80,"70% to 80%", V53<90,"80% to 90%", V53<100,"90% to 100%", TRUE,"> 100%" )} -> > 100% | X53: 413.9 | Y53: 414.25 | Z53: =IF(V53>0, ">0", IF(V53<0, "<0", "=0")) -> >0 | AA53: {=_xlfn.IFS( AND(O53>=0,O53<5),"0-5", AND(O53>=5,O53<15),"5-15", AND(O53>=15,O53<30),"15-30", AND(O53>=30,O53<60),"30-60", AND(O53>=60,O53<90),"60-90", AND(O53>=90,O53<120),"90-120", AND(O53>=120,O53<160),"120-160", AND(O53>=160,O53<200),"160-200", AND(O53>=200,O53<250),"200-250", AND(O53>=250,O53<300),"250-300", O53>=300,">300", TRUE,"Below 0" )} -> 200-250 | AB53: 70.33
A54: 45653 | B54: =TEXT(A54,"yyyy") -> 2024 | C54: Sanathan Textiles | D54: =IFERROR(LEFT(C54,FIND(" ",C54)-1),C54) -> Sanathan | E54: =TRIM(SUBSTITUTE(SUBSTITUTE(C54,"Ltd",""),"Lt","")) -> Sanathan Textiles | F54: =_xlfn.XLOOKUP(E54,MARKET_PRICE__2[Column2],MARKET_PRICE__2[Column3],"Not found") -> Not found | G54: =_xlfn.XLOOKUP(D54,MARKET_PRICE__2[Column12],MARKET_PRICE__2[Column3],"Not found") -> 500.00 | H54: 550 | J54: {=_xlfn.IFS( AND(H54>=500,H54<550),"500-550", AND(H54>=550,H54<600),"550-600", AND(H54>=600,H54<650),"600-650", AND(H54>=650,H54<700),"650-700", AND(H54>=700,H54<750),"700-750", AND(H54>=750,H54<800),"750-800", AND(H54>=800,H54<850),"800-850", AND(H54>=850,H54<900),"850-900", AND(H54>=900,H54<950),"900-950", AND(H54>=950,H54<=1000),"950-1000", H54<500,"Below 500", TRUE,"Above 1000" )} -> 550-600 | K54: =H54/10 -> 55 | N54: {=_xlfn.IFS(H54<500,"0-500",H54<1000,"500-1000",H54<1500,"1000-1500",H54<2000,"1500-2000",H54<2500,"2000-2500",H54<3000,"2500-3000",H54<3500,"3000-3500",H54<4000,"3500-4000",H54<4500,"4000-4500",H54<=5000,"4500-5000",TRUE,"Hbove 5000")} -> 500-1000 | O54: 75.62 | P54: 42.21 | Q54: 8.93 | R54: 35.12 | S54: {=_xlfn.IFS( R54<0,"< 0", R54<5,"0 to 5", R54<10,"5 to 10", R54<15,"10 to 15", R54<20,"15 to 20", R54<25,"20 to 25", R54<50,"25 to 50", R54<75,"50 to 75", R54<100,"75 to 100", R54<125,"100 to 125", R54<150,"125 to 150", R54<175,"150 to 175", R54<200,"175 to 200", TRUE,"> 200" )} -> 25 to 50 | T54: 321 | U54: 419.1 | V54: 30.56 | W54: {=_xlfn.IFS( V54<-15,"< -15%", V54<-10,"-15% to -10%", V54<-5,"-10% to -5%", V54<0,"-5% to 0%", V54<10,"0% to 10%", V54<20,"10% to 20%", V54<30,"20% to 30%", V54<40,"30% to 40%", V54<50,"40% to 50%", V54<60,"50% to 60%", V54<70,"60% to 70%", V54<80,"70% to 80%", V54<90,"80% to 90%", V54<100,"90% to 100%", TRUE,"> 100%" )} -> 30% to 40% | X54: 508.95 | Y54: 507.8 | Z54: =IF(V54>0, ">0", IF(V54<0, "<0", "=0")) -> >0 | AA54: {=_xlfn.IFS( AND(O54>=0,O54<5),"0-5", AND(O54>=5,O54<15),"5-15", AND(O54>=15,O54<30),"15-30", AND(O54>=30,O54<60),"30-60", AND(O54>=60,O54<90),"60-90", AND(O54>=90,O54<120),"90-120", AND(O54>=120,O54<160),"120-160", AND(O54>=160,O54<200),"160-200", AND(O54>=200,O54<250),"200-250", AND(O54>=250,O54<300),"250-300", O54>=300,">300", TRUE,"Below 0" )} -> 60-90 | AB54: 58.55
A55: 45653 | B55: =TEXT(A55,"yyyy") -> 2024 | C55: Concord Enviro Sys | D55: =IFERROR(LEFT(C55,FIND(" ",C55)-1),C55) -> Concord | E55: =TRIM(SUBSTITUTE(SUBSTITUTE(C55,"Ltd",""),"Lt","")) -> Concord Enviro Sys | F55: =_xlfn.XLOOKUP(E55,MARKET_PRICE__2[Column2],MARKET_PRICE__2[Column3],"Not found") -> Not found | G55: =_xlfn.XLOOKUP(D55,MARKET_PRICE__2[Column12],MARKET_PRICE__2[Column3],"Not found") -> 2682.30 | H55: 500.33 | J55: {=_xlfn.IFS( AND(H55>=500,H55<550),"500-550", AND(H55>=550,H55<600),"550-600", AND(H55>=600,H55<650),"600-650", AND(H55>=650,H55<700),"650-700", AND(H55>=700,H55<750),"700-750", AND(H55>=750,H55<800),"750-800", AND(H55>=800,H55<850),"800-850", AND(H55>=850,H55<900),"850-900", AND(H55>=900,H55<950),"900-950", AND(H55>=950,H55<=1000),"950-1000", H55<500,"Below 500", TRUE,"Above 1000" )} -> 500-550 | K55: =H55/10 -> 50.033 | N55: {=_xlfn.IFS(H55<500,"0-500",H55<1000,"500-1000",H55<1500,"1000-1500",H55<2000,"1500-2000",H55<2500,"2000-2500",H55<3000,"2500-3000",H55<3500,"3000-3500",H55<4000,"3500-4000",H55<4500,"4000-4500",H55<=5000,"4500-5000",TRUE,"Hbove 5000")} -> 500-1000 | O55: 17.32 | P55: 14.2 | Q55: 5.56 | R55: 10.67 | S55: {=_xlfn.IFS( R55<0,"< 0", R55<5,"0 to 5", R55<10,"5 to 10", R55<15,"10 to 15", R55<20,"15 to 20", R55<25,"20 to 25", R55<50,"25 to 50", R55<75,"50 to 75", R55<100,"75 to 100", R55<125,"100 to 125", R55<150,"125 to 150", R55<175,"150 to 175", R55<200,"175 to 200", TRUE,"> 200" )} -> 10 to 15 | T55: 701 | U55: 832 | V55: 18.69 | W55: {=_xlfn.IFS( V55<-15,"< -15%", V55<-10,"-15% to -10%", V55<-5,"-10% to -5%", V55<0,"-5% to 0%", V55<10,"0% to 10%", V55<20,"10% to 20%", V55<30,"20% to 30%", V55<40,"30% to 40%", V55<50,"40% to 50%", V55<60,"50% to 60%", V55<70,"60% to 70%", V55<80,"70% to 80%", V55<90,"80% to 90%", V55<100,"90% to 100%", TRUE,"> 100%" )} -> 10% to 20% | X55: 548.4 | Y55: 550.5 | Z55: =IF(V55>0, ">0", IF(V55<0, "<0", "=0")) -> >0 | AA55: {=_xlfn.IFS( AND(O55>=0,O55<5),"0-5", AND(O55>=5,O55<15),"5-15", AND(O55>=15,O55<30),"15-30", AND(O55>=30,O55<60),"30-60", AND(O55>=60,O55<90),"60-90", AND(O55>=90,O55<120),"90-120", AND(O55>=120,O55<160),"120-160", AND(O55>=160,O55<200),"160-200", AND(O55>=200,O55<250),"200-250", AND(O55>=250,O55<300),"250-300", O55>=300,">300", TRUE,"Below 0" )} -> 15-30 | AB55: -21.77
A56: 45646 | B56: =TEXT(A56,"yyyy") -> 2024 | C56: International Gemm | D56: =IFERROR(LEFT(C56,FIND(" ",C56)-1),C56) -> International | E56: =TRIM(SUBSTITUTE(SUBSTITUTE(C56,"Ltd",""),"Lt","")) -> International Gemm | F56: =_xlfn.XLOOKUP(E56,MARKET_PRICE__2[Column2],MARKET_PRICE__2[Column3],"Not found") -> Not found | G56: =_xlfn.XLOOKUP(D56,MARKET_PRICE__2[Column12],MARKET_PRICE__2[Column3],"Not found") -> 345.05 | H56: 4225 | K56: =H56/10 -> 422.5 | N56: {=_xlfn.IFS(H56<500,"0-500",H56<1000,"500-1000",H56<1500,"1000-1500",H56<2000,"1500-2000",H56<2500,"2000-2500",H56<3000,"2500-3000",H56<3500,"3000-3500",H56<4000,"3500-4000",H56<4500,"4000-4500",H56<=5000,"4500-5000",TRUE,"Hbove 5000")} -> 4000-4500 | O56: 45.8 | P56: 24.84 | Q56: 11.21 | R56: 33.78 | S56: {=_xlfn.IFS( R56<0,"< 0", R56<5,"0 to 5", R56<10,"5 to 10", R56<15,"10 to 15", R56<20,"15 to 20", R56<25,"20 to 25", R56<50,"25 to 50", R56<75,"50 to 75", R56<100,"75 to 100", R56<125,"100 to 125", R56<150,"125 to 150", R56<175,"150 to 175", R56<200,"175 to 200", TRUE,"> 200" )} -> 25 to 50 | T56: 417 | U56: 504.85 | V56: 21.07 | W56: {=_xlfn.IFS( V56<-15,"< -15%", V56<-10,"-15% to -10%", V56<-5,"-10% to -5%", V56<0,"-5% to 0%", V56<10,"0% to 10%", V56<20,"10% to 20%", V56<30,"20% to 30%", V56<40,"30% to 40%", V56<50,"40% to 50%", V56<60,"50% to 60%", V56<70,"60% to 70%", V56<80,"70% to 80%", V56<90,"80% to 90%", V56<100,"90% to 100%", TRUE,"> 100%" )} -> 20% to 30% | X56: 350.85 | Y56: 350.8 | Z56: =IF(V56>0, ">0", IF(V56<0, "<0", "=0")) -> >0 | AA56: {=_xlfn.IFS( AND(O56>=0,O56<5),"0-5", AND(O56>=5,O56<15),"5-15", AND(O56>=15,O56<30),"15-30", AND(O56>=30,O56<60),"30-60", AND(O56>=60,O56<90),"60-90", AND(O56>=90,O56<120),"90-120", AND(O56>=120,O56<160),"120-160", AND(O56>=160,O56<200),"160-200", AND(O56>=200,O56<250),"200-250", AND(O56>=250,O56<300),"250-300", O56>=300,">300", TRUE,"Below 0" )} -> 30-60 | AB56: -15.86
A57: 45645 | B57: =TEXT(A57,"yyyy") -> 2024 | C57: Inventurus Knowled | D57: =IFERROR(LEFT(C57,FIND(" ",C57)-1),C57) -> Inventurus | E57: =TRIM(SUBSTITUTE(SUBSTITUTE(C57,"Ltd",""),"Lt","")) -> Inventurus Knowled | F57: =_xlfn.XLOOKUP(E57,MARKET_PRICE__2[Column2],MARKET_PRICE__2[Column3],"Not found") -> Not found | G57: =_xlfn.XLOOKUP(D57,MARKET_PRICE__2[Column12],MARKET_PRICE__2[Column3],"Not found") -> 1524.35 | H57: 2497.92 | K57: =H57/10 -> 249.792 | N57: {=_xlfn.IFS(H57<500,"0-500",H57<1000,"500-1000",H57<1500,"1000-1500",H57<2000,"1500-2000",H57<2500,"2000-2500",H57<3000,"2500-3000",H57<3500,"3000-3500",H57<4000,"3500-4000",H57<4500,"4000-4500",H57<=5000,"4500-5000",TRUE,"Hbove 5000")} -> 2000-2500 | O57: 80.64 | P57: 23.25 | Q57: 14.55 | R57: 52.68 | S57: {=_xlfn.IFS( R57<0,"< 0", R57<5,"0 to 5", R57<10,"5 to 10", R57<15,"10 to 15", R57<20,"15 to 20", R57<25,"20 to 25", R57<50,"25 to 50", R57<75,"50 to 75", R57<100,"75 to 100", R57<125,"100 to 125", R57<150,"125 to 150", R57<175,"150 to 175", R57<200,"175 to 200", TRUE,"> 200" )} -> 50 to 75 | T57: 1329 | U57: 1856 | V57: 39.65 | W57: {=_xlfn.IFS( V57<-15,"< -15%", V57<-10,"-15% to -10%", V57<-5,"-10% to -5%", V57<0,"-5% to 0%", V57<10,"0% to 10%", V57<20,"10% to 20%", V57<30,"20% to 30%", V57<40,"30% to 40%", V57<50,"40% to 50%", V57<60,"50% to 60%", V57<70,"60% to 70%", V57<80,"70% to 80%", V57<90,"80% to 90%", V57<100,"90% to 100%", TRUE,"> 100%" )} -> 30% to 40% | X57: 1554.9 | Y57: 1554.6 | Z57: =IF(V57>0, ">0", IF(V57<0, "<0", "=0")) -> >0 | AA57: {=_xlfn.IFS( AND(O57>=0,O57<5),"0-5", AND(O57>=5,O57<15),"5-15", AND(O57>=15,O57<30),"15-30", AND(O57>=30,O57<60),"30-60", AND(O57>=60,O57<90),"60-90", AND(O57>=90,O57<120),"90-120", AND(O57>=120,O57<160),"120-160", AND(O57>=160,O57<200),"160-200", AND(O57>=200,O57<250),"200-250", AND(O57>=250,O57<300),"250-300", O57>=300,">300", TRUE,"Below 0" )} -> 60-90 | AB57: 17
A58: 45644 | B58: =TEXT(A58,"yyyy") -> 2024 | C58: Sai Life Sciences | D58: =IFERROR(LEFT(C58,FIND(" ",C58)-1),C58) -> Sai | E58: =TRIM(SUBSTITUTE(SUBSTITUTE(C58,"Ltd",""),"Lt","")) -> Sai Life Sciences | F58: =_xlfn.XLOOKUP(E58,MARKET_PRICE__2[Column2],MARKET_PRICE__2[Column3],"Not found") -> Not found | G58: =_xlfn.XLOOKUP(D58,MARKET_PRICE__2[Column12],MARKET_PRICE__2[Column3],"Not found") -> 32.80 | H58: 3042.62 | K58: =H58/10 -> 304.262 | N58: {=_xlfn.IFS(H58<500,"0-500",H58<1000,"500-1000",H58<1500,"1000-1500",H58<2000,"1500-2000",H58<2500,"2000-2500",H58<3000,"2500-3000",H58<3500,"3000-3500",H58<4000,"3500-4000",H58<4500,"4000-4500",H58<=5000,"4500-5000",TRUE,"Hbove 5000")} -> 3000-3500 | O58: 30.93 | P58: 4.92 | Q58: 1.37 | R58: 10.26 | S58: {=_xlfn.IFS( R58<0,"< 0", R58<5,"0 to 5", R58<10,"5 to 10", R58<15,"10 to 15", R58<20,"15 to 20", R58<25,"20 to 25", R58<50,"25 to 50", R58<75,"50 to 75", R58<100,"75 to 100", R58<125,"100 to 125", R58<150,"125 to 150", R58<175,"150 to 175", R58<200,"175 to 200", TRUE,"> 200" )} -> 10 to 15 | T58: 549 | U58: 660 | V58: 20.22 | W58: {=_xlfn.IFS( V58<-15,"< -15%", V58<-10,"-15% to -10%", V58<-5,"-10% to -5%", V58<0,"-5% to 0%", V58<10,"0% to 10%", V58<20,"10% to 20%", V58<30,"20% to 30%", V58<40,"30% to 40%", V58<50,"40% to 50%", V58<60,"50% to 60%", V58<70,"60% to 70%", V58<80,"70% to 80%", V58<90,"80% to 90%", V58<100,"90% to 100%", TRUE,"> 100%" )} -> 20% to 30% | X58: 925.15 | Y58: 925.9 | Z58: =IF(V58>0, ">0", IF(V58<0, "<0", "=0")) -> >0 | AA58: {=_xlfn.IFS( AND(O58>=0,O58<5),"0-5", AND(O58>=5,O58<15),"5-15", AND(O58>=15,O58<30),"15-30", AND(O58>=30,O58<60),"30-60", AND(O58>=60,O58<90),"60-90", AND(O58>=90,O58<120),"90-120", AND(O58>=120,O58<160),"120-160", AND(O58>=160,O58<200),"160-200", AND(O58>=200,O58<250),"200-250", AND(O58>=250,O58<300),"250-300", O58>=300,">300", TRUE,"Below 0" )} -> 30-60 | AB58: 68.52
A59: 45644 | B59: =TEXT(A59,"yyyy") -> 2024 | C59: Vishal Mega Mart L | D59: =IFERROR(LEFT(C59,FIND(" ",C59)-1),C59) -> Vishal | E59: =TRIM(SUBSTITUTE(SUBSTITUTE(C59,"Ltd",""),"Lt","")) -> Vishal Mega Mart L | F59: =_xlfn.XLOOKUP(E59,MARKET_PRICE__2[Column2],MARKET_PRICE__2[Column3],"Not found") -> Not found | G59: =_xlfn.XLOOKUP(D59,MARKET_PRICE__2[Column12],MARKET_PRICE__2[Column3],"Not found") -> 148.05 | H59: 8000 | K59: =H59/10 -> 800 | N59: {=_xlfn.IFS(H59<500,"0-500",H59<1000,"500-1000",H59<1500,"1000-1500",H59<2000,"1500-2000",H59<2500,"2000-2500",H59<3000,"2500-3000",H59<3500,"3000-3500",H59<4000,"3500-4000",H59<4500,"4000-4500",H59<=5000,"4500-5000",TRUE,"Hbove 5000")} -> Hbove 5000 | O59: 80.75 | P59: 14.25 | Q59: 2.31 | R59: 27.28 | S59: {=_xlfn.IFS( R59<0,"< 0", R59<5,"0 to 5", R59<10,"5 to 10", R59<15,"10 to 15", R59<20,"15 to 20", R59<25,"20 to 25", R59<50,"25 to 50", R59<75,"50 to 75", R59<100,"75 to 100", R59<125,"100 to 125", R59<150,"125 to 150", R59<175,"150 to 175", R59<200,"175 to 200", TRUE,"> 200" )} -> 25 to 50 | T59: 78 | U59: 110 | V59: 41.03 | W59: {=_xlfn.IFS( V59<-15,"< -15%", V59<-10,"-15% to -10%", V59<-5,"-10% to -5%", V59<0,"-5% to 0%", V59<10,"0% to 10%", V59<20,"10% to 20%", V59<30,"20% to 30%", V59<40,"30% to 40%", V59<50,"40% to 50%", V59<60,"50% to 60%", V59<70,"60% to 70%", V59<80,"70% to 80%", V59<90,"80% to 90%", V59<100,"90% to 100%", TRUE,"> 100%" )} -> 40% to 50% | X59: 150.6 | Y59: 150.67 | Z59: =IF(V59>0, ">0", IF(V59<0, "<0", "=0")) -> >0 | AA59: {=_xlfn.IFS( AND(O59>=0,O59<5),"0-5", AND(O59>=5,O59<15),"5-15", AND(O59>=15,O59<30),"15-30", AND(O59>=30,O59<60),"30-60", AND(O59>=60,O59<90),"60-90", AND(O59>=90,O59<120),"90-120", AND(O59>=120,O59<160),"120-160", AND(O59>=160,O59<200),"160-200", AND(O59>=200,O59<250),"200-250", AND(O59>=250,O59<300),"250-300", O59>=300,">300", TRUE,"Below 0" )} -> 60-90 | AB59: 93.08
A60: 45644 | B60: =TEXT(A60,"yyyy") -> 2024 | C60: One Mobikwik Syste | D60: =IFERROR(LEFT(C60,FIND(" ",C60)-1),C60) -> One | E60: =TRIM(SUBSTITUTE(SUBSTITUTE(C60,"Ltd",""),"Lt","")) -> One Mobikwik Syste | F60: =_xlfn.XLOOKUP(E60,MARKET_PRICE__2[Column2],MARKET_PRICE__2[Column3],"Not found") -> Not found | G60: =_xlfn.XLOOKUP(D60,MARKET_PRICE__2[Column12],MARKET_PRICE__2[Column3],"Not found") -> 277.30 | H60: 572 | J60: {=_xlfn.IFS( AND(H60>=500,H60<550),"500-550", AND(H60>=550,H60<600),"550-600", AND(H60>=600,H60<650),"600-650", AND(H60>=650,H60<700),"650-700", AND(H60>=700,H60<750),"700-750", AND(H60>=750,H60<800),"750-800", AND(H60>=800,H60<850),"800-850", AND(H60>=850,H60<900),"850-900", AND(H60>=900,H60<950),"900-950", AND(H60>=950,H60<=1000),"950-1000", H60<500,"Below 500", TRUE,"Above 1000" )} -> 550-600 | K60: =H60/10 -> 57.2 | N60: {=_xlfn.IFS(H60<500,"0-500",H60<1000,"500-1000",H60<1500,"1000-1500",H60<2000,"1500-2000",H60<2500,"2000-2500",H60<3000,"2500-3000",H60<3500,"3000-3500",H60<4000,"3500-4000",H60<4500,"4000-4500",H60<=5000,"4500-5000",TRUE,"Hbove 5000")} -> 500-1000 | O60: 119.5 | P60: 108.95 | Q60: 134.67 | R60: 119.38 | S60: {=_xlfn.IFS( R60<0,"< 0", R60<5,"0 to 5", R60<10,"5 to 10", R60<15,"10 to 15", R60<20,"15 to 20", R60<25,"20 to 25", R60<50,"25 to 50", R60<75,"50 to 75", R60<100,"75 to 100", R60<125,"100 to 125", R60<150,"125 to 150", R60<175,"150 to 175", R60<200,"175 to 200", TRUE,"> 200" )} -> 100 to 125 | T60: 279 | U60: 442.25 | V60: 58.51 | W60: {=_xlfn.IFS( V60<-15,"< -15%", V60<-10,"-15% to -10%", V60<-5,"-10% to -5%", V60<0,"-5% to 0%", V60<10,"0% to 10%", V60<20,"10% to 20%", V60<30,"20% to 30%", V60<40,"30% to 40%", V60<50,"40% to 50%", V60<60,"50% to 60%", V60<70,"60% to 70%", V60<80,"70% to 80%", V60<90,"80% to 90%", V60<100,"90% to 100%", TRUE,"> 100%" )} -> 50% to 60% | X60: 228.95 | Y60: 228.98 | Z60: =IF(V60>0, ">0", IF(V60<0, "<0", "=0")) -> >0 | AA60: {=_xlfn.IFS( AND(O60>=0,O60<5),"0-5", AND(O60>=5,O60<15),"5-15", AND(O60>=15,O60<30),"15-30", AND(O60>=30,O60<60),"30-60", AND(O60>=60,O60<90),"60-90", AND(O60>=90,O60<120),"90-120", AND(O60>=120,O60<160),"120-160", AND(O60>=160,O60<200),"160-200", AND(O60>=200,O60<250),"200-250", AND(O60>=250,O60<300),"250-300", O60>=300,">300", TRUE,"Below 0" )} -> 90-120 | AB60: -17.94
A61: 45632 | B61: =TEXT(A61,"yyyy") -> 2024 | C61: Suraksha Diagnosti | D61: =IFERROR(LEFT(C61,FIND(" ",C61)-1),C61) -> Suraksha | E61: =TRIM(SUBSTITUTE(SUBSTITUTE(C61,"Ltd",""),"Lt","")) -> Suraksha Diagnosti | F61: =_xlfn.XLOOKUP(E61,MARKET_PRICE__2[Column2],MARKET_PRICE__2[Column3],"Not found") -> Not found | G61: =_xlfn.XLOOKUP(D61,MARKET_PRICE__2[Column12],MARKET_PRICE__2[Column3],"Not found") -> 292.70 | H61: 846.25 | J61: {=_xlfn.IFS( AND(H61>=500,H61<550),"500-550", AND(H61>=550,H61<600),"550-600", AND(H61>=600,H61<650),"600-650", AND(H61>=650,H61<700),"650-700", AND(H61>=700,H61<750),"700-750", AND(H61>=750,H61<800),"750-800", AND(H61>=800,H61<850),"800-850", AND(H61>=850,H61<900),"850-900", AND(H61>=900,H61<950),"900-950", AND(H61>=950,H61<=1000),"950-1000", H61<500,"Below 500", TRUE,"Above 1000" )} -> 800-850 | K61: =H61/10 -> 84.625 | N61: {=_xlfn.IFS(H61<500,"0-500",H61<1000,"500-1000",H61<1500,"1000-1500",H61<2000,"1500-2000",H61<2500,"2000-2500",H61<3000,"2500-3000",H61<3500,"3000-3500",H61<4000,"3500-4000",H61<4500,"4000-4500",H61<=5000,"4500-5000",TRUE,"Hbove 5000")} -> 500-1000 | O61: 1.74 | P61: 1.41 | Q61: 0.95 | R61: 1.27 | S61: {=_xlfn.IFS( R61<0,"< 0", R61<5,"0 to 5", R61<10,"5 to 10", R61<15,"10 to 15", R61<20,"15 to 20", R61<25,"20 to 25", R61<50,"25 to 50", R61<75,"50 to 75", R61<100,"75 to 100", R61<125,"100 to 125", R61<150,"125 to 150", R61<175,"150 to 175", R61<200,"175 to 200", TRUE,"> 200" )} -> 0 to 5 | T61: 441 | U61: 437 | V61: -0.91 | W61: {=_xlfn.IFS( V61<-15,"< -15%", V61<-10,"-15% to -10%", V61<-5,"-10% to -5%", V61<0,"-5% to 0%", V61<10,"0% to 10%", V61<20,"10% to 20%", V61<30,"20% to 30%", V61<40,"30% to 40%", V61<50,"40% to 50%", V61<60,"50% to 60%", V61<70,"60% to 70%", V61<80,"70% to 80%", V61<90,"80% to 90%", V61<100,"90% to 100%", TRUE,"> 100%" )} -> -5% to 0% | X61: 314.2 | Y61: 314.25 | Z61: =IF(V61>0, ">0", IF(V61<0, "<0", "=0")) -> <0 | AA61: {=_xlfn.IFS( AND(O61>=0,O61<5),"0-5", AND(O61>=5,O61<15),"5-15", AND(O61>=15,O61<30),"15-30", AND(O61>=30,O61<60),"30-60", AND(O61>=60,O61<90),"60-90", AND(O61>=90,O61<120),"90-120", AND(O61>=120,O61<160),"120-160", AND(O61>=160,O61<200),"160-200", AND(O61>=200,O61<250),"200-250", AND(O61>=250,O61<300),"250-300", O61>=300,">300", TRUE,"Below 0" )} -> 0-5 | AB61: -28.75
A62: 45625 | B62: =TEXT(A62,"yyyy") -> 2024 | C62: Enviro Infra Engin | D62: =IFERROR(LEFT(C62,FIND(" ",C62)-1),C62) -> Enviro | E62: =TRIM(SUBSTITUTE(SUBSTITUTE(C62,"Ltd",""),"Lt","")) -> Enviro Infra Engin | F62: =_xlfn.XLOOKUP(E62,MARKET_PRICE__2[Column2],MARKET_PRICE__2[Column3],"Not found") -> Not found | G62: =_xlfn.XLOOKUP(D62,MARKET_PRICE__2[Column12],MARKET_PRICE__2[Column3],"Not found") -> 243.15 | H62: 650.3 | J62: {=_xlfn.IFS( AND(H62>=500,H62<550),"500-550", AND(H62>=550,H62<600),"550-600", AND(H62>=600,H62<650),"600-650", AND(H62>=650,H62<700),"650-700", AND(H62>=700,H62<750),"700-750", AND(H62>=750,H62<800),"750-800", AND(H62>=800,H62<850),"800-850", AND(H62>=850,H62<900),"850-900", AND(H62>=900,H62<950),"900-950", AND(H62>=950,H62<=1000),"950-1000", H62<500,"Below 500", TRUE,"Above 1000" )} -> 650-700 | K62: =H62/10 -> 65.03 | N62: {=_xlfn.IFS(H62<500,"0-500",H62<1000,"500-1000",H62<1500,"1000-1500",H62<2000,"1500-2000",H62<2500,"2000-2500",H62<3000,"2500-3000",H62<3500,"3000-3500",H62<4000,"3500-4000",H62<4500,"4000-4500",H62<=5000,"4500-5000",TRUE,"Hbove 5000")} -> 500-1000 | O62: 157.05 | P62: 153.8 | Q62: 24.48 | R62: 89.9 | S62: {=_xlfn.IFS( R62<0,"< 0", R62<5,"0 to 5", R62<10,"5 to 10", R62<15,"10 to 15", R62<20,"15 to 20", R62<25,"20 to 25", R62<50,"25 to 50", R62<75,"50 to 75", R62<100,"75 to 100", R62<125,"100 to 125", R62<150,"125 to 150", R62<175,"150 to 175", R62<200,"175 to 200", TRUE,"> 200" )} -> 75 to 100 | T62: 148 | U62: 218 | V62: 47.3 | W62: {=_xlfn.IFS( V62<-15,"< -15%", V62<-10,"-15% to -10%", V62<-5,"-10% to -5%", V62<0,"-5% to 0%", V62<10,"0% to 10%", V62<20,"10% to 20%", V62<30,"20% to 30%", V62<40,"30% to 40%", V62<50,"40% to 50%", V62<60,"50% to 60%", V62<70,"60% to 70%", V62<80,"70% to 80%", V62<90,"80% to 90%", V62<100,"90% to 100%", TRUE,"> 100%" )} -> 40% to 50% | X62: 268.1 | Y62: 268.25 | Z62: =IF(V62>0, ">0", IF(V62<0, "<0", "=0")) -> >0 | AA62: {=_xlfn.IFS( AND(O62>=0,O62<5),"0-5", AND(O62>=5,O62<15),"5-15", AND(O62>=15,O62<30),"15-30", AND(O62>=30,O62<60),"30-60", AND(O62>=60,O62<90),"60-90", AND(O62>=90,O62<120),"90-120", AND(O62>=120,O62<160),"120-160", AND(O62>=160,O62<200),"160-200", AND(O62>=200,O62<250),"200-250", AND(O62>=250,O62<300),"250-300", O62>=300,">300", TRUE,"Below 0" )} -> 120-160 | AB62: 81.15
A63: 45623 | B63: =TEXT(A63,"yyyy") -> 2024 | C63: NTPC Green Energy | D63: =IFERROR(LEFT(C63,FIND(" ",C63)-1),C63) -> NTPC | E63: =TRIM(SUBSTITUTE(SUBSTITUTE(C63,"Ltd",""),"Lt","")) -> NTPC Green Energy | F63: =_xlfn.XLOOKUP(E63,MARKET_PRICE__2[Column2],MARKET_PRICE__2[Column3],"Not found") -> Not found | G63: =_xlfn.XLOOKUP(D63,MARKET_PRICE__2[Column12],MARKET_PRICE__2[Column3],"Not found") -> 335.55 | H63: 10000 | K63: =H63/10 -> 1000 | N63: {=_xlfn.IFS(H63<500,"0-500",H63<1000,"500-1000",H63<1500,"1000-1500",H63<2000,"1500-2000",H63<2500,"2000-2500",H63<3000,"2500-3000",H63<3500,"3000-3500",H63<4000,"3500-4000",H63<4500,"4000-4500",H63<=5000,"4500-5000",TRUE,"Hbove 5000")} -> Hbove 5000 | O63: 3.32 | P63: 0.81 | Q63: 3.44 | R63: 2.42 | S63: {=_xlfn.IFS( R63<0,"< 0", R63<5,"0 to 5", R63<10,"5 to 10", R63<15,"10 to 15", R63<20,"15 to 20", R63<25,"20 to 25", R63<50,"25 to 50", R63<75,"50 to 75", R63<100,"75 to 100", R63<125,"100 to 125", R63<150,"125 to 150", R63<175,"150 to 175", R63<200,"175 to 200", TRUE,"> 200" )} -> 0 to 5 | T63: 108 | U63: 111.6 | V63: 3.33 | W63: {=_xlfn.IFS( V63<-15,"< -15%", V63<-10,"-15% to -10%", V63<-5,"-10% to -5%", V63<0,"-5% to 0%", V63<10,"0% to 10%", V63<20,"10% to 20%", V63<30,"20% to 30%", V63<40,"30% to 40%", V63<50,"40% to 50%", V63<60,"50% to 60%", V63<70,"60% to 70%", V63<80,"70% to 80%", V63<90,"80% to 90%", V63<100,"90% to 100%", TRUE,"> 100%" )} -> 0% to 10% | X63: 103.4 | Y63: 103.31 | Z63: =IF(V63>0, ">0", IF(V63<0, "<0", "=0")) -> >0 | AA63: {=_xlfn.IFS( AND(O63>=0,O63<5),"0-5", AND(O63>=5,O63<15),"5-15", AND(O63>=15,O63<30),"15-30", AND(O63>=30,O63<60),"30-60", AND(O63>=60,O63<90),"60-90", AND(O63>=90,O63<120),"90-120", AND(O63>=120,O63<160),"120-160", AND(O63>=160,O63<200),"160-200", AND(O63>=200,O63<250),"200-250", AND(O63>=250,O63<300),"250-300", O63>=300,">300", TRUE,"Below 0" )} -> 0-5 | AB63: -4.26
A64: 45618 | B64: =TEXT(A64,"yyyy") -> 2024 | C64: Zinka Logistics So | D64: =IFERROR(LEFT(C64,FIND(" ",C64)-1),C64) -> Zinka | E64: =TRIM(SUBSTITUTE(SUBSTITUTE(C64,"Ltd",""),"Lt","")) -> Zinka Logistics So | F64: =_xlfn.XLOOKUP(E64,MARKET_PRICE__2[Column2],MARKET_PRICE__2[Column3],"Not found") -> Not found | G64: =_xlfn.XLOOKUP(D64,MARKET_PRICE__2[Column12],MARKET_PRICE__2[Column3],"Not found") -> Not found | H64: 1114.72 | K64: =H64/10 -> 111.472 | L64: {=_xlfn.IFS( AND(H64>=1000,H64<1050),"1000-1050", AND(H64>=1050,H64<1100),"1050-1100", AND(H64>=1100,H64<1150),"1100-1150", AND(H64>=1150,H64<1200),"1150-1200", AND(H64>=1200,H64<1250),"1200-1250", AND(H64>=1250,H64<1300),"1250-1300", AND(H64>=1300,H64<1350),"1300-1350", AND(H64>=1350,H64<1400),"1350-1400", AND(H64>=1400,H64<1450),"1400-1450", AND(H64>=1450,H64<=1500),"1450-1500", H64<1000,"Below 1000", TRUE,"Above 1500" )} -> 1100-1150 | N64: {=_xlfn.IFS(H64<500,"0-500",H64<1000,"500-1000",H64<1500,"1000-1500",H64<2000,"1500-2000",H64<2500,"2000-2500",H64<3000,"2500-3000",H64<3500,"3000-3500",H64<4000,"3500-4000",H64<4500,"4000-4500",H64<=5000,"4500-5000",TRUE,"Hbove 5000")} -> 1000-1500 | O64: 2.76 | P64: 0.24 | Q64: 1.66 | R64: 1.86 | S64: {=_xlfn.IFS( R64<0,"< 0", R64<5,"0 to 5", R64<10,"5 to 10", R64<15,"10 to 15", R64<20,"15 to 20", R64<25,"20 to 25", R64<50,"25 to 50", R64<75,"50 to 75", R64<100,"75 to 100", R64<125,"100 to 125", R64<150,"125 to 150", R64<175,"150 to 175", R64<200,"175 to 200", TRUE,"> 200" )} -> 0 to 5 | T64: 273 | U64: 279.05 | V64: 2.22 | W64: {=_xlfn.IFS( V64<-15,"< -15%", V64<-10,"-15% to -10%", V64<-5,"-10% to -5%", V64<0,"-5% to 0%", V64<10,"0% to 10%", V64<20,"10% to 20%", V64<30,"20% to 30%", V64<40,"30% to 40%", V64<50,"40% to 50%", V64<60,"50% to 60%", V64<70,"60% to 70%", V64<80,"70% to 80%", V64<90,"80% to 90%", V64<100,"90% to 100%", TRUE,"> 100%" )} -> 0% to 10% | X64: 644 | Y64: 644.2 | Z64: =IF(V64>0, ">0", IF(V64<0, "<0", "=0")) -> >0 | AA64: {=_xlfn.IFS( AND(O64>=0,O64<5),"0-5", AND(O64>=5,O64<15),"5-15", AND(O64>=15,O64<30),"15-30", AND(O64>=30,O64<60),"30-60", AND(O64>=60,O64<90),"60-90", AND(O64>=90,O64<120),"90-120", AND(O64>=120,O64<160),"120-160", AND(O64>=160,O64<200),"160-200", AND(O64>=200,O64<250),"200-250", AND(O64>=250,O64<300),"250-300", O64>=300,">300", TRUE,"Below 0" )} -> 0-5 | AB64: 135.9
A65: 45610 | B65: =TEXT(A65,"yyyy") -> 2024 | C65: Niva Bupa Health I | D65: =IFERROR(LEFT(C65,FIND(" ",C65)-1),C65) -> Niva | E65: =TRIM(SUBSTITUTE(SUBSTITUTE(C65,"Ltd",""),"Lt","")) -> Niva Bupa Health I | F65: =_xlfn.XLOOKUP(E65,MARKET_PRICE__2[Column2],MARKET_PRICE__2[Column3],"Not found") -> Not found | G65: =_xlfn.XLOOKUP(D65,MARKET_PRICE__2[Column12],MARKET_PRICE__2[Column3],"Not found") -> 80.00 | H65: 2200 | K65: =H65/10 -> 220 | N65: {=_xlfn.IFS(H65<500,"0-500",H65<1000,"500-1000",H65<1500,"1000-1500",H65<2000,"1500-2000",H65<2500,"2000-2500",H65<3000,"2500-3000",H65<3500,"3000-3500",H65<4000,"3500-4000",H65<4500,"4000-4500",H65<=5000,"4500-5000",TRUE,"Hbove 5000")} -> 2000-2500 | O65: 2.06 | P65: 0.68 | Q65: 2.73 | R65: 1.8 | S65: {=_xlfn.IFS( R65<0,"< 0", R65<5,"0 to 5", R65<10,"5 to 10", R65<15,"10 to 15", R65<20,"15 to 20", R65<25,"20 to 25", R65<50,"25 to 50", R65<75,"50 to 75", R65<100,"75 to 100", R65<125,"100 to 125", R65<150,"125 to 150", R65<175,"150 to 175", R65<200,"175 to 200", TRUE,"> 200" )} -> 0 to 5 | T65: 74 | U65: 78.5 | V65: 6.08 | W65: {=_xlfn.IFS( V65<-15,"< -15%", V65<-10,"-15% to -10%", V65<-5,"-10% to -5%", V65<0,"-5% to 0%", V65<10,"0% to 10%", V65<20,"10% to 20%", V65<30,"20% to 30%", V65<40,"30% to 40%", V65<50,"40% to 50%", V65<60,"50% to 60%", V65<70,"60% to 70%", V65<80,"70% to 80%", V65<90,"80% to 90%", V65<100,"90% to 100%", TRUE,"> 100%" )} -> 0% to 10% | X65: 85.54 | Y65: 85.47 | Z65: =IF(V65>0, ">0", IF(V65<0, "<0", "=0")) -> >0 | AA65: {=_xlfn.IFS( AND(O65>=0,O65<5),"0-5", AND(O65>=5,O65<15),"5-15", AND(O65>=15,O65<30),"15-30", AND(O65>=30,O65<60),"30-60", AND(O65>=60,O65<90),"60-90", AND(O65>=90,O65<120),"90-120", AND(O65>=120,O65<160),"120-160", AND(O65>=160,O65<200),"160-200", AND(O65>=200,O65<250),"200-250", AND(O65>=250,O65<300),"250-300", O65>=300,">300", TRUE,"Below 0" )} -> 0-5 | AB65: 15.59
A66: 45609 | B66: =TEXT(A66,"yyyy") -> 2024 | C66: Swiggy Ltd | D66: =IFERROR(LEFT(C66,FIND(" ",C66)-1),C66) -> Swiggy | E66: =TRIM(SUBSTITUTE(SUBSTITUTE(C66,"Ltd",""),"Lt","")) -> Swiggy | F66: =_xlfn.XLOOKUP(E66,MARKET_PRICE__2[Column2],MARKET_PRICE__2[Column3],"Not found") -> 437.00 | G66: =_xlfn.XLOOKUP(D66,MARKET_PRICE__2[Column12],MARKET_PRICE__2[Column3],"Not found") -> 437.00 | H66: 11327.4 | K66: =H66/10 -> 1132.74 | N66: {=_xlfn.IFS(H66<500,"0-500",H66<1000,"500-1000",H66<1500,"1000-1500",H66<2000,"1500-2000",H66<2500,"2000-2500",H66<3000,"2500-3000",H66<3500,"3000-3500",H66<4000,"3500-4000",H66<4500,"4000-4500",H66<=5000,"4500-5000",TRUE,"Hbove 5000")} -> Hbove 5000 | O66: 6.02 | P66: 0.41 | Q66: 1.14 | R66: 3.59 | S66: {=_xlfn.IFS( R66<0,"< 0", R66<5,"0 to 5", R66<10,"5 to 10", R66<15,"10 to 15", R66<20,"15 to 20", R66<25,"20 to 25", R66<50,"25 to 50", R66<75,"50 to 75", R66<100,"75 to 100", R66<125,"100 to 125", R66<150,"125 to 150", R66<175,"150 to 175", R66<200,"175 to 200", TRUE,"> 200" )} -> 0 to 5 | T66: 390 | U66: 412 | V66: 5.64 | W66: {=_xlfn.IFS( V66<-15,"< -15%", V66<-10,"-15% to -10%", V66<-5,"-10% to -5%", V66<0,"-5% to 0%", V66<10,"0% to 10%", V66<20,"10% to 20%", V66<30,"20% to 30%", V66<40,"30% to 40%", V66<50,"40% to 50%", V66<60,"50% to 60%", V66<70,"60% to 70%", V66<80,"70% to 80%", V66<90,"80% to 90%", V66<100,"90% to 100%", TRUE,"> 100%" )} -> 0% to 10% | X66: 428.3 | Y66: 427.9 | Z66: =IF(V66>0, ">0", IF(V66<0, "<0", "=0")) -> >0 | AA66: {=_xlfn.IFS( AND(O66>=0,O66<5),"0-5", AND(O66>=5,O66<15),"5-15", AND(O66>=15,O66<30),"15-30", AND(O66>=30,O66<60),"30-60", AND(O66>=60,O66<90),"60-90", AND(O66>=90,O66<120),"90-120", AND(O66>=120,O66<160),"120-160", AND(O66>=160,O66<200),"160-200", AND(O66>=200,O66<250),"200-250", AND(O66>=250,O66<300),"250-300", O66>=300,">300", TRUE,"Below 0" )} -> 5-15 | AB66: 9.82
A67: 45609 | B67: =TEXT(A67,"yyyy") -> 2024 | C67: ACME Solar Holding | D67: =IFERROR(LEFT(C67,FIND(" ",C67)-1),C67) -> ACME | E67: =TRIM(SUBSTITUTE(SUBSTITUTE(C67,"Ltd",""),"Lt","")) -> ACME Solar Holding | F67: =_xlfn.XLOOKUP(E67,MARKET_PRICE__2[Column2],MARKET_PRICE__2[Column3],"Not found") -> Not found | G67: =_xlfn.XLOOKUP(D67,MARKET_PRICE__2[Column12],MARKET_PRICE__2[Column3],"Not found") -> 281.00 | H67: 2900 | K67: =H67/10 -> 290 | N67: {=_xlfn.IFS(H67<500,"0-500",H67<1000,"500-1000",H67<1500,"1000-1500",H67<2000,"1500-2000",H67<2500,"2000-2500",H67<3000,"2500-3000",H67<3500,"3000-3500",H67<4000,"3500-4000",H67<4500,"4000-4500",H67<=5000,"4500-5000",TRUE,"Hbove 5000")} -> 2500-3000 | O67: 3.54 | P67: 0.97 | Q67: 3.1 | R67: 2.75 | S67: {=_xlfn.IFS( R67<0,"< 0", R67<5,"0 to 5", R67<10,"5 to 10", R67<15,"10 to 15", R67<20,"15 to 20", R67<25,"20 to 25", R67<50,"25 to 50", R67<75,"50 to 75", R67<100,"75 to 100", R67<125,"100 to 125", R67<150,"125 to 150", R67<175,"150 to 175", R67<200,"175 to 200", TRUE,"> 200" )} -> 0 to 5 | T67: 289 | U67: 259 | V67: -10.38 | W67: {=_xlfn.IFS( V67<-15,"< -15%", V67<-10,"-15% to -10%", V67<-5,"-10% to -5%", V67<0,"-5% to 0%", V67<10,"0% to 10%", V67<20,"10% to 20%", V67<30,"20% to 30%", V67<40,"30% to 40%", V67<50,"40% to 50%", V67<60,"50% to 60%", V67<70,"60% to 70%", V67<80,"70% to 80%", V67<90,"80% to 90%", V67<100,"90% to 100%", TRUE,"> 100%" )} -> -15% to -10% | X67: 290.6 | Y67: 290.8 | Z67: =IF(V67>0, ">0", IF(V67<0, "<0", "=0")) -> <0 | AA67: {=_xlfn.IFS( AND(O67>=0,O67<5),"0-5", AND(O67>=5,O67<15),"5-15", AND(O67>=15,O67<30),"15-30", AND(O67>=30,O67<60),"30-60", AND(O67>=60,O67<90),"60-90", AND(O67>=90,O67<120),"90-120", AND(O67>=120,O67<160),"120-160", AND(O67>=160,O67<200),"160-200", AND(O67>=200,O67<250),"200-250", AND(O67>=250,O67<300),"250-300", O67>=300,">300", TRUE,"Below 0" )} -> 0-5 | AB67: 0.55
A68: 45608 | B68: =TEXT(A68,"yyyy") -> 2024 | C68: Sagility India Ltd | D68: =IFERROR(LEFT(C68,FIND(" ",C68)-1),C68) -> Sagility | E68: =TRIM(SUBSTITUTE(SUBSTITUTE(C68,"Ltd",""),"Lt","")) -> Sagility India | F68: =_xlfn.XLOOKUP(E68,MARKET_PRICE__2[Column2],MARKET_PRICE__2[Column3],"Not found") -> Not found | G68: =_xlfn.XLOOKUP(D68,MARKET_PRICE__2[Column12],MARKET_PRICE__2[Column3],"Not found") -> 44.30 | H68: 2106.4 | K68: =H68/10 -> 210.64 | N68: {=_xlfn.IFS(H68<500,"0-500",H68<1000,"500-1000",H68<1500,"1000-1500",H68<2000,"1500-2000",H68<2500,"2000-2500",H68<3000,"2500-3000",H68<3500,"3000-3500",H68<4000,"3500-4000",H68<4500,"4000-4500",H68<=5000,"4500-5000",TRUE,"Hbove 5000")} -> 2000-2500 | O68: 3.52 | P68: 1.93 | Q68: 4.16 | R68: 3.2 | S68: {=_xlfn.IFS( R68<0,"< 0", R68<5,"0 to 5", R68<10,"5 to 10", R68<15,"10 to 15", R68<20,"15 to 20", R68<25,"20 to 25", R68<50,"25 to 50", R68<75,"50 to 75", R68<100,"75 to 100", R68<125,"100 to 125", R68<150,"125 to 150", R68<175,"150 to 175", R68<200,"175 to 200", TRUE,"> 200" )} -> 0 to 5 | T68: 30 | U68: 31.06 | V68: 3.53 | W68: {=_xlfn.IFS( V68<-15,"< -15%", V68<-10,"-15% to -10%", V68<-5,"-10% to -5%", V68<0,"-5% to 0%", V68<10,"0% to 10%", V68<20,"10% to 20%", V68<30,"20% to 30%", V68<40,"30% to 40%", V68<50,"40% to 50%", V68<60,"50% to 60%", V68<70,"60% to 70%", V68<80,"70% to 80%", V68<90,"80% to 90%", V68<100,"90% to 100%", TRUE,"> 100%" )} -> 0% to 10% | X68: 46.07 | Y68: 46.06 | Z68: =IF(V68>0, ">0", IF(V68<0, "<0", "=0")) -> >0 | AA68: {=_xlfn.IFS( AND(O68>=0,O68<5),"0-5", AND(O68>=5,O68<15),"5-15", AND(O68>=15,O68<30),"15-30", AND(O68>=30,O68<60),"30-60", AND(O68>=60,O68<90),"60-90", AND(O68>=90,O68<120),"90-120", AND(O68>=120,O68<160),"120-160", AND(O68>=160,O68<200),"160-200", AND(O68>=200,O68<250),"200-250", AND(O68>=250,O68<300),"250-300", O68>=300,">300", TRUE,"Below 0" )} -> 0-5 | AB68: 53.57
A69: 45600 | B69: =TEXT(A69,"yyyy") -> 2024 | C69: Afcons Infrastruct | D69: =IFERROR(LEFT(C69,FIND(" ",C69)-1),C69) -> Afcons | E69: =TRIM(SUBSTITUTE(SUBSTITUTE(C69,"Ltd",""),"Lt","")) -> Afcons Infrastruct | F69: =_xlfn.XLOOKUP(E69,MARKET_PRICE__2[Column2],MARKET_PRICE__2[Column3],"Not found") -> Not found | G69: =_xlfn.XLOOKUP(D69,MARKET_PRICE__2[Column12],MARKET_PRICE__2[Column3],"Not found") -> 465.90 | H69: 5430 | K69: =H69/10 -> 543 | N69: {=_xlfn.IFS(H69<500,"0-500",H69<1000,"500-1000",H69<1500,"1000-1500",H69<2000,"1500-2000",H69<2500,"2000-2500",H69<3000,"2500-3000",H69<3500,"3000-3500",H69<4000,"3500-4000",H69<4500,"4000-4500",H69<=5000,"4500-5000",TRUE,"Hbove 5000")} -> Hbove 5000 | O69: 3.79 | P69: 5.05 | Q69: 0.94 | R69: 2.63 | S69: {=_xlfn.IFS( R69<0,"< 0", R69<5,"0 to 5", R69<10,"5 to 10", R69<15,"10 to 15", R69<20,"15 to 20", R69<25,"20 to 25", R69<50,"25 to 50", R69<75,"50 to 75", R69<100,"75 to 100", R69<125,"100 to 125", R69<150,"125 to 150", R69<175,"150 to 175", R69<200,"175 to 200", TRUE,"> 200" )} -> 0 to 5 | T69: 463 | U69: 430.05 | V69: -7.12 | W69: {=_xlfn.IFS( V69<-15,"< -15%", V69<-10,"-15% to -10%", V69<-5,"-10% to -5%", V69<0,"-5% to 0%", V69<10,"0% to 10%", V69<20,"10% to 20%", V69<30,"20% to 30%", V69<40,"30% to 40%", V69<50,"40% to 50%", V69<60,"50% to 60%", V69<70,"60% to 70%", V69<80,"70% to 80%", V69<90,"80% to 90%", V69<100,"90% to 100%", TRUE,"> 100%" )} -> -10% to -5% | X69: 430.95 | Y69: 430.95 | Z69: =IF(V69>0, ">0", IF(V69<0, "<0", "=0")) -> <0 | AA69: {=_xlfn.IFS( AND(O69>=0,O69<5),"0-5", AND(O69>=5,O69<15),"5-15", AND(O69>=15,O69<30),"15-30", AND(O69>=30,O69<60),"30-60", AND(O69>=60,O69<90),"60-90", AND(O69>=90,O69<120),"90-120", AND(O69>=120,O69<160),"120-160", AND(O69>=160,O69<200),"160-200", AND(O69>=200,O69<250),"200-250", AND(O69>=250,O69<300),"250-300", O69>=300,">300", TRUE,"Below 0" )} -> 0-5 | AB69: -6.92
A70: 45595 | B70: =TEXT(A70,"yyyy") -> 2024 | C70: Godavari Biorefine | D70: =IFERROR(LEFT(C70,FIND(" ",C70)-1),C70) -> Godavari | E70: =TRIM(SUBSTITUTE(SUBSTITUTE(C70,"Ltd",""),"Lt","")) -> Godavari Biorefine | F70: =_xlfn.XLOOKUP(E70,MARKET_PRICE__2[Column2],MARKET_PRICE__2[Column3],"Not found") -> Not found | G70: =_xlfn.XLOOKUP(D70,MARKET_PRICE__2[Column12],MARKET_PRICE__2[Column3],"Not found") -> 81.60 | H70: 554.75 | J70: {=_xlfn.IFS( AND(H70>=500,H70<550),"500-550", AND(H70>=550,H70<600),"550-600", AND(H70>=600,H70<650),"600-650", AND(H70>=650,H70<700),"650-700", AND(H70>=700,H70<750),"700-750", AND(H70>=750,H70<800),"750-800", AND(H70>=800,H70<850),"800-850", AND(H70>=850,H70<900),"850-900", AND(H70>=900,H70<950),"900-950", AND(H70>=950,H70<=1000),"950-1000", H70<500,"Below 500", TRUE,"Above 1000" )} -> 550-600 | K70: =H70/10 -> 55.475 | N70: {=_xlfn.IFS(H70<500,"0-500",H70<1000,"500-1000",H70<1500,"1000-1500",H70<2000,"1500-2000",H70<2500,"2000-2500",H70<3000,"2500-3000",H70<3500,"3000-3500",H70<4000,"3500-4000",H70<4500,"4000-4500",H70<=5000,"4500-5000",TRUE,"Hbove 5000")} -> 500-1000 | O70: 2.76 | P70: 0.9 | Q70: 1.71 | R70: 1.83 | S70: {=_xlfn.IFS( R70<0,"< 0", R70<5,"0 to 5", R70<10,"5 to 10", R70<15,"10 to 15", R70<20,"15 to 20", R70<25,"20 to 25", R70<50,"25 to 50", R70<75,"50 to 75", R70<100,"75 to 100", R70<125,"100 to 125", R70<150,"125 to 150", R70<175,"150 to 175", R70<200,"175 to 200", TRUE,"> 200" )} -> 0 to 5 | T70: 352 | U70: 310.55 | V70: -11.78 | W70: {=_xlfn.IFS( V70<-15,"< -15%", V70<-10,"-15% to -10%", V70<-5,"-10% to -5%", V70<0,"-5% to 0%", V70<10,"0% to 10%", V70<20,"10% to 20%", V70<30,"20% to 30%", V70<40,"30% to 40%", V70<50,"40% to 50%", V70<60,"50% to 60%", V70<70,"60% to 70%", V70<80,"70% to 80%", V70<90,"80% to 90%", V70<100,"90% to 100%", TRUE,"> 100%" )} -> -15% to -10% | X70: 261.45 | Y70: 261.9 | Z70: =IF(V70>0, ">0", IF(V70<0, "<0", "=0")) -> <0 | AA70: {=_xlfn.IFS( AND(O70>=0,O70<5),"0-5", AND(O70>=5,O70<15),"5-15", AND(O70>=15,O70<30),"15-30", AND(O70>=30,O70<60),"30-60", AND(O70>=60,O70<90),"60-90", AND(O70>=90,O70<120),"90-120", AND(O70>=120,O70<160),"120-160", AND(O70>=160,O70<200),"160-200", AND(O70>=200,O70<250),"200-250", AND(O70>=250,O70<300),"250-300", O70>=300,">300", TRUE,"Below 0" )} -> 0-5 | AB70: -25.72
A71: 45593 | B71: =TEXT(A71,"yyyy") -> 2024 | C71: Deepak Builders & | D71: =IFERROR(LEFT(C71,FIND(" ",C71)-1),C71) -> Deepak | E71: =TRIM(SUBSTITUTE(SUBSTITUTE(C71,"Ltd",""),"Lt","")) -> Deepak Builders & | F71: =_xlfn.XLOOKUP(E71,MARKET_PRICE__2[Column2],MARKET_PRICE__2[Column3],"Not found") -> Not found | G71: =_xlfn.XLOOKUP(D71,MARKET_PRICE__2[Column12],MARKET_PRICE__2[Column3],"Not found") -> 129.50 | H71: 260.04 | I71: {=_xlfn.IFS( H71<50,"0-50", H71<100,"50-100", H71<150,"100-150", H71<200,"150-200", H71<250,"200-250", H71<300,"250-300", H71<350,"300-350", H71<400,"350-400", H71<450,"400-450", H71<=500,"450-500", TRUE,"Above 500" )} -> 250-300 | K71: =H71/10 -> 26.004 | N71: {=_xlfn.IFS(H71<500,"0-500",H71<1000,"500-1000",H71<1500,"1000-1500",H71<2000,"1500-2000",H71<2500,"2000-2500",H71<3000,"2500-3000",H71<3500,"3000-3500",H71<4000,"3500-4000",H71<4500,"4000-4500",H71<=5000,"4500-5000",TRUE,"Hbove 5000")} -> 0-500 | O71: 13.91 | P71: 82.47 | Q71: 39.79 | R71: 41.54 | S71: {=_xlfn.IFS( R71<0,"< 0", R71<5,"0 to 5", R71<10,"5 to 10", R71<15,"10 to 15", R71<20,"15 to 20", R71<25,"20 to 25", R71<50,"25 to 50", R71<75,"50 to 75", R71<100,"75 to 100", R71<125,"100 to 125", R71<150,"125 to 150", R71<175,"150 to 175", R71<200,"175 to 200", TRUE,"> 200" )} -> 25 to 50 | T71: 203 | U71: 198.5 | V71: -2.22 | W71: {=_xlfn.IFS( V71<-15,"< -15%", V71<-10,"-15% to -10%", V71<-5,"-10% to -5%", V71<0,"-5% to 0%", V71<10,"0% to 10%", V71<20,"10% to 20%", V71<30,"20% to 30%", V71<40,"30% to 40%", V71<50,"40% to 50%", V71<60,"50% to 60%", V71<70,"60% to 70%", V71<80,"70% to 80%", V71<90,"80% to 90%", V71<100,"90% to 100%", TRUE,"> 100%" )} -> -5% to 0% | X71: 132.25 | Y71: 131.93 | Z71: =IF(V71>0, ">0", IF(V71<0, "<0", "=0")) -> <0 | AA71: {=_xlfn.IFS( AND(O71>=0,O71<5),"0-5", AND(O71>=5,O71<15),"5-15", AND(O71>=15,O71<30),"15-30", AND(O71>=30,O71<60),"30-60", AND(O71>=60,O71<90),"60-90", AND(O71>=90,O71<120),"90-120", AND(O71>=120,O71<160),"120-160", AND(O71>=160,O71<200),"160-200", AND(O71>=200,O71<250),"200-250", AND(O71>=250,O71<300),"250-300", O71>=300,">300", TRUE,"Below 0" )} -> 5-15 | AB71: -34.85
A72: 45593 | B72: =TEXT(A72,"yyyy") -> 2024 | C72: Waaree Energies Lt | D72: =IFERROR(LEFT(C72,FIND(" ",C72)-1),C72) -> Waaree | E72: =TRIM(SUBSTITUTE(SUBSTITUTE(C72,"Ltd",""),"Lt","")) -> Waaree Energies | F72: =_xlfn.XLOOKUP(E72,MARKET_PRICE__2[Column2],MARKET_PRICE__2[Column3],"Not found") -> 3348.15 | G72: =_xlfn.XLOOKUP(D72,MARKET_PRICE__2[Column12],MARKET_PRICE__2[Column3],"Not found") -> 1110.00 | H72: 4321.44 | K72: =H72/10 -> 432.144 | N72: {=_xlfn.IFS(H72<500,"0-500",H72<1000,"500-1000",H72<1500,"1000-1500",H72<2000,"1500-2000",H72<2500,"2000-2500",H72<3000,"2500-3000",H72<3500,"3000-3500",H72<4000,"3500-4000",H72<4500,"4000-4500",H72<=5000,"4500-5000",TRUE,"Hbove 5000")} -> 4000-4500 | O72: 208.63 | P72: 62.49 | Q72: 10.79 | R72: 76.34 | S72: {=_xlfn.IFS( R72<0,"< 0", R72<5,"0 to 5", R72<10,"5 to 10", R72<15,"10 to 15", R72<20,"15 to 20", R72<25,"20 to 25", R72<50,"25 to 50", R72<75,"50 to 75", R72<100,"75 to 100", R72<125,"100 to 125", R72<150,"125 to 150", R72<175,"150 to 175", R72<200,"175 to 200", TRUE,"> 200" )} -> 75 to 100 | T72: 1503 | U72: 2550 | V72: 69.66 | W72: {=_xlfn.IFS( V72<-15,"< -15%", V72<-10,"-15% to -10%", V72<-5,"-10% to -5%", V72<0,"-5% to 0%", V72<10,"0% to 10%", V72<20,"10% to 20%", V72<30,"20% to 30%", V72<40,"30% to 40%", V72<50,"40% to 50%", V72<60,"50% to 60%", V72<70,"60% to 70%", V72<80,"70% to 80%", V72<90,"80% to 90%", V72<100,"90% to 100%", TRUE,"> 100%" )} -> 60% to 70% | X72: 3188.15 | Y72: 3188.6 | Z72: =IF(V72>0, ">0", IF(V72<0, "<0", "=0")) -> >0 | AA72: {=_xlfn.IFS( AND(O72>=0,O72<5),"0-5", AND(O72>=5,O72<15),"5-15", AND(O72>=15,O72<30),"15-30", AND(O72>=30,O72<60),"30-60", AND(O72>=60,O72<90),"60-90", AND(O72>=90,O72<120),"90-120", AND(O72>=120,O72<160),"120-160", AND(O72>=160,O72<200),"160-200", AND(O72>=200,O72<250),"200-250", AND(O72>=250,O72<300),"250-300", O72>=300,">300", TRUE,"Below 0" )} -> 200-250 | AB72: 112.12
A73: 45587 | B73: =TEXT(A73,"yyyy") -> 2024 | C73: Hyundai Motor Indi | D73: =IFERROR(LEFT(C73,FIND(" ",C73)-1),C73) -> Hyundai | E73: =TRIM(SUBSTITUTE(SUBSTITUTE(C73,"Ltd",""),"Lt","")) -> Hyundai Motor Indi | F73: =_xlfn.XLOOKUP(E73,MARKET_PRICE__2[Column2],MARKET_PRICE__2[Column3],"Not found") -> Not found | G73: =_xlfn.XLOOKUP(D73,MARKET_PRICE__2[Column12],MARKET_PRICE__2[Column3],"Not found") -> 2405.60 | H73: 27858.8 | K73: =H73/10 -> 2785.88 | N73: {=_xlfn.IFS(H73<500,"0-500",H73<1000,"500-1000",H73<1500,"1000-1500",H73<2000,"1500-2000",H73<2500,"2000-2500",H73<3000,"2500-3000",H73<3500,"3000-3500",H73<4000,"3500-4000",H73<4500,"4000-4500",H73<=5000,"4500-5000",TRUE,"Hbove 5000")} -> Hbove 5000 | O73: 6.97 | P73: 0.6 | Q73: 0.5 | R73: 2.37 | S73: {=_xlfn.IFS( R73<0,"< 0", R73<5,"0 to 5", R73<10,"5 to 10", R73<15,"10 to 15", R73<20,"15 to 20", R73<25,"20 to 25", R73<50,"25 to 50", R73<75,"50 to 75", R73<100,"75 to 100", R73<125,"100 to 125", R73<150,"125 to 150", R73<175,"150 to 175", R73<200,"175 to 200", TRUE,"> 200" )} -> 0 to 5 | T73: 1960 | U73: 1931 | V73: -1.48 | W73: {=_xlfn.IFS( V73<-15,"< -15%", V73<-10,"-15% to -10%", V73<-5,"-10% to -5%", V73<0,"-5% to 0%", V73<10,"0% to 10%", V73<20,"10% to 20%", V73<30,"20% to 30%", V73<40,"30% to 40%", V73<50,"40% to 50%", V73<60,"50% to 60%", V73<70,"60% to 70%", V73<80,"70% to 80%", V73<90,"80% to 90%", V73<100,"90% to 100%", TRUE,"> 100%" )} -> -5% to 0% | X73: 2367.25 | Y73: 2366.6 | Z73: =IF(V73>0, ">0", IF(V73<0, "<0", "=0")) -> <0 | AA73: {=_xlfn.IFS( AND(O73>=0,O73<5),"0-5", AND(O73>=5,O73<15),"5-15", AND(O73>=15,O73<30),"15-30", AND(O73>=30,O73<60),"30-60", AND(O73>=60,O73<90),"60-90", AND(O73>=90,O73<120),"90-120", AND(O73>=120,O73<160),"120-160", AND(O73>=160,O73<200),"160-200", AND(O73>=200,O73<250),"200-250", AND(O73>=250,O73<300),"250-300", O73>=300,">300", TRUE,"Below 0" )} -> 5-15 | AB73: 20.78
A74: 45580 | B74: =TEXT(A74,"yyyy") -> 2024 | C74: Garuda Constructio | D74: =IFERROR(LEFT(C74,FIND(" ",C74)-1),C74) -> Garuda | E74: =TRIM(SUBSTITUTE(SUBSTITUTE(C74,"Ltd",""),"Lt","")) -> Garuda Constructio | F74: =_xlfn.XLOOKUP(E74,MARKET_PRICE__2[Column2],MARKET_PRICE__2[Column3],"Not found") -> Not found | G74: =_xlfn.XLOOKUP(D74,MARKET_PRICE__2[Column12],MARKET_PRICE__2[Column3],"Not found") -> 196.90 | H74: 264.1 | I74: {=_xlfn.IFS( H74<50,"0-50", H74<100,"50-100", H74<150,"100-150", H74<200,"150-200", H74<250,"200-250", H74<300,"250-300", H74<350,"300-350", H74<400,"350-400", H74<450,"400-450", H74<=500,"450-500", TRUE,"Above 500" )} -> 250-300 | K74: =H74/10 -> 26.41 | N74: {=_xlfn.IFS(H74<500,"0-500",H74<1000,"500-1000",H74<1500,"1000-1500",H74<2000,"1500-2000",H74<2500,"2000-2500",H74<3000,"2500-3000",H74<3500,"3000-3500",H74<4000,"3500-4000",H74<4500,"4000-4500",H74<=5000,"4500-5000",TRUE,"Hbove 5000")} -> 0-500 | O74: 1.24 | P74: 9.03 | Q74: 10.81 | R74: 7.55 | S74: {=_xlfn.IFS( R74<0,"< 0", R74<5,"0 to 5", R74<10,"5 to 10", R74<15,"10 to 15", R74<20,"15 to 20", R74<25,"20 to 25", R74<50,"25 to 50", R74<75,"50 to 75", R74<100,"75 to 100", R74<125,"100 to 125", R74<150,"125 to 150", R74<175,"150 to 175", R74<200,"175 to 200", TRUE,"> 200" )} -> 5 to 10 | T74: 95 | U74: 103.2 | V74: 8.63 | W74: {=_xlfn.IFS( V74<-15,"< -15%", V74<-10,"-15% to -10%", V74<-5,"-10% to -5%", V74<0,"-5% to 0%", V74<10,"0% to 10%", V74<20,"10% to 20%", V74<30,"20% to 30%", V74<40,"30% to 40%", V74<50,"40% to 50%", V74<60,"50% to 60%", V74<70,"60% to 70%", V74<80,"70% to 80%", V74<90,"80% to 90%", V74<100,"90% to 100%", TRUE,"> 100%" )} -> 0% to 10% | X74: 191.7 | Y74: 192.25 | Z74: =IF(V74>0, ">0", IF(V74<0, "<0", "=0")) -> >0 | AA74: {=_xlfn.IFS( AND(O74>=0,O74<5),"0-5", AND(O74>=5,O74<15),"5-15", AND(O74>=15,O74<30),"15-30", AND(O74>=30,O74<60),"30-60", AND(O74>=60,O74<90),"60-90", AND(O74>=90,O74<120),"90-120", AND(O74>=120,O74<160),"120-160", AND(O74>=160,O74<200),"160-200", AND(O74>=200,O74<250),"200-250", AND(O74>=250,O74<300),"250-300", O74>=300,">300", TRUE,"Below 0" )} -> 0-5 | AB74: 101.79
A75: 45569 | B75: =TEXT(A75,"yyyy") -> 2024 | C75: Diffusion Engineer | D75: =IFERROR(LEFT(C75,FIND(" ",C75)-1),C75) -> Diffusion | E75: =TRIM(SUBSTITUTE(SUBSTITUTE(C75,"Ltd",""),"Lt","")) -> Diffusion Engineer | F75: =_xlfn.XLOOKUP(E75,MARKET_PRICE__2[Column2],MARKET_PRICE__2[Column3],"Not found") -> Not found | G75: =_xlfn.XLOOKUP(D75,MARKET_PRICE__2[Column12],MARKET_PRICE__2[Column3],"Not found") -> 368.30 | H75: 157.96 | I75: {=_xlfn.IFS( H75<50,"0-50", H75<100,"50-100", H75<150,"100-150", H75<200,"150-200", H75<250,"200-250", H75<300,"250-300", H75<350,"300-350", H75<400,"350-400", H75<450,"400-450", H75<=500,"450-500", TRUE,"Above 500" )} -> 150-200 | K75: =H75/10 -> 15.796 | N75: {=_xlfn.IFS(H75<500,"0-500",H75<1000,"500-1000",H75<1500,"1000-1500",H75<2000,"1500-2000",H75<2500,"2000-2500",H75<3000,"2500-3000",H75<3500,"3000-3500",H75<4000,"3500-4000",H75<4500,"4000-4500",H75<=5000,"4500-5000",TRUE,"Hbove 5000")} -> 0-500 | O75: 95.74 | P75: 207.6 | Q75: 85.61 | R75: 114.49 | S75: {=_xlfn.IFS( R75<0,"< 0", R75<5,"0 to 5", R75<10,"5 to 10", R75<15,"10 to 15", R75<20,"15 to 20", R75<25,"20 to 25", R75<50,"25 to 50", R75<75,"50 to 75", R75<100,"75 to 100", R75<125,"100 to 125", R75<150,"125 to 150", R75<175,"150 to 175", R75<200,"175 to 200", TRUE,"> 200" )} -> 100 to 125 | T75: 168 | U75: 188 | V75: 11.9 | W75: {=_xlfn.IFS( V75<-15,"< -15%", V75<-10,"-15% to -10%", V75<-5,"-10% to -5%", V75<0,"-5% to 0%", V75<10,"0% to 10%", V75<20,"10% to 20%", V75<30,"20% to 30%", V75<40,"30% to 40%", V75<50,"40% to 50%", V75<60,"50% to 60%", V75<70,"60% to 70%", V75<80,"70% to 80%", V75<90,"80% to 90%", V75<100,"90% to 100%", TRUE,"> 100%" )} -> 10% to 20% | X75: 344.65 | Y75: 344.5 | Z75: =IF(V75>0, ">0", IF(V75<0, "<0", "=0")) -> >0 | AA75: {=_xlfn.IFS( AND(O75>=0,O75<5),"0-5", AND(O75>=5,O75<15),"5-15", AND(O75>=15,O75<30),"15-30", AND(O75>=30,O75<60),"30-60", AND(O75>=60,O75<90),"60-90", AND(O75>=90,O75<120),"90-120", AND(O75>=120,O75<160),"120-160", AND(O75>=160,O75<200),"160-200", AND(O75>=200,O75<250),"200-250", AND(O75>=250,O75<300),"250-300", O75>=300,">300", TRUE,"Below 0" )} -> 90-120 | AB75: 105.15
A76: 45568 | B76: =TEXT(A76,"yyyy") -> 2024 | C76: KRN Heat Exchanger | D76: =IFERROR(LEFT(C76,FIND(" ",C76)-1),C76) -> KRN | E76: =TRIM(SUBSTITUTE(SUBSTITUTE(C76,"Ltd",""),"Lt","")) -> KRN Heat Exchanger | F76: =_xlfn.XLOOKUP(E76,MARKET_PRICE__2[Column2],MARKET_PRICE__2[Column3],"Not found") -> Not found | G76: =_xlfn.XLOOKUP(D76,MARKET_PRICE__2[Column12],MARKET_PRICE__2[Column3],"Not found") -> 829.00 | H76: 341.95 | I76: {=_xlfn.IFS( H76<50,"0-50", H76<100,"50-100", H76<150,"100-150", H76<200,"150-200", H76<250,"200-250", H76<300,"250-300", H76<350,"300-350", H76<400,"350-400", H76<450,"400-450", H76<=500,"450-500", TRUE,"Above 500" )} -> 300-350 | K76: =H76/10 -> 34.195 | N76: {=_xlfn.IFS(H76<500,"0-500",H76<1000,"500-1000",H76<1500,"1000-1500",H76<2000,"1500-2000",H76<2500,"2000-2500",H76<3000,"2500-3000",H76<3500,"3000-3500",H76<4000,"3500-4000",H76<4500,"4000-4500",H76<=5000,"4500-5000",TRUE,"Hbove 5000")} -> 0-500 | O76: 253.04 | P76: 431.63 | Q76: 98.29 | R76: 214.42 | S76: {=_xlfn.IFS( R76<0,"< 0", R76<5,"0 to 5", R76<10,"5 to 10", R76<15,"10 to 15", R76<20,"15 to 20", R76<25,"20 to 25", R76<50,"25 to 50", R76<75,"50 to 75", R76<100,"75 to 100", R76<125,"100 to 125", R76<150,"125 to 150", R76<175,"150 to 175", R76<200,"175 to 200", TRUE,"> 200" )} -> > 200 | T76: 220 | U76: 470 | V76: 113.64 | W76: {=_xlfn.IFS( V76<-15,"< -15%", V76<-10,"-15% to -10%", V76<-5,"-10% to -5%", V76<0,"-5% to 0%", V76<10,"0% to 10%", V76<20,"10% to 20%", V76<30,"20% to 30%", V76<40,"30% to 40%", V76<50,"40% to 50%", V76<60,"50% to 60%", V76<70,"60% to 70%", V76<80,"70% to 80%", V76<90,"80% to 90%", V76<100,"90% to 100%", TRUE,"> 100%" )} -> > 100% | X76: 954.75 | Y76: 955.3 | Z76: =IF(V76>0, ">0", IF(V76<0, "<0", "=0")) -> >0 | AA76: {=_xlfn.IFS( AND(O76>=0,O76<5),"0-5", AND(O76>=5,O76<15),"5-15", AND(O76>=15,O76<30),"15-30", AND(O76>=30,O76<60),"30-60", AND(O76>=60,O76<90),"60-90", AND(O76>=90,O76<120),"90-120", AND(O76>=120,O76<160),"120-160", AND(O76>=160,O76<200),"160-200", AND(O76>=200,O76<250),"200-250", AND(O76>=250,O76<300),"250-300", O76>=300,">300", TRUE,"Below 0" )} -> 250-300 | AB76: 333.98
A77: 45565 | B77: =TEXT(A77,"yyyy") -> 2024 | C77: Manba Finance Ltd | D77: =IFERROR(LEFT(C77,FIND(" ",C77)-1),C77) -> Manba | E77: =TRIM(SUBSTITUTE(SUBSTITUTE(C77,"Ltd",""),"Lt","")) -> Manba Finance | F77: =_xlfn.XLOOKUP(E77,MARKET_PRICE__2[Column2],MARKET_PRICE__2[Column3],"Not found") -> 134.50 | G77: =_xlfn.XLOOKUP(D77,MARKET_PRICE__2[Column12],MARKET_PRICE__2[Column3],"Not found") -> 134.50 | H77: 150.84 | I77: {=_xlfn.IFS( H77<50,"0-50", H77<100,"50-100", H77<150,"100-150", H77<200,"150-200", H77<250,"200-250", H77<300,"250-300", H77<350,"300-350", H77<400,"350-400", H77<450,"400-450", H77<=500,"450-500", TRUE,"Above 500" )} -> 150-200 | K77: =H77/10 -> 15.084 | N77: {=_xlfn.IFS(H77<500,"0-500",H77<1000,"500-1000",H77<1500,"1000-1500",H77<2000,"1500-2000",H77<2500,"2000-2500",H77<3000,"2500-3000",H77<3500,"3000-3500",H77<4000,"3500-4000",H77<4500,"4000-4500",H77<=5000,"4500-5000",TRUE,"Hbove 5000")} -> 0-500 | O77: 148.55 | P77: 511.62 | Q77: 143.95 | R77: 224.05 | S77: {=_xlfn.IFS( R77<0,"< 0", R77<5,"0 to 5", R77<10,"5 to 10", R77<15,"10 to 15", R77<20,"15 to 20", R77<25,"20 to 25", R77<50,"25 to 50", R77<75,"50 to 75", R77<100,"75 to 100", R77<125,"100 to 125", R77<150,"125 to 150", R77<175,"150 to 175", R77<200,"175 to 200", TRUE,"> 200" )} -> > 200 | T77: 120 | U77: 150 | V77: 25 | W77: {=_xlfn.IFS( V77<-15,"< -15%", V77<-10,"-15% to -10%", V77<-5,"-10% to -5%", V77<0,"-5% to 0%", V77<10,"0% to 10%", V77<20,"10% to 20%", V77<30,"20% to 30%", V77<40,"30% to 40%", V77<50,"40% to 50%", V77<60,"50% to 60%", V77<70,"60% to 70%", V77<80,"70% to 80%", V77<90,"80% to 90%", V77<100,"90% to 100%", TRUE,"> 100%" )} -> 20% to 30% | X77: 140.05 | Y77: 139.95 | Z77: =IF(V77>0, ">0", IF(V77<0, "<0", "=0")) -> >0 | AA77: {=_xlfn.IFS( AND(O77>=0,O77<5),"0-5", AND(O77>=5,O77<15),"5-15", AND(O77>=15,O77<30),"15-30", AND(O77>=30,O77<60),"30-60", AND(O77>=60,O77<90),"60-90", AND(O77>=90,O77<120),"90-120", AND(O77>=120,O77<160),"120-160", AND(O77>=160,O77<200),"160-200", AND(O77>=200,O77<250),"200-250", AND(O77>=250,O77<300),"250-300", O77>=300,">300", TRUE,"Below 0" )} -> 120-160 | AB77: 16.71
A78: 45559 | B78: =TEXT(A78,"yyyy") -> 2024 | C78: Arkade Developers | D78: =IFERROR(LEFT(C78,FIND(" ",C78)-1),C78) -> Arkade | E78: =TRIM(SUBSTITUTE(SUBSTITUTE(C78,"Ltd",""),"Lt","")) -> Arkade Developers | F78: =_xlfn.XLOOKUP(E78,MARKET_PRICE__2[Column2],MARKET_PRICE__2[Column3],"Not found") -> Not found | G78: =_xlfn.XLOOKUP(D78,MARKET_PRICE__2[Column12],MARKET_PRICE__2[Column3],"Not found") -> 165.90 | H78: 410 | I78: {=_xlfn.IFS( H78<50,"0-50", H78<100,"50-100", H78<150,"100-150", H78<200,"150-200", H78<250,"200-250", H78<300,"250-300", H78<350,"300-350", H78<400,"350-400", H78<450,"400-450", H78<=500,"450-500", TRUE,"Above 500" )} -> 400-450 | K78: =H78/10 -> 41 | N78: {=_xlfn.IFS(H78<500,"0-500",H78<1000,"500-1000",H78<1500,"1000-1500",H78<2000,"1500-2000",H78<2500,"2000-2500",H78<3000,"2500-3000",H78<3500,"3000-3500",H78<4000,"3500-4000",H78<4500,"4000-4500",H78<=5000,"4500-5000",TRUE,"Hbove 5000")} -> 0-500 | O78: 163.16 | P78: 163.02 | Q78: 51.39 | R78: 106.83 | S78: {=_xlfn.IFS( R78<0,"< 0", R78<5,"0 to 5", R78<10,"5 to 10", R78<15,"10 to 15", R78<20,"15 to 20", R78<25,"20 to 25", R78<50,"25 to 50", R78<75,"50 to 75", R78<100,"75 to 100", R78<125,"100 to 125", R78<150,"125 to 150", R78<175,"150 to 175", R78<200,"175 to 200", TRUE,"> 200" )} -> 100 to 125 | T78: 128 | U78: 175.9 | V78: 37.42 | W78: {=_xlfn.IFS( V78<-15,"< -15%", V78<-10,"-15% to -10%", V78<-5,"-10% to -5%", V78<0,"-5% to 0%", V78<10,"0% to 10%", V78<20,"10% to 20%", V78<30,"20% to 30%", V78<40,"30% to 40%", V78<50,"40% to 50%", V78<60,"50% to 60%", V78<70,"60% to 70%", V78<80,"70% to 80%", V78<90,"80% to 90%", V78<100,"90% to 100%", TRUE,"> 100%" )} -> 30% to 40% | X78: 183.1 | Y78: 183.05 | Z78: =IF(V78>0, ">0", IF(V78<0, "<0", "=0")) -> >0 | AA78: {=_xlfn.IFS( AND(O78>=0,O78<5),"0-5", AND(O78>=5,O78<15),"5-15", AND(O78>=15,O78<30),"15-30", AND(O78>=30,O78<60),"30-60", AND(O78>=60,O78<90),"60-90", AND(O78>=90,O78<120),"90-120", AND(O78>=120,O78<160),"120-160", AND(O78>=160,O78<200),"160-200", AND(O78>=200,O78<250),"200-250", AND(O78>=250,O78<300),"250-300", O78>=300,">300", TRUE,"Below 0" )} -> 160-200 | AB78: 43.05
A79: 45559 | B79: =TEXT(A79,"yyyy") -> 2024 | C79: Northern ARC Capit | D79: =IFERROR(LEFT(C79,FIND(" ",C79)-1),C79) -> Northern | E79: =TRIM(SUBSTITUTE(SUBSTITUTE(C79,"Ltd",""),"Lt","")) -> Northern ARC Capit | F79: =_xlfn.XLOOKUP(E79,MARKET_PRICE__2[Column2],MARKET_PRICE__2[Column3],"Not found") -> Not found | G79: =_xlfn.XLOOKUP(D79,MARKET_PRICE__2[Column12],MARKET_PRICE__2[Column3],"Not found") -> 165.00 | H79: 777 | J79: {=_xlfn.IFS( AND(H79>=500,H79<550),"500-550", AND(H79>=550,H79<600),"550-600", AND(H79>=600,H79<650),"600-650", AND(H79>=650,H79<700),"650-700", AND(H79>=700,H79<750),"700-750", AND(H79>=750,H79<800),"750-800", AND(H79>=800,H79<850),"800-850", AND(H79>=850,H79<900),"850-900", AND(H79>=900,H79<950),"900-950", AND(H79>=950,H79<=1000),"950-1000", H79<500,"Below 500", TRUE,"Above 1000" )} -> 750-800 | K79: =H79/10 -> 77.7 | N79: {=_xlfn.IFS(H79<500,"0-500",H79<1000,"500-1000",H79<1500,"1000-1500",H79<2000,"1500-2000",H79<2500,"2000-2500",H79<3000,"2500-3000",H79<3500,"3000-3500",H79<4000,"3500-4000",H79<4500,"4000-4500",H79<=5000,"4500-5000",TRUE,"Hbove 5000")} -> 500-1000 | O79: 240.79 | P79: 142.41 | Q79: 31.08 | R79: 110.91 | S79: {=_xlfn.IFS( R79<0,"< 0", R79<5,"0 to 5", R79<10,"5 to 10", R79<15,"10 to 15", R79<20,"15 to 20", R79<25,"20 to 25", R79<50,"25 to 50", R79<75,"50 to 75", R79<100,"75 to 100", R79<125,"100 to 125", R79<150,"125 to 150", R79<175,"150 to 175", R79<200,"175 to 200", TRUE,"> 200" )} -> 100 to 125 | T79: 263 | U79: 351 | V79: 33.46 | W79: {=_xlfn.IFS( V79<-15,"< -15%", V79<-10,"-15% to -10%", V79<-5,"-10% to -5%", V79<0,"-5% to 0%", V79<10,"0% to 10%", V79<20,"10% to 20%", V79<30,"20% to 30%", V79<40,"30% to 40%", V79<50,"40% to 50%", V79<60,"50% to 60%", V79<70,"60% to 70%", V79<80,"70% to 80%", V79<90,"80% to 90%", V79<100,"90% to 100%", TRUE,"> 100%" )} -> 30% to 40% | X79: 252.3 | Y79: 252.1 | Z79: =IF(V79>0, ">0", IF(V79<0, "<0", "=0")) -> >0 | AA79: {=_xlfn.IFS( AND(O79>=0,O79<5),"0-5", AND(O79>=5,O79<15),"5-15", AND(O79>=15,O79<30),"15-30", AND(O79>=30,O79<60),"30-60", AND(O79>=60,O79<90),"60-90", AND(O79>=90,O79<120),"90-120", AND(O79>=120,O79<160),"120-160", AND(O79>=160,O79<200),"160-200", AND(O79>=200,O79<250),"200-250", AND(O79>=250,O79<300),"250-300", O79>=300,">300", TRUE,"Below 0" )} -> 200-250 | AB79: -4.07
